Workbook

Sheet Locaçao Mensal
B1: CONTROLE UTILIZAÇÃO CARRO CORPORATIVO LOCAÇÕES MENSAIS - ATIVOS
A3: Legenda
A4: BARREIRAS | D4: NATAL
A5: BRASILIA | D5: RECIFE
A6: GARULHOS | D6: SÃO JOSE DO RIO PRETO
A7: AEROPORTO GOIANIA | D7: SOROCABA
A8: JUAZEIRO | D8: TERESINA
A9: LONDRINA | D9: PIRAJU
A10: PETROLINA | D10: SALVADOR
A11: FORTALEZA
A13: Quant | B13: RETIRADA | C13: PLACA | D13: CARRO | E13: Categoria | F13: DATA SUBS | G13: CARRO SUBS | H13: DATA SUBS2 | I13: CARRO SUBS2 | J13: DATA SUBS4 | K13: CARRO SUBS5 | L13: DATA ENCERRAMENTO | M13: STATUS | N13: USUARIO | O13: Obra | P13: CODIGO | Q13: LOCADORA | R13: LOCAL DE RETIRADA | S13: OBS | T13: KM CONTRATADO
A14: 1 | B14: 44135 | C14: QXA 8199 | D14: DUSTER | E14: Passeio | F14: 44260 | G14: DUSTER QXE 7794 | H14: 44303 | I14: RENEGADE RFW6A64 | M14: ATIVO | N14: ANDRE PLACIDO | O14: PARANAPANEMA | P14: 20022 | Q14: UNIDAS | R14: LONDRINA | S14: Foi entregue um veículo 4x2 devido não ter carro passeio no patio | T14: 6000KM
A15: 2 | B15: 44169 | C15: RFH5G63 | D15: TORO | E15: 4X2 | F15: 44552 | G15: TORO RNX0C53 | M15: ATIVO | N15: RICARDO TORUNSKY | O15: SGG | P15: 20003 | Q15: UNIDAS | R15: RECIFE | S15: Veículo chegou na cidade no final de semana e entrou no parque dia 07/12/ Carro passou para Ricardo em 17/01/2022 | T15: 6000KM
A16: 3 | B16: 44182 | C16: QYE 6085 | D16: TCROSS | E16: 4x2 | F16: 44344 | G16: TCROSS QYS7I76 | M16: ATIVO | N16: NATANAEL GRANGEIRO | O16: SGG | P16: 20003 | Q16: PARVI | R16: RECIFE | S16: Veículo não estava abastecido | T16: 5000KM
A17: 4 | B17: 44188 | C17: QYP3A76 | D17: TCROSS | E17: 4X2 | M17: ATIVO | N17: ALAIN SIQUEIRA | O17: SGG | P17: 20003 | Q17: PARVI | R17: RECIFE | S17: Veículo não estava abastecido | T17: 5000KM
A18: 5 | B18: 44262 | C18: RFY7G67 | D18: S10 | E18: 4X4 | F18: 44529 | G18: S10 RNS0F31 | M18: ATIVO | N18: AUGUSTO JAEGER | O18: SGG | P18: 20003 | Q18: UNIDAS | R18: TERESINA | S18: Veículo foi substituido pelo Marcos, devido a solicitação da Unidas | T18: 6000KM
A19: 6 | B19: 44286 | C19: QYR6C58 | D19: TORO | E19: 4X4 | M19: ATIVO | N19: ROBERTO FERREIRA | O19: SGG | P19: 20003 | Q19: PARVI | R19: RECIFE | S19: Passou para o Roberto em 28/12/2021 | T19: 5000KM
B20: 44293 | C20: RFJ5B90 | D20: RENEGADE | E20: 4X2 | L20: 44680 | M20: INATIVO | N20: JOAO CARLOS | O20: SGG | P20: 20003 | Q20: UNIDAS | R20: BRASILIA | S20: Veículo retirado pelo Iram e entregue no dia 08/04/ Carro passou para Joao em 17/01/2022 | T20: 3000KM
A21: 7 | B21: 44322 | C21: RME5J55 | D21: RENEGADE | E21: 4X2 | F21: 44463 | G21: TCROSS RFM4J87 | M21: ATIVO | N21: WESLEY | O21: SGG | P21: 20003 | Q21: UNIDAS | R21: BRASILIA | S21: Veículo retirado pelo iram e entregue dia 07/05 | T21: 3000KM
A22: 8 | B22: 44323 | C22: RML8I33 | D22: TRACKER | E22: 4X2 | M22: ATIVO | N22: JAMILLE | O22: DESAPROPRIAÇÃO | P22: 19011 | Q22: UNIDAS | R22: JUAZEIRO - BA | T22: 3000KM
A23: 9 | B23: 44332 | C23: RMP4D25 | D23: LOGAN | E23: Passeio | M23: ATIVO | N23: ESEQUIAS | O23: CUMARU | P23: 20013 | Q23: UNIDAS | R23: NATAL
A24: 11 | B24: 44340 | C24: QUD 8801 | D24: DUSTER | E24: 4X2 | F24: 44552 | G24: DUSTER RND2C46 | M24: ATIVO | N24: JOAO CARLOS | O24: SGG | P24: 20003 | Q24: UNIDAS | R24: BRASILIA | S24: Veículo estava com o André e repassado para a Melânia em 15/04 | T24: 3000KM
A25: 12 | B25: 44344 | C25: QYS2C06 | D25: TCROSS | E25: 4X2 | M25: ATIVO | N25: MELANIA | O25: SGG | P25: 20003 | Q25: PARVI | R25: BARREIRAS | S25: Veículo estava com o Jailton e repassado para o João em 27/04 | T25: 5000KM
A26: 13 | B26: 44344 | C26: QYT3B20 | D26: TCROSS | E26: 4X2 | M26: ATIVO | N26: RODRIGO MORILHO | O26: SGG | P26: 20003 | Q26: PARVI | R26: BARREIRAS | T26: 5000KM
A27: 14 | B27: 44345 | C27: QYS3A26 | D27: TCROSS | E27: 4X2 | M27: ATIVO | N27: LUCAS RIBEIRO | O27: SGG | P27: 20003 | Q27: PARVI | R27: BARREIRAS | T27: 5000KM
A28: 15 | B28: 44345 | C28: QYS7J36 | D28: TCROSS | E28: 4X2 | M28: ATIVO | N28: JONATHAN | O28: SGG | P28: 20003 | Q28: PARVI | R28: BARREIRAS | T28: 5000KM
A29: 16 | B29: 44345 | C29: QYS7J86 | D29: TCROSS | E29: 4X2 | M29: ATIVO | N29: MARCO ANTONIO | O29: SGG | P29: 20003 | Q29: PARVI | R29: BARREIRAS | T29: 5000KM
A30: 17 | B30: 44506 | C30: RNY0D96 | D30: S10 | E30: 4X4 | M30: ATIVO | N30: JOELSON | O30: SGG | P30: 20003 | Q30: UNIDAS | R30: TERESINA | S30: Retirado pelo Iram em 06/11 e entregue ao Joelson em 07/11/2021
A31: 18 | B31: 44568 | C31: RFL8J66 | D31: UNO | E31: Passeio | F31: 44575 | G31: ONIX RFZ7I71 | M31: ATIVO | N31: WARLEY | O31: AEROPORTO GOIANIA | P31: 21029 | Q31: UNIDAS | R31: GOIANIA
A32: 19 | B32: 44568 | C32: RFL8500 | D32: UNO | E32: Passeio | F32: 44575 | G32: ARGO RFH6B50 | M32: ATIVO | N32: PEDRO | O32: AEROPORTO GOIANIA | P32: 21029 | Q32: UNIDAS | R32: GOIANIA
A33: 20 | B33: 44573 | C33: RFV6A52 | D33: ONIX | E33: Passeio | F33: 44582 | G33: FORD KA QXV5E41 | H33: 44583 | I33: ARGO RTE1I62 | M33: ATIVO | N33: GLEISON | O33: AEROPORTO GOIANIA | P33: 21029 | Q33: UNIDAS | R33: GOIANIA
A34: 21 | B34: 44578 | C34: RFG4F42 | D34: ARGO | E34: Passeio | M34: ATIVO | N34: RAINOR | O34: AEROPORTO GOIANIA | P34: 21029 | Q34: UNIDAS | R34: GOIANIA
B35: 44591 | C35: RFY5F27 | D35: RENEGADE | E35: 4x2 | L35: 44691 | M35: INATIVO | N35: JANE | O35: TERESINA | P35: 20003 | Q35: UNIDAS | R35: TERESINA
A36: 22 | B36: 44612 | C36: RNB2F48 | D36: RENEGADE | E36: 4X2 | M36: ATIVO | N36: ANNE | O36: AVALIAÇÕES | P36: 22005 | Q36: UNIDAS | R36: RECIFE
A37: 23 | B37: 44621 | C37: RTQ1E09 | D37: HB20 | E37: Passeio | M37: ATIVO | N37: JOSE LEONARDO | O37: AROEIRA | P37: 22006 | Q37: UNIDAS | R37: JUAZEIRO - BA
A38: 24 | B38: 44622 | C38: RFE4D91 | D38: ARGO | E38: Passeio | M38: ATIVO | N38: ADEILSON | O38: AROEIRA | P38: 22006 | Q38: UNIDAS | R38: JUAZEIRO - BA
A39: 25 | B39: 44625 | C39: RNS5H28 | D39: S10 | E39: 4X4 | M39: ATIVO | N39: RAIMUNDO GERSON | O39: LAGOA | P39: 22007 | Q39: UNIDAS | R39: RECIFE | S39: Carro foi retirado por Gerardo e entregue ao Raimundo em 07/03
A40: 26 | B40: 44627 | C40: RT03A77 | D40: C4 | E40: 4X2 | F40: 44679 | G40: RENEGADE RMQ4B22 | M40: ATIVO | N40: THAIS MEDEIROS | O40: LAGOA | P40: 22007 | Q40: UNIDAS | R40: JUAZEIRO - BA
A41: 27 | B41: 44629 | C41: RFK1H13 | D41: RENEGADE | E41: 4x2 | M41: ATIVO | N41: DIOSTENES | O41: AROEIRA | P41: 22006 | Q41: UNIDAS | R41: AEROPORTO SALVADOR | S41: Carro retirado no dia 09/03 pelo Rodrigo e passado para o Diostenes dia 21/03
A42: 28 | B42: 44628 | C42: RNR1J89 | D42: S10 | E42: 4X4 | M42: ATIVO | N42: DOUGLAS BOSCHETTI | O42: AROEIRA | P42: 22006 | Q42: UNIDAS | R42: NATAL PONTA NEGRA
A43: 29 | B43: 44633 | C43: RTL1H00 | D43: FRONTIER | E43: 4X4 | M43: ATIVO | N43: ERIKA LIMA | O43: AROEIRA | P43: 22006 | Q43: UNIDAS | R43: AEROPORTO FORTALEZA
A44: 0 | B44: 44635 | C44: RFN5J89 | D44: GOL | E44: Passeio | M44: ATIVO | N44: ROBERTA MELO | O44: AROEIRA | P44: 22006 | Q44: UNIDAS | R44: JUAZEIRO - BA | S44: Veículo foi retirado por Gerardo
A45: 31 | B45: 44638 | C45: RMJ6B95 | D45: L200 | E45: 4X4 | F45: 44694 | G45: RMJ6B77 | M45: ATIVO | N45: JOSE ERIVAM | O45: AROEIRA | P45: 22006 | Q45: UNIDAS | R45: AEROPORTO SALVADOR
A46: 32 | B46: 44639 | C46: RNR4A65 | D46: S10 | E46: 4X4 | M46: ATIVO | N46: RODRIGO ROLDAO | O46: AROEIRA | P46: 22006 | Q46: UNIDAS | R46: AEROPORTO SALVADOR
A47: 33 | B47: 44640 | C47: RNA2B29 | D47: ARGO | E47: Passeio | M47: ATIVO | N47: GEORGE ANUNCIAÇÃO | O47: AROEIRA | P47: 22006 | Q47: UNIDAS | R47: AEROPORTO SALVADOR
A48: 34 | B48: 44644 | C48: RTR7B21 | D48: FRONTIER | E48: 4X4 | M48: ATIVO | N48: CLAUDIO AMARAL | O48: LAGOA | P48: 22007 | Q48: MOVIDA | R48: PETROLINA
A49: 35 | B49: 44650 | C49: RFT0F81 | D49: UNO | E49: Passeio | M49: ATIVO | N49: JOSE SANTANA | O49: LAGOA | P49: 22007 | Q49: MOVIDA | R49: PETROLINA
A50: 36 | B50: 44655 | C50: RMY5D97 | D50: UNO | E50: Passeio | M50: ATIVO | N50: JOAO ADRIANO | O50: AROEIRA | P50: 22006 | Q50: MOVIDA | R50: PETROLINA
A51: 37 | B51: 44657 | C51: RTF8B01 | D51: C4 | E51: 4X2 | M51: ATIVO | N51: ALIRE | O51: AROEIRA | P51: 22006 | Q51: MOVIDA | R51: PETROLINA
A52: 38 | B52: 44662 | C52: RMX8B76 | D52: CRETA | E52: 4X2 | M52: ATIVO | N52: ARTHUR | O52: LAGOA | P52: 22007 | Q52: MOVIDA | R52: PETROLINA
A53: 39 | B53: 44668 | C53: RNI8E63 | D53: CRETA | E53: 4X2 | M53: ATIVO | N53: RITA MERCIA | O53: AROEIRA | P53: 22006 | Q53: MOVIDA | R53: PETROLINA | S53: Veículo retirado pelo Diogo e repassado para a Rita em 03/05
A54: 40 | B54: 44666 | C54: QGM7F17 | D54: CRETA | E54: 4x2 | M54: ATIVO | N54: TACIO SILVA | O54: LAGOA | P54: 22007 | Q54: LOCAÇÃO COLABORADOR | R54: LOCAÇÃO COLABORADOR
A55: 41 | B55: 44666 | C55: PKE9B77 | D55: ONIX | E55: Passeio | M55: ATIVO | N55: IAGO ALVES | O55: LAGOA | P55: 22007 | Q55: LOCAÇÃO COLABORADOR | R55: LOCAÇÃO COLABORADOR
A56: 42 | B56: 44669 | C56: RNH5H36 | D56: C4 | E56: 4X2 | M56: ATIVO | N56: GERMANO | O56: LAGOA | P56: 22007 | Q56: MOVIDA | R56: PETROLINA
A57: 43 | B57: 44669 | C57: RNX3G48 | D57: C4 | E57: 4X2 | M57: ATIVO | N57: LOURIVAL | O57: LAGOA | P57: 22007 | Q57: MOVIDA | R57: PETROLINA
A58: 44 | B58: 44669 | C58: RMJ6B94 | D58: L200 | E58: 4X4 | M58: ATIVO | N58: WANDERSON CARVALHO | O58: AROEIRA | P58: 22006 | Q58: UNIDAS | R58: JUAZEIRO - BA
A59: 45 | B59: 44669 | C59: RMY2A10 | D59: RENEGADE | E59: 4X2 | M59: ATIVO | N59: FRANCISMAR | O59: SGG | P59: 20003 | Q59: MOVIDA | R59: BRASILIA
A60: 46 | B60: 44670 | C60: RNN1G70 | D60: C4 | E60: 4X2 | M60: ATIVO | N60: LAUREANE | O60: LAGOA | P60: 22007 | Q60: MOVIDA | R60: PETROLINA
A61: 47 | B61: 44670 | C61: RMX9C96 | D61: CRETA | E61: 4X2 | M61: ATIVO | N61: ANDERSON | O61: LAGOA | P61: 22007 | Q61: MOVIDA | R61: PETROLINA
A62: 48 | B62: 44670 | C62: RTB9A55 | D62: CRETA | E62: 4X2 | F62: 44686 | G62: C4 RNZ8IEE | H62: 44696 | I62: RENEGADE RNM2B33 | M62: ATIVO | N62: LAILLA MACEDO | O62: LAGOA | P62: 22007 | Q62: MOVIDA | R62: PETROLINA
A63: 49 | B63: 44672 | C63: RNJ1A38 | D63: 2008 | E63: 4X2 | M63: ATIVO | N63: ZULMIRA LOPES | O63: LAGOA | P63: 22007 | Q63: MOVIDA | R63: PETROLINA
A64: 50 | B64: 44672 | C64: RTF8B05 | D64: C4 | E64: 4X2 | M64: ATIVO | N64: FRANSLEY | O64: LAGOA | P64: 22007 | Q64: MOVIDA | R64: PETROLINA
A65: 51 | B65: 44672 | C65: RNZ8IEE | D65: C4 | E65: 4X2 | F65: 44679 | G65: CRETA RMX9C94 | M65: ATIVO | N65: ADRIANA | O65: LAGOA | P65: 22007 | Q65: MOVIDA | R65: PETROLINA
A66: 52 | B66: 44673 | C66: RTF8C37 | D66: S10 | E66: 4X4 | M66: ATIVO | N66: ALEXANDRE MADEIRA | O66: AROEIRA | P66: 22006 | Q66: MOVIDA | R66: NATAL AEROPORTO
A67: 53 | B67: 44676 | C67: RTM3E71 | D67: 2008 | E67: 4X2 | M67: ATIVO | N67: JOSE MARIA | O67: LAGOA | P67: 22007 | Q67: MOVIDA | R67: PETROLINA
A68: 54 | B68: 44673 | C68: QQN 8382 | D68: C4 | E68: 4X2 | F68: 44691 | G68: C4 RTU8E36 | M68: ATIVO | N68: BRUNO SIVOLELLA | O68: SGG | P68: 20003 | Q68: LOCALIZA | R68: BARREIRAS
A69: 55 | B69: 44673 | C69: RMW 0J55 | D69: C4 | E69: 4X2 | F69: 44677 | G69: DUSTER RMQ4C87 | M69: ATIVO | N69: GUILHERME GODOIS | O69: SGG | P69: 20003 | Q69: LOCALIZA | R69: BARREIRAS
A70: 56 | B70: 44684 | C70: QYX6C91 | D70: CRETA | E70: 4X2 | M70: ATIVO | N70: THAIS VANDERLEI | O70: AROEIRA | P70: 22006 | Q70: LOCAÇÃO COLABORADOR | R70: LOCAÇÃO COLABORADOR
A71: 57 | B71: 44686 | C71: RMH0B14 | D71: S10 | E71: 4x4 | M71: ATIVO | N71: ADENILTON | O71: AROEIRA | P71: 22006 | Q71: UNIDAS | R71: SALVADOR
A72: 58 | B72: 44687 | C72: RTZ9A27 | D72: L200 | E72: 4X4 | M72: ATIVO | N72: VALMIR | O72: LAGOA | P72: 22007 | Q72: MOVIDA | R72: PETROLINA
A73: 59 | B73: 44694 | C73: RND2C28 | D73: DUSTER | E73: 4X2 | M73: ATIVO | N73: ANDRE AMARAL | O73: AROEIRA | P73: 22006 | Q73: UNIDAS | R73: SALVADOR
A74: 60 | B74: 44697 | C74: RTL5A64 | D74: FRONTIER | E74: 4X4 | M74: ATIVO | N74: DIOGO TANILLE | O74: AROEIRA | P74: 22006 | Q74: MOVIDA | R74: PETROLINA

Sheet Locação Mensal
A1: GESTÃO DE FROTAS
A2: CONTROLE GERAL DE VEÍCULOS - ATIVOS E INATIVOS
A3: Quant | B3: STATUS | C3: OBRA | D3: CÓDIGO | E3: RETIRADA | F3: USUARIO | G3: LOCAL | H3: PLACA | I3: CARRO | J3: CARRO COM RASTREADOR | K3: CATEGORIA | L3: TESTE FUMAÇA PRETA | M3: DATA TESTE DE FUMAÇA PRETA | N3: LOCADORA | O3: DATA 1ª SUBS | P3: MODELO | Q3: DATA 2ª SUBS | R3: MODELO2 | S3: DATA 3 SUBS | T3: MODELO3 | U3: DATA 4ª SUBS | V3: MODELO4 | W3: DATA 5ª SUBS2 | X3: MODELO6 | Y3: DATA 6ª SUBS22 | Z3: MODELO7 | AA3: DATA ENCERRAMENTO | AB3: KM CONTRATADO | AC3: LOCAL DE RETIRADA | AD3: OBS
A4: 1 | B4: INATIVO | C4: MAPEAMENTO | D4: 22005 | E4: 44323 | F4: RENATA | G4: JUAZEIRO | H4: RML8I33 | I4: TRACKER | J4: SIM | K4: 4X2 | L4: NÃO | M4: NÃO | N4: LOCALIZA | O4: 44895 | P4: TCROSS ENI9F24 | Q4: 44990 | AA4: 45401 | AB4: 3000 | AC4: JUAZEIRO - BA | AD4: Veículo migrado para a Localiza. Repasse para Renata em 24/03/2023. Condutora antiga Jamille. Dia 19/01/2024 Renata repassou o veiculo para Jamille
A5: 2 | B5: INATIVO | C5: GOIANIA | D5: 21029 | E5: 44568 | F5: PEDRO | G5: GOIANIA | H5: RFL8J66 | I5: UNO | J5: NÃO | K5: Passeio | L5: NÃO | M5: NÃO | N5: UNIDAS | O5: 44575 | P5: ONIX RFZ7I71 | Q5: 44798 | R5: ARGO RUM5I29 | S5: 45154 | T5: ARGO RGD4F42 | AA5: 45163 | AB5: 3000 | AC5: GOIANIA
A6: 284 | B6: INATIVO | C6: AUREN | D6: 25001 | E6: 45714 | F6: ALAIN | G6: PONTA NEGRA | H6: TDP1E16 | I6: S10 | J6: SIM | K6: 4X4 | L6: SIM | M6: 46086 | N6: UNIDAS | AA6: 46112 | AB6: 3000 | AC6: PONTA NEGRA - RN | AD6: Uso particular carnaval 28/02 a 05/03/2025
A7: 111. | B7: ATIVO | C7: SUSTENTABILIDADE | D7: 24006 | E7: 45384 | F7: ALIRE CAVALCANTE | G7: SALVADOR | H7: EGK2E03 | I7: TCROSS | J7: SIM | K7: 4X2 | L7: NÃO | M7: NÃO | N7: UNIDAS | O7: 45883 | P7: Tracker TEL5D67 | Q7: 46088 | R7: Tracker TEL2B29 | AB7: 3000 | AC7: SALVADOR - BA
A8: 5 | B8: INATIVO | C8: AROEIRA | D8: 22006 | E8: 44621 | F8: ROBERTA MELO | G8: JUAZEIRO | H8: RTQ1E09 | I8: HB20 | J8: SIM | K8: Passeio | L8: NÃO | M8: NÃO | N8: LOCALIZA | AA8: 45129 | AB8: 3000 | AC8: JUAZEIRO - BA | AD8: Veículo migrado para a Localiza
A9: 6 | B9: INATIVO | C9: LAGOA | D9: 22007 | E9: 44625 | F9: RAIMUNDO GERSON | G9: RECIFE | H9: RNS5H28 | I9: S10 | J9: SIM | K9: 4X4 | L9: NÃO | N9: UNIDAS | O9: 45012 | P9: S10 RVS1B18 | AA9: 45331 | AB9: 6000 | AC9: RECIFE | AD9: Carro foi retirado por Gerardo e entregue ao Raimundo em 07/03
A10: 7 | B10: INATIVO | C10: LAGOA | D10: 22007 | E10: 44627 | F10: CONTIGÊNCIA QUALIDADE | G10: JUAZEIRO | H10: RT03A77 | I10: C4 | J10: SIM | K10: 4X2 | L10: NÃO | M10: NÃO | N10: LOCALIZA | O10: 44679 | P10: RENEGADE RMQ4B22 | Q10: 44946 | R10: RENEGADE RUY6G80 | S10: 44966 | T10: TRACKER RUW4B73 | U10: 44993 | V10: TRACKER RUX6E92 | W10: 45134 | X10: RENEGADE RVF2B30 | Y10: 45141 | Z10: RVH2E00 TRACKER | AA10: 45184 | AB10: 3000 | AC10: JUAZEIRO - BA | AD10: Veículo sofreu sinistro no dia 15/02/2023 e foi retirada um em substituição apenas em 08/03/2023
A11: 8 | B11: INATIVO | C11: AROEIRA | D11: 22006 | E11: 44640 | F11: LUCAS | G11: SALVADOR | H11: RNA2B29 | I11: ARGO | J11: CARRO INATIVO | K11: Passeio | L11: NÃO | M11: NÃO | N11: UNIDAS | O11: 44728 | P11: VOYAGE GBK0J65 | AA11: ?? | AB11: 3000 | AC11: AEROPORTO SALVADOR | AD11: Veículo do George foi entregue no lugar do veículo do Lucas
A12: 9 | B12: INATIVO | C12: AROEIRA | D12: 22006 | E12: 44694 | F12: CAIO / ROBERTA MELO / CHICÃO | G12: SALVADOR | H12: RND2C28 | I12: DUSTER | J12: NÃO | K12: 4X2 | L12: NÃO | M12: NÃO | N12: UNIDAS | O12: 44756 | P12: RENEGADE RUF4J65 | Q12: 45059 | R12: HB20X RNU4G47 | AA12: 45222 | AB12: 4500 | AC12: SALVADOR | AD12: Veículo era do Andre e foi repassado ao Douglas, com saída do Douglas, foi passado ao Caio. DIA 25/09 FOI REPASSADO O CARRO PRA CHICAO
A13: 10 | B13: INATIVO | C13: PROJETOS CEARA | D13: 22004 | E13: 44750 | F13: ROGERIO | G13: FORTALEZA | H13: RFQ0178 | I13: ARGO | J13: NÃO | K13: Passeio | L13: NÃO | M13: NÃO | N13: LOCALIZA | O13: 45240 | P13: ARGO RNF0E22 | AA13: 45162 | AB13: 5000
A14: 11 | B14: INATIVO | C14: MAPEAMENTO | D14: 22005 | E14: 44753 | F14: SUIANNE | G14: RECIFE | H14: RUL4E12 | I14: CRETA | J14: NÃO | K14: 4X2 | L14: NÃO | M14: NÃO | N14: LOCALIZA | O14: 44769 | P14: C4 RNZ1C32 | Q14: 45118 | R14: PULSE SHB4H30 | AA14: 45310 | AB14: 4000 | AC14: RECIFE | AD14: Veiculo utilizado por Anne, repassado para Suianne no dia 23/01/2023
A15: 12 | B15: INATIVO | C15: LAGOA | D15: 22007 | E15: 44758 | F15: PAULO | G15: PICOS | H15: RTA2A27 | I15: RENEGADE | J15: CARRO INATIVO | K15: 4X2 | L15: NÃO | M15: NÃO | N15: LOCALIZA | AA15: 45045 | AB15: 5000 | AC15: PICOS
A16: 13 | B16: INATIVO | C16: LAGOA | D16: 22007 | E16: 44758 | F16: ALDEMIR | G16: SALVADOR | H16: RNU6J01 | I16: S10 | J16: SIM | K16: 4X4 | L16: NÃO | N16: LOCALIZA | O16: 44878 | P16: VOYAGE GBK0J65 | Q16: 44971 | R16: L200 RUK9G41 | AA16: 45142 | AB16: 5000 | AC16: SALVADOR | AD16: Veículo foi repassado para a obra de Lagoa em 14/02/2023
A17: 14 | B17: INATIVO | C17: LAGOA | D17: 22007 | E17: 44758 | F17: VALMIR | G17: PICOS | H17: RGC2G70 | I17: S10 | J17: SIM | K17: 4X4 | L17: NÃO | N17: LOCALIZA | O17: 45213 | P17: C4 RFZ1A35 | Q17: 44855 | R17: RTX9C83 S10 | AA17: 45076 | AB17: 5000 | AC17: PICOS | AD17: Veículo foi entregue em Petrolina, devido a precisar ter sido entregue o carro em Petrolina, impossibilitando a logistica até Picos
A18: 15 | B18: INATIVO | C18: LAGOA | D18: 22007 | E18: 44758 | F18: CLAUDIO AMARAL | G18: PICOS | H18: RFZ3C18 | I18: S10 | J18: SIM | K18: 4X4 | L18: NÃO | N18: LOCALIZA | O18: 44868 | P18: S10 RNY7D61 | Q18: 44946 | R18: RTF5A73 S10 | AA18: 45071 | AB18: 5000 | AC18: PICOS | AD18: Veículo foi entregue em Petrolina, devido a precisar ter sido entregue o carro em Petrolina, impossibilitando a logistica até Picos
A19: 16 | B19: INATIVO | C19: LAGOA | D19: 22007 | E19: 44765 | F19: FABIN | G19: PICOS | H19: RUM5D82 | I19: KICKS | J19: SIM | K19: 4X2 | L19: NÃO | M19: NÃO | N19: LOCALIZA | O19: 44874 | P19: C4 RMT8A08 | AA19: 45110 | AB19: 5000 | AC19: PICOS | AD19: Veículo foi entregue em Petrolina, devido a precisar ter sido entregue o carro em Petrolina, impossibilitando a logistica até Picos. Veículo foi passado para o Fabin, com a saída do Arthur.
A20: 17 | B20: INATIVO | C20: LAGOA | D20: 22007 | E20: 44765 | F20: EIDER BRENO | G20: PICOS | H20: RFY4F46 | I20: RENEGADE | J20: CARRO INATIVO | K20: 4X2 | L20: NÃO | M20: NÃO | N20: LOCALIZA | AA20: 45033 | AB20: 5000 | AC20: PICOS | AD20: Veículo foi entregue em Petrolina, devido a precisar ter sido entregue o carro em Petrolina, impossibilitando a logistica até Picos/ Veículo repasso para o Breno em 14/11/2022
A21: 18 | B21: INATIVO | C21: AROEIRA | D21: 22006 | E21: 44767 | F21: ALIRE | G21: FEIRA DE SANTANA | H21: RUH2D55 | I21: C4 | J21: CARRO INATIVO | K21: 4x2 | L21: NÃO | M21: NÃO | N21: LOCALIZA | AA21: 45033 | AB21: 3000 | AC21: FEIRA DE SANTANA | AD21: Veículo retirado pelo Augusto e Gerardo
A22: 19 | B22: INATIVO | C22: AROEIRA | D22: 22006 | E22: 44767 | F22: ALVARO | G22: FEIRA DE SANTANA | H22: RGC2G78 | I22: S10 | J22: SIM | K22: 4X4 | L22: NÃO | N22: LOCALIZA | O22: 44828 | P22: RUZ0D64 L200 | AA22: 45087 | AB22: 5000 | AC22: FEIRA DE SANTANA | AD22: Veículo retirado pelo Antonio, entregue ao Jose Erivan e em novembro repassado para Rita, CARRO PASSADO PARA ALVARO
A23: 20 | B23: INATIVO | C23: AROEIRA | D23: 22006 | E23: 44769 | F23: GIVALDO | G23: FEIRA DE SANTANA | H23: QWR9447 | I23: S10 | J23: SIM | K23: 4X2 | L23: NÃO | M23: NÃO | N23: LOCALIZA | O23: 44898 | P23: RVD3B25 RENEGADE | AA23: 45068 | AB23: 5000 | AC23: FEIRA DE SANTANA | AD23: Devido a indisponibilidade do veículo do grupo foi entregue um superior
A24: 21 | B24: INATIVO | C24: LAGOA | D24: 22007 | E24: 44779 | F24: NADSON | G24: PICOS | H24: RTN8C48 | I24: RENEGADE | J24: SIM | K24: 4X2 | L24: NÃO | M24: NÃO | N24: LOCALIZA | O24: 44903 | P24: RTN8D64 RENEGADE | Q24: 45010 | R24: RTA4H88 RENEGADE | AA24: 45114 | AB24: 3000 | AC24: PICOS
A25: 22 | B25: INATIVO | C25: AROEIRA | D25: 22006 | E25: 44794 | F25: GEORGE ANUNCIAÇÃO | G25: SALVADOR | H25: RUN6D05 | I25: PEUGEOT | J25: NÃO | K25: Passeio | L25: NÃO | M25: NÃO | N25: LOCALIZA | AA25: 45055 | AB25: 3000 | AC25: SALVADOR | AD25: Veículo passou para George em 29/03/2023
A26: 23 | B26: INATIVO | C26: LAGOA | D26: 22007 | E26: 44807 | F26: KLEBER | G26: SALVADOR | H26: RUO8I29 | I26: HILUX | J26: CARRO INATIVO | K26: 4X4 | L26: NÃO | N26: LOCALIZA | AA26: 45050 | AB26: 5000 | AC26: SALVADOR
A27: 24 | B27: INATIVO | C27: AROEIRA | D27: 22006 | E27: 44810 | F27: MICHEL | G27: PICOS | H27: RTM7E34 | I27: HB20 | J27: SIM | K27: Passeio | L27: NÃO | M27: NÃO | N27: LOCALIZA | O27: 45014 | P27: RUX4D45 HB20 | AA27: 45188 | AB27: 5000 | AC27: PICOS
A28: 25 | B28: INATIVO | C28: LAGOA | D28: 22007 | E28: 44810 | F28: MARCONIS FRANCISCO EDILSON | G28: PICOS | H28: RFZ4B11 | I28: RENEGADE | J28: SIM | K28: 4X2 | L28: NÃO | M28: NÃO | N28: LOCALIZA | O28: 44820 | P28: RENEGADE RNZ5J61 | Q28: 44924 | R28: RENEGADE RUX1H96 | S28: 45097 | T28: RENEGADE SHY2C77 | AA28: 45334 | AB28: 5000 | AC28: PICOS
A29: 26 | B29: INATIVO | C29: LAGOA | D29: 22007 | E29: 44830 | F29: ARLEN | G29: PICOS | H29: RTA2B45 | I29: RENEGADE | J29: NÃO | K29: 4X2 | L29: NÃO | M29: NÃO | N29: LOCALIZA | O29: 44872 | P29: RENEGADE RUX0H17 | AA29: 45069 | AB29: 5000
A30: 27 | B30: INATIVO | C30: AROEIRA | D30: 22006 | E30: 44834 | F30: DEVALDO | G30: FEIRA DE SANTANA | H30: RUH9C37 | I30: CRONOS | J30: SIM | K30: Passeio | L30: NÃO | M30: NÃO | N30: UNIDAS | AA30: 45199 | AB30: 4500 | AC30: FEIRA DE SANTANA | AD30: Veículo foi repassado para o Joao Adriano
A31: 28 | B31: INATIVO | C31: HORIZONTE | D31: 22035 | E31: 44849 | F31: JOSE SANTANA | G31: BARREIRAS | H31: RVA2C75 | I31: ARGO | J31: CARRO INATIVO | K31: Passeio | L31: NÃO | M31: NÃO | N31: LOCALIZA | AA31: 45033 | AB31: 3000 | AC31: BARREIRAS
A32: 29 | B32: INATIVO | C32: HORIZONTE | D32: 22035 | E32: 44851 | F32: ADEMIR | G32: BARREIRAS | H32: RTY9H03 | I32: HB20 | J32: NÃO | K32: Passeio | L32: NÃO | M32: NÃO | N32: LOCALIZA | AA32: 45091 | AB32: 3000 | AC32: BARREIRAS
A33: 30 | B33: INATIVO | C33: AROEIRA | D33: 22006 | E33: 44859 | F33: ANDRE AMARAL | G33: SALVADOR | H33: RUX1I22 | I33: GOL | J33: CARRO INATIVO | K33: Passeio | L33: NÃO | M33: NÃO | N33: UNIDAS | AA33: 45019 | AB33: 4500 | AC33: SALVADOR | AD33: Veículo estava com Maria Luiza e foi devolvido no lugar do veículo do Andre
A34: 31 | B34: INATIVO | C34: AROEIRA | D34: 22006 | E34: 44863 | F34: MARIA LUIZA / GILVALDO | G34: FEIRA DE SANTANA | H34: RUL2D73 | I34: CRONOS | J34: SIM | K34: Passeio | L34: NÃO | M34: NÃO | N34: UNIDAS | AA34: 45103 | AB34: 4500 | AC34: FEIRA DE SANTANA | AD34: Veículo retirado pelo Antonio (Chicão) / Veículo repassado para Maria Luiza em 31/03/2023
A35: 32 | B35: INATIVO | C35: LAGOA | D35: 22007 | E35: 44866 | F35: BRAZ | G35: JUAZEIRO | H35: RFUD7D97 | I35: VIRTUS | J35: SIM | K35: Passeio | L35: NÃO | M35: NÃO | N35: UNIDAS | O35: 44884 | P35: GOL SDX5H38 | AA35: 45133 | AB35: 4500 | AC35: JUAZEIRO - BA
A36: 33 | B36: INATIVO | C36: AROEIRA | D36: 22006 | E36: 44871 | F36: RITA MERCIA / MARIA LUIZA | G36: SALVADOR | H36: RNX9A67 | I36: RENEGADE | J36: SIM | K36: 4X2 | L36: NÃO | M36: NÃO | N36: UNIDAS | O36: 45059 | P36: 208 SHS9A71 | AA36: 45189 | AB36: 4500 | AC36: SALVADOR | AD36: Veículo retirado pelo George, Carro esta sendo utilizado por RITA MERCIA
A37: 34 | B37: INATIVO | C37: LAGOA | D37: 22007 | E37: 44877 | F37: THAIS/ CLAUDIO | G37: PICOS | H37: RUE9A65 | I37: RENEGADE | J37: SIM | K37: 4X2 | L37: NÃO | M37: NÃO | N37: LOCALIZA | O37: 45098 | P37: RENEGADE RNZ5J33 | AA37: 45113 | AB37: 5000 | AC37: PICOS
A38: 35 | B38: INATIVO | C38: LAGOA | D38: 22007 | E38: 44894 | F38: EDILSON /CLAUDIO AMARAL | G38: PICOS | H38: RUY1D37 | I38: RENEGADE | J38: SIM | K38: 4X2 | L38: NÃO | M38: NÃO | N38: LOCALIZA | O38: 45112 | P38: RVH2E00 TRACKER | Q38: 45141 | R38: RENEGADE RVF2B30 | AA38: 45229 | AB38: 5000 | AC38: PICOS
A39: 36 | B39: INATIVO | C39: SGG | D39: 20003 | E39: 44898 | F39: JONATHAN | G39: BARREIRAS | H39: RVL0A39 | I39: TRACKER | J39: NÃO | K39: 4X2 | L39: NÃO | M39: NÃO | N39: LOCALIZA | AA39: 45031 | AB39: 4000 | AC39: BARREIRAS
A40: 37 | B40: INATIVO | C40: HORIZONTE | D40: 22035 | E40: 44905 | F40: SAMIRA | G40: BARREIRAS | H40: RNE0B60 | I40: ARGO | J40: CARRO INATIVO | K40: Passeio | L40: NÃO | M40: NÃO | N40: LOCALIZA | AA40: 45044 | AB40: 3000 | AC40: BARREIRAS
A41: 38 | B41: INATIVO | C41: AROEIRA | D41: 22006 | E41: 44905 | F41: LAERCIO | G41: SALVADOR | H41: RVH8G52 | I41: C3 | J41: SIM | K41: Passeio | L41: NÃO | M41: NÃO | N41: LOCALIZA | AA41: 45087 | AB41: 5000 | AC41: SALVADOR
A42: 39 | B42: INATIVO | C42: AROEIRA | D42: 22006 | E42: 44912 | F42: ADENILTON | G42: FEIRA DE SANTANA | H42: RVR4H76 | I42: ARGO | J42: CARRO INATIVO | K42: Passeio | L42: NÃO | M42: NÃO | N42: LOCALIZA | AA42: 45054 | AB42: 5000 | AC42: FEIRA DE SANTANA | AD42: Veículo retirado pelo Antonio, Carro devolvido
A43: 40 | B43: INATIVO | C43: LAGOA | D43: 22007 | E43: 44914 | F43: IRMA MACEDO / HERMES XAVIER | G43: JUAZEIRO | H43: SDW7B57 | I43: PULSE | J43: SIM | K43: 4X2 | L43: NÃO | M43: NÃO | N43: UNIDAS | AA43: 45231 | AB43: 4500 | AC43: JUAZEIRO - BA | AD43: Carro repassado para Hermes e Samila dia 15/09/2023. Utilizado também como carro de contingência.
A44: 41 | B44: INATIVO | C44: HORIZONTE | D44: 22035 | E44: 44929 | F44: TAUAN | H44: RP09A13 | I44: HB20 | J44: CARRO INATIVO | K44: Passeio | L44: NÃO | M44: NÃO | N44: AGREGADO | AA44: 45032 | AB44: ILIMITADO | AC44: -
A45: 42 | B45: INATIVO | C45: AROEIRA | D45: 22006 | E45: 44930 | F45: DIOGO TANILLE | G45: FEIRA DE SANTANA | H45: RNE3H34 | I45: ARGO | J45: SIM | K45: Passeio | L45: NÃO | M45: NÃO | N45: UNIDAS | AA45: 45111 | AB45: 4500 | AC45: FEIRA DE SANTANA | AD45: Veículo retirado pelo Augusto
A46: 43 | B46: INATIVO | C46: LAGOA | D46: 22007 | E46: 44944 | F46: ELBER | G46: PICOS | H46: RVY4G31 | I46: RENEGADE | J46: SIM | K46: 4X2 | L46: NÃO | M46: NÃO | N46: LOCALIZA | AA46: 45141 | AB46: 5000 | AC46: PICOS
A47: 44 | B47: INATIVO | C47: AROEIRA | D47: 22006 | E47: 44947 | F47: JOSE ERIVAN | G47: FEIRA DE SANTANA | H47: RVV9E35 | I47: ARGO | J47: SIM | K47: Passeio | L47: NÃO | M47: NÃO | N47: LOCALIZA | AA47: 45111 | AB47: 5000 | AC47: FEIRA DE SANTANA | AD47: Veículo retirado pelo Antonio, carro do Adenilton repassado para Jose Erivan sem avarias.
A48: 45 | B48: INATIVO | C48: NOVA OLINDA CGN | D48: 23001 | E48: 44947 | F48: JOAO PAULO | G48: JUAZEIRO DO NORTE | H48: RTK8D25 | I48: SANDERO | J48: CARRO INATIVO | K48: Passeio | L48: NÃO | M48: NÃO | N48: LOCALIZA | AA48: 0 | AB48: 5000 | AC48: JUAZEIRO DO NORTE
A49: 31 | B49: INATIVO | C49: TOTAL EREN | D49: 23004 | E49: 44950 | F49: RILDSON | G49: SALVADOR | H49: RMJ6B96 | I49: L200 | J49: NÃO | K49: 4X4 | L49: NÃO | N49: LOCALIZA | AA49: 44990 | AB49: 5000 | AC49: SALVADOR
A50: 310 | B50: ATIVO | C50: AUREN | D50: 25001 | E50: 45840 | F50: ELISSON | G50: AEROPORTO NATAL | H50: PVR3B92 | I50: ONIX | J50: SIM | K50: Passeio | L50: NÃO | M50: NÃO | N50: UNIDAS | O50: 45892 | P50: Polo TJL7E95 | AB50: 3000 | AC50: AEROPORTO NATAL - RN
A51: 48 | B51: INATIVO | C51: LAGOA | D51: 22007 | E51: 44963 | F51: MATHEUS MIRANDA | G51: PICOS | H51: RVI1H11 | I51: RENEGADE | J51: SIM | K51: 4X2 | L51: NÃO | M51: NÃO | N51: LOCALIZA | AA51: 45288 | AB51: 5000 | AC51: PICOS
A52: 49 | B52: INATIVO | C52: NOVA OLINDA CGN | D52: 23001 | E52: 44966 | F52: ANA CAROLINE | G52: JUAZEIRO | H52: GIG8H82 | I52: GOL | J52: CARRO INATIVO | K52: Passeio | L52: NÃO | M52: NÃO | N52: UNIDAS | AA52: 45017 | AB52: 6000 | AC52: JUAZEIRO - BA
A53: 50 | B53: INATIVO | C53: NOVA OLINDA CGN | D53: 23001 | E53: 44968 | F53: UALACE ROLDAO | G53: PICOS | H53: SHB9A62 | I53: ARGO | J53: CARRO INATIVO | K53: Passeio | L53: NÃO | M53: NÃO | N53: LOCALIZA | AA53: 45017 | AB53: 5000 | AC53: PICOS
A54: 51 | B54: INATIVO | C54: AROEIRA | D54: 22006 | E54: 44971 | F54: GEORGE ANUNCIAÇÃO / JONATHAN | G54: JUAZEIRO | H54: RTJ7C86 | I54: 208 | J54: SIM | K54: Passeio 1.6 | L54: NÃO | M54: NÃO | N54: UNIDAS | O54: 45022 | P54: 208 RT05B73 | AA54: 45296 | AB54: 4500 | AC54: JUAZEIRO - BA | AD54: Veículo retirado pelo Gerardo. Carro utilizado pelo Leonardo e George anunciação.
A55: 52 | B55: INATIVO | C55: FURNAS ANGRA | D55: 19018 | E55: 44972 | F55: LUIZ FERNANDO | G55: GUARATINGUETA | H55: RVS1J80 | I55: S10 | J55: NÃO | K55: 4X4 | L55: NÃO | N55: UNIDAS | AA55: 45106 | AB55: 6000 | AC55: GUARATINGUETA
A56: 53 | B56: INATIVO | C56: FURNAS ANGRA | D56: 19018 | E56: 44972 | F56: MARIO RAIMO | G56: GUARULHOS | H56: RVS1J62 | I56: S10 | J56: NÃO | K56: 4X4 | L56: NÃO | N56: UNIDAS | AA56: 45100 | AB56: 6000 | AC56: GUARULHOS
A57: 54 | B57: INATIVO | C57: AROEIRA | D57: 22006 | E57: 44996 | F57: ANTONIO (CHICÃO) | G57: FEIRA DE SANTANA | H57: SHG0H04 | I57: ARGO | J57: SIM | K57: Passeio | L57: NÃO | M57: NÃO | N57: LOCALIZA | O57: 45164 | P57: ONIX SHQ9B43 | AA57: 45185 | AB57: 5000 | AC57: FEIRA DE SANTANA
A58: 55 | B58: INATIVO | C58: NOVA OLINDA CGN | D58: 23001 | E58: 45010 | F58: WELLITON | G58: PICOS | H58: RUA7I01 | I58: PULSE | J58: CARRO INATIVO | K58: 4X2 | L58: NÃO | M58: NÃO | N58: LOCALIZA | AA58: 45034 | AB58: 5000 | AC58: PICOS
A59: 56 | B59: INATIVO | C59: NOVA OLINDA CGN | D59: 23001 | E59: 45010 | F59: ALAIN | G59: PICOS | H59: RVJ5F76 | I59: RENEGADE | J59: CARRO INATIVO | K59: 4X2 | L59: NÃO | M59: NÃO | N59: LOCALIZA | AA59: 45057 | AB59: 5000 | AC59: PICOS
A60: 57 | B60: INATIVO | C60: NOVA OLINDA CGN | D60: 23001 | E60: 45010 | F60: ADRIANO | G60: PICOS | H60: RVX0C20 | I60: C4 | J60: SIM | K60: 4X2 | L60: NÃO | M60: NÃO | N60: LOCALIZA | AA60: 45062 | AB60: 5000 | AC60: PICOS | AD60: Veículo retirado pelo Joao Paulo
A61: 58 | B61: INATIVO | C61: PEDRA PINTADA | D61: 22005 | E61: 45016 | F61: SHEILA | G61: BARREIRAS | H61: SDZ7C36 | I61: T CROSS | J61: NÃO | K61: 4X2 | L61: NÃO | M61: NÃO | N61: UNIDAS | AB61: 3000 | AC61: SALVADOR | AD61: Veículo retirado pela Sheila
A62: 59 | B62: INATIVO | C62: NOVA OLINDA CGN | D62: 23001 | E62: 45017 | F62: UALACE ROLDAO | G62: PICOS | H62: RUV6F79 | I62: T CROSS | J62: CARRO INATIVO | K62: 4X2 | L62: NÃO | M62: NÃO | N62: LOCALIZA | AA62: 45045 | AB62: 5000 | AC62: PICOS
A63: 60 | B63: INATIVO | C63: NOVA OLINDA CGN | D63: 23001 | E63: 45017 | F63: ANA CAROLINE | G63: JUAZEIRO | H63: ECU3H93 | I63: T CROSS | J63: CARRO INATIVO | K63: 4x2 | L63: NÃO | M63: NÃO | N63: UNIDAS | AA63: 45059 | AB63: 4500 | AC63: JUAZEIRO - BA
A64: 61 | B64: INATIVO | C64: NOVA OLINDA CGN | D64: 23001 | E64: 45031 | F64: JOAO PAULO | G64: BARREIRAS | H64: RVA3J73 | I64: TRACKER | J64: CARRO INATIVO | K64: 4X2 | L64: NÃO | M64: NÃO | N64: LOCALIZA | AA64: 45045 | AB64: 5000 | AC64: JUAZEIRO - CE | AD64: Veículo retirado pelo Joao Paulo
A65: 62 | B65: INATIVO | C65: HORIZONTE | D65: 22035 | E65: 45043 | F65: SHEILA | G65: BARREIRAS | H65: RVW8I65 | I65: PULSE | J65: CARRO INATIVO | K65: 4X2 | L65: NÃO | M65: NÃO | N65: LOCALIZA | AA65: 45056 | AB65: 3000 | AC65: BARREIRAS
A66: 63 | B66: INATIVO | C66: DNIT | D66: 20017 | E66: 45054 | F66: NELLO | G66: BARREIRAS | H66: SHO9G87 | I66: MOBI | J66: CARRO INATIVO | K66: Passeio | L66: NÃO | M66: NÃO | N66: LOCALIZA | AA66: 45059 | AB66: LIVRE | AC66: PARACATU - MG
A67: 64 | B67: INATIVO | C67: AROEIRA | D67: 22006 | E67: 45054 | F67: JONATHAN | G67: SALVADOR | H67: RTU6D82 | I67: ARGO | J67: NÃO | K67: Passeio | L67: NÃO | M67: NÃO | N67: UNIDAS | AA67: 45102 | AB67: LIVRE | AC67: SALVADOR | AD67: Entre na desmobilização de George Anunciação
A68: 65 | B68: INATIVO | C68: DNIT - VISITA | D68: 20017 | E68: 45055 | F68: GILSON | G68: BARREIRAS | H68: SHQ7D52 | I68: KWID | J68: CARRO INATIVO | K68: Passeio | L68: NÃO | M68: NÃO | N68: LOCALIZA | AA68: 45057 | AB68: LIVRE | AC68: VILA VELHA -ES
A69: 66 | B69: INATIVO | C69: AROEIRA | D69: 22006 | E69: 44935 | F69: ANTONIO (CHICÃO) | G69: FEIRA DE SANTANA | H69: RFX4B09 | I69: GOL | J69: CARRO INATIVO | K69: PASSEIO 1.6 | L69: NÃO | M69: NÃO | N69: LOCALIZA | AA69: 44996 | AB69: 5000 | AC69: FEIRA DE SANTANA | AD69: Veículo retirado pelo Antonio
A70: 67 | B70: INATIVO | C70: NOVA OLINDA CGN | D70: 23001 | E70: 44956 | F70: WELLITON | G70: PICOS | H70: GJD1B35 | I70: GOL | J70: CARRO INATIVO | K70: PASSEIO | L70: NÃO | M70: NÃO | N70: LOCALIZA | AA70: 45010 | AB70: 5000 | AC70: PICOS
A71: 68 | B71: INATIVO | C71: NOVA OLINDA CGN | D71: 23001 | E71: 44959 | F71: ADRIANO | G71: PICOS | H71: ECU7C233 | I71: GOL | J71: CARRO INATIVO | K71: PASSEIO | L71: NÃO | M71: NÃO | N71: LOCALIZA | AA71: 45010 | AB71: 5000 | AC71: PICOS
A72: 69 | B72: INATIVO | C72: NOVA OLINDA CGN | D72: 23001 | E72: 44960 | F72: ALAN | G72: PICOS | H72: RUK1G33 | I72: HB20 | J72: CARRO INATIVO | K72: PASSEIO | L72: NÃO | M72: NÃO | N72: LOCALIZA | AA72: 45010 | AB72: 5000 | AC72: PICOS
A73: 70 | B73: INATIVO | C73: AROEIRA | D73: 22006 | E73: 45078 | F73: ALVARO | G73: BARREIRAS | H73: RVB6E15 | I73: C4 | J73: NÃO | K73: 4x2 | L73: NÃO | M73: NÃO | N73: LOCALIZA | O73: 45094 | P73: ARGO RVA0H10 | AA73: 45194 | AB73: 5000 | AC73: NATAL
A74: 71 | B74: INATIVO | C74: AROEIRA - VISTITA | D74: 22006 | E74: 45088 | F74: SHEILA | G74: BARREIRAS | H74: FJN2J75 | I74: T-CROSS | J74: NÃO | K74: 4X2 | L74: NÃO | M74: NÃO | N74: LOCALIZA | AA74: 45094 | AB74: LIVRE
A75: 72 | B75: INATIVO | C75: DNIT - VISITA | D75: 20017 | E75: 45090 | F75: GILSON | G75: BARREIRAS | H75: SHG3G60 | I75: ARGO | J75: NÃO | K75: PASSEIO | L75: NÃO | M75: NÃO | N75: LOCALIZA | AA75: 45091 | AB75: LIVRE
A76: 73 | B76: INATIVO | C76: DNIT - VISITA | D76: 20017 | E76: 45089 | F76: NELLO | G76: BARREIRAS | H76: RVI6G17 | I76: MOBI | J76: NÃO | K76: PASSEIO | L76: NÃO | M76: NÃO | N76: LOCALIZA | AA76: 45094 | AB76: LIVRE
A77: 74 | B77: INATIVO | C77: FURNAS ANGRA | D77: 19018 | E77: 45106 | F77: LUIZ FERNANDO | G77: RIO DE JANEIRO | H77: RUK9G23 | I77: L200 | J77: NÃO | K77: 4X4 | L77: NÃO | N77: LOCALIZA | AA77: 45157 | AB77: 4500 | AC77: RIO DE JANEIRO
A78: 75 | B78: INATIVO | C78: FURNAS ANGRA | D78: 19018 | E78: 45100 | F78: MARIO RAIMO / ANDERSON MOREIRA | G78: RIO DE JANEIRO | H78: RTC2C91 | I78: S10 | J78: NÃO | K78: 4X4 | L78: NÃO | N78: LOCALIZA | O78: 45220 | P78: S10 RNY1D98 | Q78: 45262 | R78: S10 SHF5J17 | AA78: 45323 | AB78: 4500 | AC78: RIO DE JANEIRO | AD78: Veiculo repasado para Anderson dia 13/09/2023
A79: 76 | B79: INATIVO | C79: DNIT - VISITA | D79: 20017 | E79: 45110 | F79: NELLO | G79: BARREIRAS | H79: SHG2C72 | I79: MOBI | J79: NÃO | K79: PASSEIO | L79: NÃO | M79: NÃO | N79: LOCALIZA | AA79: 45119 | AB79: LIVRE | AC79: PARACATU/MG
A80: 77 | B80: INATIVO | C80: DNIT-VISITA | D80: 20017 | E80: 45118 | F80: GILSON | G80: BARREIRAS | H80: RVG8G08 | I80: C3 | J80: NÃO | K80: PASSEIO | L80: NÃO | M80: NÃO | N80: LOCALIZA | AA80: 45119 | AB80: LIVRE | AC80: VILA VELHA - ES
A81: 78 | B81: INATIVO | C81: LAGOA | D81: 22007 | E81: 45139 | F81: ADEMIR | G81: JUAZEIRO | H81: SHW6C40 | I81: ARGO | J81: SIM | K81: PASSEIO | L81: NÃO | M81: NÃO | N81: UNIDAS | AA81: 45554 | AB81: 4500 | AC81: JUAZEIRO - BA
A82: 79 | B82: INATIVO | C82: IBIMIRIM | D82: 23018 | E82: 45157 | F82: UALACE ROLDAO | G82: RECIFE | H82: EET8J83 | I82: TCROSS | J82: SIM | K82: 4x2 | L82: NÃO | M82: NÃO | N82: UNIDAS | AA82: 45164 | AB82: 3000 | AC82: RECIFE-PE
A83: 80 | B83: INATIVO | C83: FURNAS ANGRA | D83: 19018 | E83: 45157 | F83: MARIO RAIMO / LUIZ FERNANDO | G83: RIO DE JANEIRO | H83: SEO0D82 | I83: HILUX | J83: NÃO | K83: 4X4 | L83: SIM | N83: UNIDAS | O83: 45528 | P83: S10 SYD6H52 | AA83: 45551 | AB83: 4500 | AC83: RIO DE JANEIRO | AD83: Carro repassado para Anderson dia 01/02/2024.
A84: 81 | B84: INATIVO | C84: IBIMIRIM | D84: 23018 | E84: 45166 | F84: JOSE CARLOS - ANDRE E UALACE | G84: RECIFE | H84: SIH5F91 | I84: RENEGADE | J84: SIM | K84: 4X2 | L84: NÃO | M84: NÃO | N84: UNIDAS | O84: 45499 | P84: TCROSS FPC5J63 | Q84: 45502 | R84: TCROSS EZO1E92 | AA84: 45534 | AB84: 3000 | AC84: RECIFE-PE | AD84: CARRO REPASSADO PARA ANDRE E UALACE
A85: 82 | B85: INATIVO | C85: IBIMIRIM | D85: 23018 | E85: 45166 | F85: LAZARO | G85: RECIFE | H85: SIG2C14 | I85: TORO | J85: SIM | K85: 4X2 | L85: NÃO | M85: NÃO | N85: UNIDAS | O85: 45369 | P85: PULSE RVJ8D67 | AA85: 45418 | AB85: 5000 | AC85: RECIFE-PE
A86: 83 | B86: INATIVO | C86: IBIMIRIM | D86: 23018 | E86: 45164 | F86: UALACE | G86: RECIFE | H86: SIG2B87 | I86: TORO | J86: SIM | K86: 4X2 | L86: NÃO | M86: NÃO | N86: UNIDAS | AA86: 45198 | AB86: 3000 | AC86: RECIFE-PE
A87: 84 | B87: INATIVO | C87: AROEIRA | D87: 22006 | E87: 45173 | F87: SHEILA | G87: BARREIRAS | H87: EZO9F73 | I87: TCROSS | J87: NÃO | K87: 4X2 | L87: NÃO | M87: NÃO | N87: UNIDAS | AA87: 45209
A88: 85 | B88: INATIVO | C88: ENG. AGRONOMO | D88: 22023 | E88: 45183 | F88: GUSTAVO | G88: BARREIRAS | H88: SIM2I94 | I88: TRACKER | J88: SIM | K88: 4X2 | L88: NÃO | M88: NÃO | N88: LOCALIZA | O88: 45402 | P88: TCROSS SHX9G91 | AA88: 45451 | AB88: 3000 | AC88: BARREIRAS | AD88: Gustavo saiu da obra de São Gonçalo para Aroeira dia 24/10/2023.
A89: 86 | B89: INATIVO | C89: IBIMIRIM | D89: 23018 | E89: 45198 | F89: ALAIN /DEVALDO | G89: RECIFE | H89: RVL0I63 | I89: HB20 | J89: SIM | K89: PASSEIO | L89: NÃO | M89: NÃO | N89: LOCALIZA | AA89: 45293 | AB89: 3000 | AC89: RECIFE-PE | AD89: Carro retirado na subsituição da TORO SIG2B87
A90: 87 | B90: INATIVO | C90: MAPEAMENTO | D90: 22005 | E90: 38643 | F90: PAULO RICARDO | G90: JUAZEIRO | H90: SIM9C98 | I90: RENEGADE | J90: SIM | K90: 4X2 | L90: NÃO | M90: NÃO | N90: UNIDAS | AA90: 45434 | AB90: 4500 | AC90: JUAZEIRO - BA
A91: 88 | B91: INATIVO | C91: IBIMIRIM | D91: 23018 | E91: 45222 | F91: FAUSTO ALENCAR / ANDRE E UALACE | G91: JUAZEIRO | H91: SIM6A02 | I91: ONIX LT | J91: SIM | K91: Passeio | L91: NÃO | M91: NÃO | N91: UNIDAS | O91: 45362 | P91: PEUGEOT 208 RTG4C60 | AA91: 45417 | AB91: 3000 | AC91: JUAZEIRO - BA | AD91: PEUGEOT REPASSADO PARA UALACE E ANDRE
A92: 89 | B92: INATIVO | C92: LAGOA | D92: 22007 | E92: 45231 | F92: SAMILA | G92: JUAZEIRO | H92: SIT1G63 | I92: ONIX | J92: SIM | K92: Passeio | L92: NÃO | M92: NÃO | N92: UNIDAS | AA92: 45602 | AB92: 4500 | AC92: JUAZEIRO - BA | AD92: Carro retirado por Raimundo Gerson
A93: 90 | B93: INATIVO | C93: LAGOA | D93: 22007 | E93: 45231 | F93: HERMES | G93: JUAZEIRO | H93: SIU5B06 | I93: ONIX | J93: SIM | K93: Passeio | L93: NÃO | M93: NÃO | N93: UNIDAS | AA93: 45537 | AB93: 4500 | AC93: JUAZEIRO - BA
A94: 91 | B94: INATIVO | C94: LAGOA | D94: 22007 | E94: 45230 | F94: SHEILA | G94: JUAZEIRO | H94: SIN6B92 | I94: RENEGADE | J94: NÃO | K94: 4X2 | L94: NÃO | M94: NÃO | N94: UNIDAS | AA94: 45247 | AB94: LIVRE | AC94: JUAZEIRO - BA
A95: 92 | B95: INATIVO | C95: LAGOA | D95: 22007 | E95: 45250 | F95: ANTONIO VAGNER | G95: NATAL | H95: RVJ0I15 | I95: TRACKER | J95: SIM | K95: 4X2 | L95: NÃO | M95: NÃO | N95: UNIDAS | O95: 45309 | P95: RENEGADE SIG2E24 | AA95: 45390 | AB95: 6000 | AC95: NATAL -- RN
A96: 93. | B96: INATIVO | C96: CGN LAGOA | D96: 23026 | E96: 45250 | F96: JERFFERSON MOREIRA | G96: PICOS | H96: SHV3E43 | I96: TRACKER | J96: SIM | K96: 4x2 | L96: NÃO | M96: NÃO | N96: LOCALIZA | O96: 45429 | P96: RENEGADE RVU5A22 | Q96: 45534 | R96: TRACKER TCB9G87 | AA96: 45677 | AB96: 5000 | AC96: PICOS - PI | AD96: carro rebocado dia 18/05/2024 - Uso Particular do carro TCB9G87 por Felipe Silva 20.12 a 06.01.25 - DEVOLVIDO EM FORTALEZA CE
A97: 94. | B97: INATIVO | C97: CGN | D97: 23026 | E97: 45258 | F97: CARLOS EDUARDO | G97: JUAZEIRO DO NORTE | H97: RVS1B22 | I97: S10 | J97: SIM | K97: 4X4 | L97: NÃO | N97: UNIDAS | O97: 45311 | P97: S10 SHG4A99 | AA97: 45378 | AB97: 6000 | AC97: JUAZEIRO DO NORTE - CE
A98: 95. | B98: INATIVO | C98: IBIMIRIM | D98: 23018 | E98: 45272 | F98: DANIEL - CLAUDIO | G98: RECIFE | H98: SJB3G42 | I98: C3 LIVE | J98: SIM | K98: Passeio | L98: NÃO | M98: NÃO | N98: UNIDAS | O98: 45324 | P98: ONIX SIM5H02 | Q98: 45353 | R98: ONIX SIN6B14 | AA98: 45603 | AB98: 3000 | AC98: RECIFE-PE | AD98: Carro retirado por Andre para obra de Ibimirim. Carros compartilhados ONIX REPASSADO PARA DANIEL DIA 12/03/2024
A99: 96. | B99: INATIVO | C99: IBIMIRIM | D99: 23018 | E99: 45293 | F99: ALAIN/DEVALDO | G99: RECIFE | H99: SEA2D46 | I99: GOL | J99: SIM | K99: Passeio | L99: NÃO | M99: NÃO | N99: UNIDAS | O99: 45371 | P99: ONIX SHQ6E86 | AA99: 45614 | AB99: 3000 | AC99: RECIFE-PE
A100: 97. | B100: INATIVO | C100: LAGOA | D100: 22007 | E100: 45243 | F100: FABIO SIQUEIRA | G100: NATAL | H100: RNX9A52 | I100: RENEGADE | J100: SIM | K100: 4X2 | L100: NÃO | M100: NÃO | N100: UNIDAS | AA100: 45334 | AB100: 6000 | AC100: NATAL -- RN
...

Sheet Uso Particular 
C1: Folga / Uso Particular
A2: STATUS | B2: OBRA | C2: CONDUTOR | D2: MODELO | E2: PLACA | F2: USO PARTICULAR | G2: OBSERVAÇÕES
A3: INATIVO | B3: GOIANIA | C3: RAINOR | D3: ARGO | E3: RUM5I29
A4: INATIVO | B4: GOIANIA | C4: GLEISON | D4: ARGO | E4: RTE1I62
A5: INATIVO | B5: RIACHO | C5: ISAAC/UALACE | D5: TCROSS | E5: FZP1E71 | F5: 5
A6: ATIVO | B6: RIACHO | C6: UALACE
A7: ATIVO | B7: RIACHO | C7: ANDRE PLACIDO | D7: ARGO | E7: TDY8E51 | F7: 1
A8: INATIVO | B8: RIACHO | C8: EDNEI | D8: HB20 | E8: TCZ6B67 | F8: 3
A9: ATIVO | B9: RIACHO | C9: CLAUDIO
A10: INATIVO | B10: RIACHO | C10: ANDRE | D10: TCROSS | E10: SVW5E64 | F10: 2
A11: ATIVO | B11: CGN lagoa | C11: JERFFERSON MOREIRA | D11: TCROSS | E11: SUI0E07
A12: ATIVO | B12: CGN russas | C12: ROGERIO | D12: TRACKER | E12: TEU0E62 | F12: 1 | G12: uso não solicitado
A13: INATIVO | B13: CGN russas | C13: ELIOMAR | D13: TCROSS | E13: SIJ3F45 | F13: 1 | G13: Não enviou fotos | H13: RECESSO 2025
A14: ATIVO | B14: CGN russas | C14: ANDRE GADELHA | D14: TCROSS | E14: TYA5C83 | F14: 1
A15: ATIVO | B15: CGN russas | C15: CLEBERSON
A16: ATIVO | B16: ELERA | C16: ROBSON
A17: INATIVO | B17: SUSTENTABILIDADE | C17: LUCIANE
A18: ATIVO | B18: SUSTENTABILIDADE | C18: ALIRE | D18: TRACKER | E18: TEL5D67 | F18: 1
A19: INATIVO | B19: SUSTENTABILIDADE | C19: EUCILENE | D19: RENEGADE | E19: SIG2E45 | F19: 5
A20: INATIVO | B20: SUSTENTABILIDADE | C20: EUCILENE | D20: TCROSS | E20: SUO8H64 | F20: 3 | G20: Ocorrencia de avarias
A21: INATIVO | B21: STATKRAFT mdc | C21: GEFERSON
A22: INATIVO | B22: STATKRAFT mdc | C22: JOAO CARLOS
A23: INATIVO | B23: STATKRAFT mdc | C23: ANA PAULA
A24: INATIVO | B24: STATKRAFT vse | C24: FRANCISCO AUGUSTO | D24: TCROSS | E24: EJA1H12 | F24: 1 | G24: falta de informação | H24: RECESSO 2025
A25: ATIVO | B25: STATKRAFT vse | C25: FRANCISCO AUGUSTO | D25: CRETA | E25: TXZ1G58 | F25: 2 | G25: uso não solicitado
A26: ATIVO | B26: STATKRAFT vse | C26: JURANDIR
A27: INATIVO | B27: STATKRAFT vse | C27: JHONNY
A28: INATIVO | B28: STATKRAFT vse | C28: NILBERTO | D28: TCROSS | E28: TKX8G73 | F28: 3 | G28: uso não solicitado
A29: INATIVO | B29: STATKRAFT vse | C29: ANA LUIZA
A30: ATIVO | B30: STATKRAFT vse | C30: ANA CAROLINE | D30: TCROSS | E30: TJE8B31 | F30: 2
A31: ATIVO | B31: STATKRAFT vse | C31: RONIERI | D31: TCROSS | E31: TJR5F89 | F31: 2 | G31: pendente envio retorno | H31: RECESSO 2025
A32: INATIVO | B32: STATKRAFT vse | C32: WASHINGTON | D32: TCROSS | E32: FFW5H24 | F32: 1
A33: INATIVO | B33: STATKRAFT vse | C33: FRANCISCO DE MORAIS | D33: TCROSS | E33: SWD0G64 | F33: 1 | H33: RECESSO 2025
A34: ATIVO | B34: STATKRAFT vse | C34: FRANCISCO DE MORAIS | D34: CRETA | E34: TXW4I69 | F34: 1 | G34: uso não solicitado
A35: ATIVO | B35: STATKRAFT vse | C35: ERIC
A36: INATIVO | B36: STATKRAFT vse | C36: JAIR | D36: TRACKER | E36: TEL5D17 | F36: 1 | G36: envio atrasado e não seguiu orientação de troca de veículo | H36: RECESSO 2025
A37: INATIVO | B37: STATKRAFT rsh | C37: FRANCISCO IRANILDO | D37: TCROSS | E37: SWH5H35 | F37: 1
A38: ATIVO | B38: STATKRAFT vse | C38: LUIS DALADIUER | D38: RENEGADE | E38: TXL2A88 | F38: 1 | G38: pendente envio retorno
A39: ATIVO | B39: STATKRAFT rsh | C39: IZADORA | D39: CRETA | E39: TXB9I08 | F39: 3 | G39: pendente envio retorno | H39: RECESSO 2025
A40: ATIVO | B40: STATKRAFT rsh | C40: GEFERSON | D40: TRACKER | E40: TEU0E78 | F40: 7 | G40: Uso não solicitado | H40: RECESSO 2025
A41: ATIVO | B41: STATKRAFT rsh | C41: GERALDO | D41: TCROSS | E41: SWM9B65 | F41: 2 | H41: RECESSO 2025
A42: INATIVO | B42: STATKRAFT rsh | C42: JOÃO CARLOS | D42: TCROSS | E42: TJD9D17 | F42: 2 | G42: Uso sem autorização
A43: INATIVO | B43: STATKRAFT sfh | C43: CLAUDIO ULIANA | D43: TCROSS | E43: FJH3D91 | F43: 3 | H43: RECESSO 2025
A44: INATIVO | B44: STATKRAFT sfh | C44: AIRISMILA | D44: TCROSS | E44: TYA5C94 | F44: 3 | H44: RECESSO 2025
A45: ATIVO | B45: STATKRAFT rsh | C45: JOÃO CARLOS | D45: TRACKER | E45: UBT5H05
A46: ATIVO | B46: STATKRAFT rsh | C46: RAILSON | D46: RENEGADE | E46: TDX0E39 | F46: 2 | G46: Uso sem autorização
A47: ATIVO | B47: STATKRAFT sfh | C47: CLAUDIO ULIANA | D47: TRACKER | E47: TXW4H18 | F47: 2 | G47: Uso não solicitado
A48: ATIVO | B48: STATKRAFT sfh | C48: MARCELO | D48: TCROSS | E48: TXW4I71 | F48: 2 | H48: RECESSO 2025
A49: ATIVO | B49: STATKRAFT sfh | C49: ESDRAS | D49: TRACKER | E49: TEL5D58 | F49: 2 | G49: pendente envio retorno | H49: RECESSO 2025
A50: ATIVO | B50: STATKRAFT sfh | C50: WEILLER | D50: CRETA | E50: TXW4I63 | F50: 4
A51: ATIVO | B51: STATKRAFT sfh | C51: FERNANDO | D51: TRACKER | E51: UBT5I55 | F51: 1
A52: ATIVO | B52: AUREN | C52: EIDER BRENO | D52: DUSTER | E52: TDJ7G97 | F52: 4 | H52: RECESSO 2026
A53: INATIVO | B53: AUREN | C53: ROBERTO | D53: S10 | E53: UAI4B92
A54: INATIVO | B54: AUREN | C54: CHRIS | D54: ARGO | E54: TDQ6D38 | F54: 6 | G54: 2 uso recesso - total 564km | H54: RECESSO 2026
A55: INATIVO | B55: AUREN | C55: YANCA | D55: POLO | E55: STZ7D92 | F55: 1 | G55: uso sem solicitação
A56: INATIVO | B56: AUREN | C56: ALAIN | D56: S10 | E56: TDP1E16 | F56: 10 | G56: pendente registros | H56: RECESSO 2025
A57: ATIVO | B57: AUREN | C57: MARCILIO | D57: ONIX | E57: SJH8E03 | F57: 2 | G57: Ocorrencia de avarias
A58: ATIVO | B58: AUREN | C58: EIDER BRENO | D58: ARGO | E58: TWZ9A06 | F58: 4 | G58: informação atrasada | H58: RECESSO 2025
A59: INATIVO | B59: AUREN | C59: TIAGO GONÇALVES | D59: S10 | E59: TEZ5D42 | F59: 1 | G59: pendente envio de retorno | H59: RECESSO 2025
A60: ATIVO | B60: AUREN | C60: WILDSON | D60: ARGO | E60: TCT9C97 | F60: 1
A61: ATIVO | B61: AUREN | C61: EDUARDO SILVA | D61: POLO | E61: EWF6F13 | F61: 1
A62: ATIVO
A63: ATIVO
A64: ATIVO
A65: ATIVO
A66: ATIVO
A67: ATIVO
A68: ATIVO
A69: ATIVO
A70: ATIVO
A71: ATIVO
A72: ATIVO
A73: ATIVO
A74: ATIVO
A75: TOTAL | F75: =SUM(F3:F74) -> 102
B76: Planilha criada para verificar a utilização do carro na folga ou uso particular e assim verificar possivel avaria no veiculo nesse periodo.
B77: Orientação: Verificar rastreador e acompanhamento do check list veicular.

Sheet Valor Mensal - Faturas
B1: PLANILHA DE VEÍCULOS ATIVOS
A2: OBRA | B2: CONDUTOR | C2: MODELO | D2: PLACA | E2: KM | F2: CONTRATADO | G2: FATURA | H2: LOCADORA | I2: EXTRAS | J2: OBSERVAÇÕES
A3: LAGOA | B3: RAIMUNDO GERSON | C3: S10 | D3: RVS1B18 | E3: 6000 | F3: 7434 | H3: Unidas | I3: nenhuma | J3: Desmobilizado 09/02/2024
A4: LAGOA | B4: CONTINGÊNCIA QUALIDADE | C4: TRACKER | D4: RVH2E00 | E4: 3000 | F4: 3467.99 | H4: Localiza | I4: nenhuma | J4: Desmobilizado 15/09
A5: LAGOA | B5: CLAUDIO | C5: RENEGADE | D5: RVF2B30 | E5: 3000 | F5: 3476.26 | H5: Localiza | I5: nenhuma | J5: Desmobilizado 30/10
A6: LAGOA | B6: MATHEUS MIRANDA | C6: RENEGADE | D6: RVI1H11 | E6: 5000 | F6: 3952.03 | H6: Localiza | I6: nenhuma | J6: Desmobilizado 28/12
A7: LAGOA | B7: FRANCISCO EDILSON | C7: RENEGADE | D7: SHY2C77 | E7: 5000 | F7: 3145.99 | H7: Localiza | I7: nenhuma | J7: Desmobilizado 12/02/2024
A8: LAGOA | B8: ANTONIO VAGNER | C8: RENEGADE | D8: SIG2E24 | E8: 6000 | F8: 3775.99 | H8: Unidas | I8: nenhuma | J8: Desmobilizado 08/04/2024
A9: LAGOA | B9: FABIO SIQUEIRA | C9: RENEGADE | D9: RNX9A52 | E9: 6000 | F9: 3775.99 | H9: Unidas | I9: nenhuma | J9: Desmobilizado 14/02/2024
A10: CAJUÍNAS | B10: ALAIN | C10: S10 | D10: TDP1E16 | E10: 3000 | F10: 7553 | G10: 7553 | H10: Unidas
A11: LAGOA | B11: IRMA MACEDO | C11: PULSE | D11: SDW7B57 | E11: 4500 | F11: 3455.99 | H11: Unidas | I11: nenhuma | J11: Desmobilizado 01/11
A12: AROEIRA | B12: ANTONIO (CHICÃO) | C12: HB20X | D12: RNU4G47 | E12: 3000 | F12: 2986 | H12: Unidas | I12: com proteção de vidros | J12: Desmobilizado 23/10
A13: AROEIRA | B13: MICHEL | C13: HB20 | D13: RUX4D45 | E13: x | F13: 2169.99 | H13: Localiza | I13: nenhuma | J13: Desmobilizado 19/09
A14: AROEIRA | B14: DEVALDO | C14: CHRONOS | D14: RUH9C37 | E14: x | F14: 2554 | H14: Unidas | I14: nenhuma | J14: Desmobilizado 30/09
A15: AROEIRA | B15: MARIA LUIZA | C15: 208 | D15: SHS9A71 | E15: x | F15: 2986 | H15: Unidas | I15: nenhuma | J15: Desmobilizado 20/09
A16: AROEIRA | B16: JONATHAN | C16: 208 | D16: RT05B73 | E16: 4500 | F16: 2741 | H16: Unidas | I16: nenhuma | J16: Desmobilizado 05/01/2024
A17: AROEIRA | B17: ANTÔNIO (CHICÃO) | C17: ONIX | D17: SHQ9B43 | E17: x | F17: 2473.97 | H17: Localiza | I17: nenhuma | J17: Desmobilizado 16/09
A18: ENG AGRONOMO | B18: GUSTAVO | C18: TRACKER | D18: SIM2I94 | E18: 3000 | F18: 4227 | H18: Localiza | I18: com proteção de vidros e pneus | J18: Desmobilizado 08/06/2024
A19: AROEIRA | B19: ALVARO | C19: ARGO | D19: RVA0H10 | E19: x | F19: 2591.23 | H19: Localiza | I19: nenhuma | J19: Desmobilizado 25/09
A20: CAJUÍNAS | B20: ALVERSON | C20: POLO | D20: TJL7E95 | E20: 3000 | F20: 2484 | G20: 2484 | H20: Unidas
A21: FURNAS ANGRA | B21: MARIO RAIMO | C21: S10 | D21: RNY1D98 | E21: 5000 | F21: 8294.4 | H21: Localiza | I21: nenhuma | J21: Desmobilizado 01/02/2024
A22: CAJUÍNAS | B22: CHRIS | C22: ARGO | D22: TDQ6D38 | E22: 3000 | F22: 2484 | G22: 2484 | H22: Unidas
A23: CAJUÍNAS | B23: EIDER BRENO | C23: ONIX | D23: SJH8E03 | E23: 3000 | F23: 2484 | G23: 2484 | H23: Unidas
A24: CAJUÍNAS | B24: GEOVANI | C24: POLO | D24: SSW2I35 | E24: 3000 | F24: 2484 | G24: 2484 | H24: Unidas
A25: CAJUÍNAS | B25: IDALECIO | C25: POLO | D25: STZ7D92 | E25: 3000 | F25: 2484 | G25: 2484 | H25: Unidas
A26: CAJUÍNAS | B26: MARCILIO | C26: DUSTER | D26: TDJ7G97 | E26: 3000 | F26: 3837 | G26: 3837 | H26: Unidas
A27: CAJUÍNAS | B27: ROBERTO | C27: S10 | D27: UAI4B92 | E27: 4500 | F27: 8158 | G27: 8158 | H27: Unidas
A28: CAJUÍNAS | B28: TIAGO GONÇALVES | C28: S10 | D28: TEZ5D42 | E28: 3000 | F28: 7553 | H28: Unidas
A29: CAJUÍNAS | B29: WILDSON | C29: POLO | D29: TJF8C34 | E29: 3000 | F29: 2484 | H29: Unidas
A30: CAJUÍNAS | B30: UBIRATAN | C30: S10 | D30: TDP1D97 | E30: 3000 | F30: 7553 | H30: Unidas
A31: CGN | B31: ELIOMAR | C31: TCROSS | D31: SIJ3F45 | E31: 5000 | F31: 4335.99 | G31: 4335.99 | H31: Unidas
A32: CGN | B32: JERFFERSON MOREIRA | C32: TCROSS | D32: SUI0E07 | E32: 4500 | F32: 4144 | G32: 4144 | H32: Unidas
A33: CGN | B33: ROGERIO | C33: TCROSS | D33: SVW2F07 | E33: 3000 | F33: 3837 | G33: 3837 | H33: Unidas
A34: GOIANIA | B34: RAINOR | C34: POLO | D34: TJZ9J36 | E34: 3000 | F34: 2484 | G34: 2484 | H34: Unidas
A35: GOIANIA | B35: GLEISON | C35: ARGO | D35: RTE1I62 | E35: 3000 | F35: 2484 | G35: 2484 | H35: Unidas
A36: MAPEAMENTO | B36: RENATA | C36: T-CROSS | D36: ENI9F24 | E36: 3000 | F36: 4191.94 | H36: Localiza | I36: nenhuma | J36: Desmobilizado 19/04/2024
A37: MAPEAMENTO | B37: SUIANE | C37: PULSE | D37: SHB4H30 | E37: 4000 | F37: 3702.72 | H37: Localiza | I37: com proteção de vidros e pneus | J37: Desmobilizado 19/01
A38: MAPEAMENTO | B38: PAULO RICARDO | C38: RENEGADE | D38: SIM9C98 | E38: 4500 | F38: 3455.99 | H38: Unidas | I38: nenhuma | J38: Desmobilizado 22/05/2024
A39: LABORATORIO | B39: LABORATORIO | C39: S10 | D39: SHG4A46 | E39: x | F39: 7434 | H39: Unidas | I39: nenhuma | J39: Desmobilizado 17/10
A40: LABORATORIO | B40: LABORATORIO | C40: S10 | D40: SHG4A45 | E40: x | F40: 7467.8 | H40: Unidas | I40: nenhuma | J40: Desmobilizado 03/10
A41: RIACHO | B41: ANDRE PLACIDO | C41: TCROSS | D41: SVW5E64 | E41: 4500 | F41: 4144 | G41: 4144 | H41: Unidas
A42: IBIMIRIM | B42: ANDRE E UALACE | C42: PEUGEOT 208 | D42: RTG4C60 | E42: 3000 | F42: 2091 | H42: Unidas | I42: nenhuma | J42: Desmobilizado 05/05/2024
A43: IBIMIRIM | B43: LAZARO | C43: PULSE | D43: RVJ8D67 | E43: 5000 | F43: 2990 | H43: Unidas | I43: nenhuma | J43: Desmobilizado 06/05/2024
A44: RIACHO | B44: LAZARO | C44: TCROSS | D44: SVR2H85 | E44: 3000 | F44: 3837 | G44: 3837 | H44: Unidas
A45: IBIMIRIM | B45: NICANOR / UALACE | C45: TORO | D45: SIG2B87 | E45: x | F45: 4518.86 | H45: Unidas | I45: com proteção de vidros | J45: Desmobilizado 29/09
A46: RIACHO | B46: EDNEI | C46: HB20 | D46: TCZ6B67 | E46: 3000 | F46: 2484 | G46: 2484 | H46: Unidas
A47: RIACHO | B47: WENDEL | C47: POLO | D47: DKU8J41 | E47: 3000 | F47: 2484 | G47: 2484 | H47: Unidas
A48: IBIMIRIM | B48: ALAIN | C48: HB20 | D48: RVL0I63 | E48: 3000 | F48: 2295.89 | H48: Localiza | I48: nenhuma | J48: Desmobilizado 02/01/2024
A49: RIACHO | B49: CLAUDIO | C49: ARGO | D49: TCY1C25 | E49: 3000 | F49: 2484 | G49: 2484 | H49: Unidas
A50: RIACHO | B50: ISAAC | C50: TCROSS | D50: FZP1E71 | E50: 3000 | F50: 3837 | G50: 3837 | H50: Unidas
A51: KROMA | B51: ELIKESTH | C51: HB20 | D51: TDT7A83 | E51: 3000 | F51: 2484 | G51: 2484 | H51: Unidas
A52: CGN | B52: ROGERIO | C52: TCROSS | D52: SVW2F07 | E52: 3000 | F52: 3837 | G52: 3837 | H52: Unidas
A53: CGN | B53: ELIOMAR | C53: TCROSS | D53: SIJ3F45 | E53: 5000 | F53: 4335.99 | G53: 4335.99 | H53: Unidas
A54: CGN | B54: JERFFERSON MOREIRA | C54: TCROSS | D54: SUI0E07 | E54: 4500 | F54: 4144 | G54: 4144 | H54: Unidas
A55: AROEIRA | B55: ESEQUIAS | C55: TCROSS | D55: SYD7G06 | E55: 5000 | F55: 3615.99 | H55: Unidas | I55: nenhuma | J55: Desmobilizado 26/03/2024
A56: ELERA | B56: ROBSON COSTA | C56: ARGO | D56: TCU0B50 | E56: 3000 | F56: 2484 | G56: 2484 | H56: Unidas
A57: SEDE | B57: JOSE LUIS | C57: JEEP COMPASS | D57: SJC2A75 | E57: 3000 | F57: 4788 | H57: Localiza | I57: nenhuma | J57: Desmobilizado dia 05/07/2024
A58: ELERA | B58: ANTONIO FLAVIO | C58: HB20 | D58: TDA0G20 | E58: 3000 | F58: 2484 | H58: Unidas
A59: FOLHA LARGA | B59: EMERSON | C59: POLO | D59: TJW0B84 | E59: 3000 | F59: 2484 | G59: 2484 | H59: Unidas
A60: SUSTENTABILIDADE | B60: TAYONARA | C60: RENEGADE | D60: TEJ8H62 | E60: 3000 | F60: 4039.73 | G60: 4039.73 | H60: Localiza
A61: SUSTENTABILIDADE | B61: ERIKA | C61: TORO | D61: SHX8B47 | E61: 5000 | F61: 5025.55 | H61: Localiza | I61: nenhuma | J61: Desmobilizado 21/05/2024
A62: SUSTENTABILIDADE | B62: ALIRE | C62: TRACKER | D62: TEL5D67 | E62: 3000 | F62: 3837 | G62: 3837 | H62: Unidas
A63: SUSTENTABILIDADE | B63: EUCILENE | C63: TCROSS | D63: SUO8H64 | E63: 3000 | F63: 3837 | H63: Unidas
A64: STATKRAFT MDC | B64: JOÃO CARLOS | C64: TCROSS | D64: SVG7A45 | E64: 5000 | F64: 4335.99 | G64: 4335.99 | H64: Unidas
A65: STATKRAFT MDC | B65: WILLIAN | C65: TCROSS | D65: SYD7G06 | E65: 4500 | F65: 4144 | H65: Unidas
A66: STATKRAFT MDC | B66: ANA PAULA | C66: TCROSS | D66: SYD7F82 | E66: 4500 | F66: 4144 | G66: 4144 | H66: Unidas
A67: STATKRAFT VSE | B67: ANA LUIZA | C67: NIVUS | D67: SYG2I07 | E67: 4500 | F67: 4144 | G67: 4144 | H67: Unidas
A68: STATKRAFT VSE | B68: HERIK | C68: TRACKER | D68: TEL5D17 | E68: 3000 | F68: 3837 | G68: 3837 | H68: Unidas
A69: STATKRAFT VSE | B69: ERIC | C69: TCROSS | D69: TLP7F80 | E69: 4500 | F69: 4144 | G69: 4144 | H69: Unidas
A70: STATKRAFT VSE | B70: FRANCISCO AUGUSTO | C70: TCROSS | D70: EJA1H12 | E70: 5000 | F70: 4335.99 | G70: 4335.99 | H70: Unidas
A71: STATKRAFT VSE | B71: FRANCISCO DE MORAIS | C71: TCROSS | D71: SWD0G64 | E71: 4500 | F71: 4144 | G71: 4144 | H71: Unidas
A72: STATKRAFT VSE | B72: JAIR | C72: TCROSS | D72: SIS6B61 | E72: 4500 | F72: 4144 | H72: Unidas
A73: STATKRAFT VSE | B73: JHONNY WEIDE | C73: TRACKER | D73: TEL5D86 | E73: 3000 | F73: 3837 | H73: Unidas
A74: STATKRAFT VSE | B74: JURANDIR | C74: TCROSS | D74: EVW1E22 | E74: 5000 | F74: 4335.99 | G74: 4335.99 | H74: Unidas
A75: STATKRAFT VSE | B75: NILBERTO | C75: TCROSS | D75: TKX8G73 | E75: 4500 | F75: 4144 | G75: 4144 | H75: Unidas
A76: STATKRAFT VSE | B76: RONIERI | C76: TCROSS | D76: TJR5F89 | E76: 5000 | F76: 4335.99 | G76: 4335.98 | H76: Unidas
A77: STATKRAFT VSE | B77: SÁVIO | C77: RANGER | D77: TEU5A95 | E77: 3000 | F77: 7553 | G77: 7553 | H77: Unidas
A78: STATKRAFT VSE | B78: WASHINGTON | C78: CRETA | D78: SJE5D96 | E78: 4500 | F78: 4144 | G78: 4144 | H78: Unidas
A79: STATKRAFT RSH | B79: GEFERSON | C79: TRACKER | D79: TEU0E78 | E79: 3000 | F79: 3837 | H79: Unidas
A80: STATKRAFT RSH | B80: IRANILDO | C80: TCROSS | D80: SWH5H35 | E80: 3000 | F80: 3837 | H80: Unidas
A81: STATKRAFT SFH | B81: AIRISMILA | C81: TCROSS | D81: TYA5C94 | E81: 3000 | F81: 3837 | H81: Unidas
A82: STATKRAFT SFH | B82: MARCELO OLIVEIRA | C82: CRETA | D82: TXW4I71 | E82: 3000 | F82: 3837 | H82: Unidas
K133: =K10:K133 -> 0
B134: COTAÇÃO VEICULOS
A135: VEICULO | B135: KM | C135: UNIDAS - maio | D135: Unidas - novembro | E135: NOVO ACORDO 05/2024 - loja franqueada | F135: VEICULO | H135: KM | I135: LOCALIZA | J135: PROTEÇÃO | K135: CIDADE
A136: Passeio Basico | B136: 3000 | C136: 2185.1 | D136: 2294.35 | E136: 2891,47 / 3004,20 | F136: Passeio Basico | H136: 3000 | I136: 2295.89 | J136: 2239.1 | K136: Salvador, Feira de Santa, Recife,Goiania, Ceara
A137: Passeio Basico | B137: 4500 | C137: 2359.61 | D137: 2477.59 | E137: 3122,84 / 3244,59 | F137: Passeio Basico | H137: 4000 | I137: 2382.91 | J137: 2312.35 | K137: Salvador, Feira de Santa, Recife,Goiania, Ceara
A138: Passeio Basico | B138: 5000 | C138: 2469.34 | D138: 2592.8 | E138: - | F138: Passeio Basico | H138: 5000 | I138: 2494.13 | J138: 2620.13 | K138: Salvador, Feira de Santa, Recife,Goiania, Ceara
A139: Passeio Basico | B139: 6000 | C139: 2578.02 | D139: 2706.92 | E139: - | F139: Passeio Basico | H139: 3000 | I139: 2353.01 | J139: 2607.08 | K139: Picos
A140: SUV 4X2 | B140: 3000 | C140: 3344 | D140: 3511.2 | E140: 4513,27 / 4642,80 | F140: Passeio Basico | H140: 4000 | I140: 2443.06 | J140: 2433.31 | K140: Picos
A141: SUV 4X2 | B141: 4500 | C141: 3611.52 | D141: 3792.09 | E141: 4873,29 / 5013,15 | F141: Passeio Basico | H141: 5000 | I141: 2555.95 | J141: 2528.4 | K141: Picos
A142: SUV 4X2 | B142: 5000 | C142: 3778.72 | D142: 3967.66 | E142: - | F142: Passeio Basico | H142: 3000 | I142: 2942.02 | J142: 3496.2 | K142: Juazeiro - BA, Petrolina
A143: SUV 4X2 | B143: 6000 | C143: 3945.92 | D143: 4143.22 | E143: - | F143: Passeio Basico | H143: 4000 | I143: 3264.91 | J143: 3724.22 | K143: Juazeiro - BA, Petrolina
A144: 4x4 | B144: 3000 | C144: 6583.5 | D144: 6912.67 | E144: 8884,34 / 9239,71 | F144: Passeio Basico | H144: 5000 | I144: 3321.02 | J144: 3927.17 | K144: Juazeiro - BA, Petrolina
A145: 4x4 | B145: 4500 | C145: 7110.18 | D145: 7465.69 | E145: 9595,36 / 9979,17 | F145: SUV 4X2 | H145: 3000 | I145: 3379.15 | J145: 3879.79 | K145: Salvador, Feira de Santa, Recife,Goiania, Ceara
A146: 4x4 | B146: 5000 | C146: 7439.36 | D146: 7811.33 | E146: - | F146: SUV 4X2 | H146: 4000 | I146: 3520.94 | J146: 4021.58 | K146: Salvador, Feira de Santa, Recife,Goiania, Ceara
A147: 4x4 | B147: 6000 | C147: 7768.53 | D147: 8156.96 | E147: - | F147: SUV 4X2 | H147: 5000 | I147: 3701.04 | J147: 4201.68 | K147: Salvador, Feira de Santa, Recife,Goiania, Ceara
A148: Passeio automatico | B148: 3000 | C148: 2810.01 | D148: 2919.56 | F148: SUV 4X2 | H148: 3000 | I148: 3463.15 | J148: 3799.15 | K148: Picos
A149: Passeio automatico | B149: 4500 | C149: 3034.68 | D149: 3152.99 | F149: SUV 4X2 | H149: 4000 | I149: 3608.98 | J149: 3944.98 | K149: Picos
A150: Passeio automatico | B150: 5000 | C150: 3175.76 | D150: 3299.57 | F150: SUV 4X2 | H150: 5000 | I150: 3794.11 | J150: 4130.11 | K150: Picos
...

Sheet Obras Diversas - Laboratorio
C1: LABORATÓRIO
A2: DATA DE USO | B2: PLACA | C2: CARRO | D2: TESTE DE FUMAÇA PRETA | E2: DATA SUBST. CARRO | F2: CARRO SUBSTITUIDO | G2: DATA SUBST. CARRO | H2: CARRO SUBSTITUIDO | I2: REBOQUE/TEREZA | J2: USUÁRIO | K2: LOCADORA | L2: OBRA | M2: DESTINO | N2: DATA FINALIZAÇÃO USO | O2: OBS
A3: 42668 | B3: PGS9869 | C3: S10 | E3: - | F3: - | J3: UFV BJ | K3: ACCESS | L3: 16020 | N3: 42669
A4: 42713 | B4: PGS 9869 | C4: S10 | E4: - | F4: - | J4: Carlos/Luis | K4: ACCESS | L4: 16023 | N4: 17.12.2016 | O4: Carro no galpão em 16.12
A5: 42821 | B5: PFY 4358 | C5: S10 | E5: - | F5: - | J5: LUIS | K5: ACCESS | L5: PIRAPORA | N5: 42831 | O5: Carro entregue em 25/03-mais uso a ser considerado a partir de 27/03-Entregue Felipe dia 07/04
A6: 42940 | B6: PGS 9869 | C6: S10 | E6: - | F6: - | J6: VICTOR | K6: ACCESS | L6: PIRAPORA | N6: 42951 | O6: Carro entregue em 24/07 - Retirada no galpão dia 07/08/2017
A7: 43046 | B7: PGS 9869 | C7: S10 | E7: - | F7: - | J7: VICTOR | K7: ACCESS | L7: S.J.BELMONTE | N7: 43052 | O7: Carro entregue em 13/11/2017 por Romero
A8: 43111 | B8: PFY 4358 | C8: 4 X 4 | E8: - | F8: - | I8: PDY6842 | J8: VICTOR | K8: ACCESS | L8: 18001 | M8: GUIMARANEA -MG | N8: 43126 | O8: Carro entregue por Edilson em 10/01 com problema freio de mão, retornou a entrega em 11/01
A9: 43154 | B9: PDA 1177 | C9: AMAROK 4X4 | E9: - | F9: - | J9: VICTOR | K9: ACCESS | L9: 18006 | N9: 43175 | O9: Entregue em 23/03/2018
A10: 43222 | B10: PDJ 2372 | C10: ONIX | E10: - | F10: - | J10: FERNANDA | K10: ACCESS | L10: 18011 | N10: 43224 | O10: Foi trocado dois óleos (aguardando foto) KM:32.119
A11: 43279 | B11: QNF 9482 | C11: ONIX | E11: - | F11: - | J11: VICTOR | K11: LOCALIZA | L11: 18014 | N11: 43279 | O11: Carro entregue Victor.28/06/2018
A12: 43286 | B12: GNI 6925 | C12: PRISMA | E12: - | F12: - | J12: VICTOR | K12: LOCALIZA | L12: 18015 | N12: 43286 | O12: Carro entregue Victor. 05/07/2018
A13: 43296 | B13: PCT 9415 | C13: 4 X 4 | E13: - | F13: - | I13: PDY6842 | J13: VICTOR | K13: ACCESS | L13: 18.016/18.018 e 18.019 | M13: S.JOAO GURGUEIA(PI)- DRACENA(SP) - CEILANDIA(DF) | N13: 43330 | O13: Acrescer uma diaria 12/07 e troca em 18/08/2018
A14: 43299 | B14: PGR 2514 | C14: 4 x 4 | E14: - | F14: - | I14: PDY 6842 | J14: VICTOR | K14: ACCESS | L14: 18017 | M14: SÃO JOAO DO PIAUI - PI | N14: 43363 | O14: Carro saiu em 08/09/2018 e entregue em dia 20/09/2018 e substituido pela S10 de placa PGS 9869 entregue no dia 21/09/2018
A15: 43346 | B15: QOR 2213 | C15: 4 x 2 | E15: - | F15: - | J15: JAMILE | K15: LOCALIZA | L15: 18020 | N15: 43374
A16: 43369 | B16: QMX 2231 | C16: ONIX | E16: - | F16: - | J16: VICTOR | K16: LOCALIZA | L16: 18026 | N16: 43370 | O16: CARRO ENTREGUE POR VARELA
A17: 43377 | B17: QMX 0135 | C17: UNO | E17: - | F17: - | J17: VICTOR | K17: LOCALIZA | L17: 18026 | N17: 43377 | O17: CARRO ENTREGUE POR VICTOR
A18: 43374 | B18: QNE 1560 | C18: S10 | E18: - | F18: - | J18: ANNE | K18: LOCALIZA | L18: 18024 | N18: 43414 | O18: CARRO ENTREGUE POR JAMILE/ANNE
A19: 43374 | B19: PZZ 0552 | C19: S10 | E19: - | F19: - | J19: JAMILE | K19: LOCALIZA | L19: 18024 | N19: 43379 | O19: CARRO ENTREGUE POR ANNE
A20: 43392 | B20: PZP 8902 | C20: S10 | E20: - | F20: - | J20: ALVES | K20: LOCALIZA | L20: 18029 | N20: 43409 | O20: CARRO ENTREGUE POR ALVES
A21: 43396 | B21: PDI 0158 | C21: AMAROK | E21: - | F21: - | I21: PDY 6842 | J21: VICTOR | K21: SUCESSO | L21: 18031 | M21: PEREIRA BARRETO - SP | N21: 43425 | O21: **11/11/2018 chegaram de viagem/ Carrro entregue por Fernanda
A22: 43425 | B22: QPJ 4916 | C22: GOL | E22: - | F22: - | J22: ALVES | K22: LOCALIZA | L22: 18029 | N22: 43430 | O22: CARRO ENTREGUE POR ALVES
A23: 43443 | B23: FKP 7088 | C23: GOL | E23: - | F23: - | J23: VICTOR | K23: LOCALIZA | L23: 18033 | N23: 43445 | O23: CARRO ENTREGUE POR VICTOR
A24: 43588 | B24: QQF 5990 | C24: S10 | I24: PDY 6842 | J24: VICTOR HUGO | K24: UNIDAS | L24: Obra 19.004 | M24: PAULO AFONSO - BA | N24: 43605 | O24: chegou sexta dia 17/05 - 17/05 seguiu conserto
A25: 43592 | B25: QPM 4740 | C25: HILUX | J25: FERNANDA TOLENTINO | K25: UNIDAS | L25: Obra 19.006 | N25: 43599 | O25: Chegou sexta 10/05 - 13/05 seguiu para conserto
A26: 43595 | B26: QPM 4740 | C26: HILUX | I26: PDY 6842 | J26: RAFAEL GOMES | K26: UNIDAS | L26: Obra 19.007 | M26: DELMIRO GOUVEIA(AL) E CEILANDIA - DF | N26: 43602
A27: 43633 | B27: QPM 4740 | C27: HILUX | E27: - | F27: - | I27: PDY 6842 | J27: RAFAEL GOMES | K27: UNIDAS | L27: Obra 19.010 | M27: TORRINHA E EMBUGUAÇU - SP | N27: 43644 | O27: Carro entregue por Victor - sem avarias
A28: 43654 | B28: QQF 5990 | C28: S10 | I28: PDY 6842 | J28: MARCOS DA COSTA | K28: UNIDAS | L28: Obra 19.013 | M28: RIO DO PEIXE - PB | N28: 43661 | O28: Carro chegou no sábado dia 13/07,porém precisava tirar o reboque e lavar, por issoa entrega na segunda 15/07
A29: 43682 | B29: QQF 5990 | C29: S10 | E29: 43698 | F29: RANGER - QOW 9208 | I29: PDY 6842 | J29: MARCOS DA COSTA | K29: UNIDAS | L29: Obra 19.015/19.017 | M29: ARAXA - MG | N29: 43706 | O29: Troca devido a embreagem parar de funcionar
A30: 43683 | B30: QQY 1385 | C30: SAVEIRO | J30: VICTOR HUGO | K30: UNIDAS | L30: Obra 19.016 | N30: 43704
A31: 43717 | B31: QUE 8657 | C31: PRISMA | E31: - | F31: - | J31: MARCELO PORTUGAL | K31: LOCALIZA | L31: Consorcio Conen | N31: 43728
A32: 43742 | B32: QUJ 5225 | C32: AMAROK | J32: VICTOR HUGO | K32: UNIDAS | L32: Obra 19.015 | N32: 43754 | O32: Carro chegou no dia 15/09 às 17:00
A33: 43612 | B33: PDU 4368 | C33: AMAROK | E33: 43766 | F33: S10 - QPI 4065 | J33: SOLA | K33: LOCALIZA | L33: Obra 18.030 | N33: 43766 | O33: Carro com para-brisas trincado , ar não funciona
A34: 43794 | B34: QUT 0500 | C34: STRADA | J34: MARCOS DA COSTA | K34: UNIDAS | L34: Obra 19.001
A35: 43809 | B35: PCE 8966 | C35: GOL | J35: FELIPE HIPOLITO | K35: LOCALIZA | L35: Obra 19.011 | N35: 43813 | O35: Entregue por Felipe
A36: 43836 | B36: QUJ 2156 | C36: ECOSPORT | J36: NILO CESAR | K36: UNIDAS | L36: CONSORCIO CONEN | N36: 43847
A37: 43846 | B37: QPM 2436 | C37: HILUX | I37: PDY 6842 | J37: MARCOS DA COSTA | K37: UNIDAS | L37: Obra 19.009 | M37: BARREIRAS/BA | N37: 43908 | O37: Carro foi entregue a Rafael em 01/02/ Carro com avarias, chegou ao galpão dia 13/03
A38: 43860 | B38: QUK 8329 | C38: S10 | J38: VICTOR HUGO | K38: LOCALIZA | L38: OBRA 20.001 | N38: 43902 | O38: Carro chegou no galpão dia 08/03/ Devolvido por Marcos
A39: 43860 | B39: QWR 0464 | C39: S10 | J39: RAFAEL GOMES | K39: LOCALIZA | L39: OBRA 20.001 | N39: 43901 | O39: Carro foi entregue a Marcos em 01/02/2020 - Carro chegou no galpão dia 07/03 e foi para revitalização/ Devolvido por Marcos
A40: 44021 | B40: QUT 0507 | C40: STRADA | J40: MARCOS DA COSTA | K40: UNIDAS | L40: - | N40: 44022 | O40: Carro locado para levar o reboque para manutenção
A41: 44025 | B41: QXJ 4082 | C41: S10 | J41: MARCOS DA COSTA | K41: UNIDAS | L41: 20018/20.019 | N41: 44049 | O41: Carro chegou no galpao em 15/07, com problemas na embreagem e parabrisa trincado
A42: 44074 | B42: QXJ8548 | C42: GOL | J42: MARCOS DA COSTA | K42: UNIDAS | L42: 20019 | N42: 44078
A43: 44082 | B43: RFG1D16 | C43: TORO | J43: MARCOS DA COSTA | K43: UNIDAS | L43: 20018/ 20.019 | N43: 44112
A44: 44090 | B44: PCF 6905 | C44: S10 | J44: JOSE DIEGO DIAS | K44: SOLUÇÕES RENT A CAR | L44: 20019 | M44: COREMAS/PB | N44: 44099 | O44: Carro chegou ao galpao em 25/09
A45: 44090 | B45: QUC 6650 | C45: ONIX | J45: GILSON BUENO | K45: LOCALIZA | L45: 20017 | N45: 44091
A46: 44106 | B46: RFM6G06 | C46: S10 | I46: PDY 6842 | J46: RAFAEL GOMES/MARCOS | K46: UNIDAS | L46: 20.024/20.025 | M46: UIBAI/BA
A47: 44118 | B47: QXD 0460 | C47: ONIX | J47: GILSON BUENO | K47: LOCALIZA | L47: 20017 | N47: 44119
A48: 44145 | B48: QUH 6804 | C48: RENEGADE | J48: GILSON BUENO | K48: LOCALIZA | L48: 20017
A49: 44153 | B49: RFM6F94 | C49: S10 | I49: PDY 6842 | J49: RAFAEL GOMES | K49: UNIDAS | L49: 20.029/20.030/20.031 | M49: DOM INOCENCIO/PI - SÃO JOSE DO BELMONTE/PE - ITAPORANGA/PB | N49: 44186
A50: 44169 | B50: QXI 5442 | C50: POLO | J50: JOSE DIEGO DIAS | K50: UNIDAS | N50: 44176
A51: 44173 | B51: QXA4841 | C51: ACTIVE | J51: GILSON BUENO | K51: LOCALIZA | L51: 20017 | N51: 44175
A52: 44208 | B52: QUI3383 | C52: HB20S | J52: GILSON BUENO | K52: LOCALIZA | L52: 20017 | N52: 44211
A53: 44222 | B53: RFP9B76 | C53: S10 | F53: RFN1A96 S10 | I53: PDY 6842 | J53: ADALBERTO ARAUJO | K53: UNIDAS | L53: 21004 | M53: PIRAPORA/MG | N53: 44303 | O53: O veículo chegou no galpão, porém só seguiu viagem dia 28/01
A54: 44236 | B54: QUY 9228 | C54: LOGAN | J54: GILSON BUENO | K54: LOCALIZA | L54: 20017
A55: 44241 | B55: QWS 6816 | C55: S10 | J55: DIEGO DIAS | K55: UNIDAS | L55: 20005 | N55: 44246
A56: 44327 | B56: RFQ1A68 | C56: TORO | J56: THIAGO/DEBORA | K56: LOCALIZA | L56: Of 21039 E OBRA 21015 | N56: 44340 | O56: Utilizado dia 11 para proposta e seguiu equipe lab dia 12
A57: 44328 | B57: QYT2J73 | C57: S10 | I57: PDY 6842 | J57: EDILSON | K57: SOLUÇOES RENT A CAR | L57: Obra 21.013/ 21.015 | M57: LAGOA DO BARRO/PI | N57: 44358
A58: 44354 | B58: QWS6816 | C58: RANGER | I58: PDY 6842 | J58: ADALBERTO ARAUJO | K58: UNIDAS | L58: 21007 | M58: LAGARTO/SE | N58: 44358
A59: 44368 | B59: RNC0G24 | C59: LOGAN | J59: ALEX RAMOS | K59: UNIDAS | L59: 21008 | N59: 44370
A60: 44398 | B60: QUJ8045 | C60: ONIX | J60: ALEX RAMOS | K60: LOCALIZA | L60: 21008 | N60: 44400
A61: 44398 | B61: RFT0H82 | C61: TORO | J61: ALEX RAMOS | K61: UNIDAS | L61: 21019 | N61: 44480 | O61: Veículo foi usado por Diego e Débora (a partir de 08/09)
A62: 44407 | B62: QXJ 4082 | C62: S10 | I62: PDY 6842 | J62: ADALBERTO ARAUJO | K62: UNIDAS | L62: 21019 | M62: FLORESTA/PE | N62: 44414
A63: 44449 | B63: RFV8H14 | C63: S10 | J63: ALEX RAMOS | K63: UNIDAS | L63: 21022 | N63: 44489 | O63: Veículo foi repassado para Tony e Edilson
A64: 44461 | B64: QQD 7740 | C64: SAVEIRO | J64: ADALBERTO ARAUJO | K64: UNIDAS | L64: 21024 | N64: 44466
A65: 44466 | B65: RNS5H18 | C65: S10 | J65: ADALBERTO ARAUJO | K65: UNIDAS | L65: 21024 | N65: 44478
A66: 44503 | B66: RFJ8C80 | C66: FIORINO | J66: RAFAEL | K66: UNIDAS | L66: 21025 | N66: 44505
A67: 44505 | B67: RNS3B89 | C67: S10 | I67: PDY 6842 | J67: ADALBERTO ARAUJO | K67: UNIDAS | L67: 21020 | M67: SÃO JOAO DO PIAUI/PI | N67: 44550
A68: 44510 | B68: RFH1C71 | C68: TORO | J68: RAFAEL | K68: UNIDAS | L68: 21027 | N68: 44510
A69: 44515 | B69: RGD7A64 | C69: VOYAGE | J69: ALEX RAMOS | K69: UNIDAS | L69: 20024 | N69: 44518
A70: 44565 | B70: RNR0E79 | C70: S10 | I70: PDY 6842 | J70: RAFAEL | K70: UNIDAS | L70: 22201 | M70: OUROESTE/SP | N70: 44600
A71: 44571 | B71: RNX7H29 | C71: S10 | J71: ADALBERTO | K71: UNIDAS | L71: 22202 | N71: 44579
A72: 44634 | B72: FVA6A54 | C72: FRONTIER | J72: ADALBERTO | K72: MOVIDA | L72: 22009 | N72: 44641
A73: 44641 | B73: RNS3B85 | C73: S10 | J73: ALEX | K73: UNIDAS | L73: 22010 | N73: 44674 | O73: Veículo passou para Tony e Edilson em 25/03
A74: 44649 | B74: RTN5B43 | C74: S10 | J74: DIEGO | K74: MOVIDA | L74: 22011 | N74: 44653
A75: 44655 | B75: RLM6H19 | C75: S10 | J75: ALEX | K75: MOVIDA | L75: 22010 | N75: 44685
A76: 44658 | B76: RNS3B86 | C76: S10 | J76: ADALBERTO | K76: UNIDAS | L76: 22010 | N76: 44669
A77: 44678 | B77: RFW2C76 | C77: S10 | J77: DIEGO | K77: UNIDAS | N77: 44701
A78: 44739 | B78: RNR1J94 | C78: S10 | J78: DIEGO | K78: UNIDAS | L78: 22020 | N78: 44741
A79: 44741 | B79: RTN5G47 | C79: S10 | J79: DEBORA | K79: MOVIDA | L79: Oferta 22052 | N79: 44743
A80: 44753 | B80: RNF0D39 | C80: TORO | J80: THIAGO | K80: LOCALIZA | L80: 22019 | N80: 44756
A81: 44755 | B81: RNS3B85 | C81: 4X4 | J81: ADALBERTO | K81: UNIDAS | L81: 22020 e 22022 | N81: 44789 | O81: Veículo entregue em Natal - Utilizado pelo Enio do período de 12 a 16/08
A82: 44760 | B82: RNV8E63 | C82: 4X4 | J82: EDILSON | K82: UNIDAS | L82: 22025 e 22026 | N82: 44974
A83: 44765 | B83: RNC2I08 | C83: 4X4 | J83: RAFAEL | K83: LOCALIZA | L83: 22025 e 22015 | O83: Veículo retirado por Diego em Joao Pessoa/ Usado na obra 22025 por Rafael, Alex e Débora e 22015 Bruno e Yury
A84: 44776 | B84: RTR1D86 | C84: passeio | J84: ALEX | K84: LOCALIZA | L84: 22025 | N84: 44777 | O84: Veículo devolvido pela Débora
A85: 44781 | B85: RGB1J33 | C85: 4x4 | J85: DIEGO | K85: LOCALIZA | L85: 22022 | N85: 44785
A86: 44787 | B86: RZJ1E52 | C86: 4x2 | J86: ALEX | K86: LOCALIZA | L86: 22006 | N86: 44792
A87: 44809 | B87: RUQ4E88 | C87: 4x4 | E87: 44814 | F87: RUQ4E88 | G87: 44838 | H87: L200 - RUS7F37 | J87: ADALBERTO/ JOSE | K87: UNIDAS | L87: 22030 | O87: Veículo retirado por Rafael/ Veículo utilizado por Adalberto a partir de 18/10
A88: 44814 | B88: RNE8D11 | C88: 4x4 | J88: ADRIELLY | K88: UNIDAS | L88: 22005 | N88: 44827
A89: 44825 | B89: RMK9F03 | C89: RENEGADE | J89: ALEX | K89: UNIDAS | L89: 22010 | N89: 44827
A90: 44841 | B90: RNR6D47 | C90: HB20X | J90: DIEGO | K90: UNIDAS | L90: 22034 | N90: 44842
A91: 44843 | B91: RTO5B28 | C91: 208 | J91: ALEX | K91: UNIDAS | L91: 22006 | N91: 44847
A92: 45216 | B92: RUS7F47 | C92: L200 | J92: ADALBERTO | K92: UNIDAS | N92: 45289
A93: 44851 | B93: RMO9E65 | C93: VOYAGE | J93: MELK | K93: UNIDAS | L93: 22015 | N93: 44856
A94: 44858 | B94: RFZ1H62 | C94: S10 | J94: ALEX | K94: UNIDAS | N94: 44860 | O94: Veículo guinchado
A95: 44867 | B95: RVH1F34 | C95: TRACKER | J95: JOSE ALVES | K95: LOCALIZA | L95: 22015
A96: 44869 | B96: RUH2G23 | C96: L200 | J96: RAFAEL | K96: UNIDAS | N96: 44947
A97: 44871 | B97: RUS7G17 | C97: L200 | E97: 44943 | F97: L200 RMJ6B94 | J97: DIEGO | K97: UNIDAS | L97: 22.029/22.010 | N97: 45000 | O97: Veículo utilizado por Diego de 06/11 a 21/11 - Veículo utilizado pelo Jose Alves a partir de 22/11
A98: 44906 | B98: RFP9C09 | C98: S10 | J98: DIEGO | K98: UNIDAS | L98: 22010 | N98: 44910
A99: 44921 | B99: RVD2F82 | C99: C3 | J99: ALEX | K99: LOCALIZA | L99: 22014
A100: 44942 | B100: RUH9H42 | C100: Fiorino | J100: JOSE ALVES | K100: LOCALIZA | L100: 23003 | M100: APARECIDA DO TABOADO/MS | N100: 44947
...

Sheet Controle Combustivel
C1: OBRAS ATIVA | D1: VEÍCULOS ATIVO | E1: RESUMO DO CONTROLE DE COMBUSTÍVEL | AQ1: DATA DE ATUALIZAÇÃO
C2: =COUNTIF(E5:E82,"ATIVA") -> 8 | D2: =SUM(D5:D82) -> 8 | AQ2: 45348
A3: OBRA | B3: LOCAL | D3: QUANTIDADE VEÍCULO | E3: SITUAÇÃO DA OBRA | F3: ACUMULADO ABAST. | G3: JANEIRO | J3: FEVEREIRO | M3: MARÇO | P3: ABRIL | S3: MAIO | V3: JUNHO | Y3: JULHO | AB3: AGOSTO | AE3: SETEMBRO | AH3: OUTUBRO | AK3: NOVEMBRO | AN3: DEZEMBRO | AQ3: OBSERVAÇÕES
G4: KM | H4: QTD ABAST. | I4: VALOR TOTAL | J4: KM | K4: QTD ABAST. | L4: VALOR TOTAL | M4: KM | N4: QTD ABAST. | O4: VALOR TOTAL | P4: KM | Q4: QTD ABAST. | R4: VALOR TOTAL | S4: KM | T4: QTD ABAST. | U4: VALOR TOTAL | V4: KM | W4: QTD ABAST. | X4: VALOR TOTAL | Y4: KM | Z4: QTD. ABAST. | AA4: VALOR TOTAL | AB4: KM | AC4: QTD. ABAST. | AD4: VALOR TOTAL | AE4: KM | AF4: QTD. ABAST. | AG4: VALOR TOTAL | AH4: KM | AI4: QTD. ABAST. | AJ4: VALOR TOTAL | AK4: KM | AL4: QTD. ABAST. | AM4: VALOR TOTAL | AN4: KM | AO4: QTD. ABAST. | AP4: VALOR TOTAL
A5: 22023 | B5: ENG. AGRONOMO | D5: =COUNTIF('22039_ARINOS'!D5:D24,"ATIVO") -> 0 | E5: ATIVA | F5: =SUM(H5+K5+N5+Q5+T5+W5+Z5+AC5+AF5+AI5+AL5+AO5) -> 70 | G5: =SUM('22039_ARINOS'!G5:G6) -> 3433 | H5: =SUM('22039_ARINOS'!H5:H6) -> 2 | I5: =SUM('22039_ARINOS'!J5:J6) -> 745.95 | J5: =SUM('22039_ARINOS'!G7:G8) -> 3319 | K5: =SUM('22039_ARINOS'!H7:H8) -> 7 | L5: =SUM('22039_ARINOS'!J7:J8) -> 1683.72 | M5: =SUM('22039_ARINOS'!G9:G10) -> 4673 | N5: =SUM('22039_ARINOS'!H9:H10) -> 9 | O5: =SUM('22039_ARINOS'!J9:J10) -> 2344.12 | P5: =SUM('22039_ARINOS'!G11:G13) -> 3922 | Q5: =SUM('22039_ARINOS'!H11:H13) -> 11 | R5: =SUM('22039_ARINOS'!J11:J13) -> 2734.83 | S5: =SUM('22039_ARINOS'!G14:G15) -> 5004 | T5: =SUM('22039_ARINOS'!H14:H15) -> 5 | U5: =SUM('22039_ARINOS'!J14:J15) -> 1603.34 | V5: =SUM('22039_ARINOS'!G16) -> 2610 | W5: =SUM('22039_ARINOS'!H16) -> 4 | X5: =SUM('22039_ARINOS'!J16) -> 1458.97 | Y5: =SUM('22039_ARINOS'!G17:G18) -> 4186 | Z5: =SUM('22039_ARINOS'!H17:H18) -> 6 | AA5: =SUM('22039_ARINOS'!J17:J18) -> 2712.12 | AB5: =SUM('22039_ARINOS'!G19:G20) -> 6455 | AC5: =SUM('22039_ARINOS'!H19:H20) -> 13 | AD5: =SUM('22039_ARINOS'!H19:J20) -> 4394.25 | AE5: =SUM('22039_ARINOS'!G21:G22) -> 4903 | AF5: =SUM('22039_ARINOS'!H21:H22) -> 13 | AG5: =SUM('22039_ARINOS'!H21:J22) -> 3990.101
A6: 22007 | B6: LDV-V | D6: =COUNTIF('22007_LDV-V'!D3:D47,"ATIVO") -> 2 | E6: ATIVA | F6: =SUM(H6+K6+N6+Q6+T6+W6+Z6+AC6+AF6+AI6+AL6+AO6) -> 157 | G6: =SUM('22007_LDV-V'!G3:G10) -> 21980 | H6: =SUM('22007_LDV-V'!I3:I10) -> 29 | I6: =SUM('22007_LDV-V'!H3:H10) -> 7071.16 | J6: =SUM('22007_LDV-V'!G11:G17) -> 14221 | K6: =SUM('22007_LDV-V'!I11:I17) -> 18 | L6: =SUM('22007_LDV-V'!H11:H17) -> 4173.11 | M6: =SUM('22007_LDV-V'!G18:G21) -> 10784 | N6: =SUM('22007_LDV-V'!I18:I21) -> 19 | O6: =SUM('22007_LDV-V'!H18:H21) -> 3674.26 | P6: =SUM('22007_LDV-V'!G22:G25) -> 10094 | Q6: =SUM('22007_LDV-V'!I22:I25) -> 19 | R6: =SUM('22007_LDV-V'!H22:H25) -> 3461.17 | S6: =SUM('22007_LDV-V'!G26:G28) -> 8629 | T6: =SUM('22007_LDV-V'!I26:I28) -> 18 | U6: =SUM('22007_LDV-V'!H26:H28) -> 3283.73 | V6: =SUM('22007_LDV-V'!G29:G31) -> 7953 | W6: =SUM('22007_LDV-V'!I29:I31) -> 15 | X6: =SUM('22007_LDV-V'!H29:H31) -> 2788.51 | Y6: =SUM('22007_LDV-V'!G32:G34) -> 9416 | Z6: =SUM('22007_LDV-V'!I32:I34) -> 16 | AA6: =SUM('22007_LDV-V'!H32:H34) -> 3189.14 | AB6: =SUM('22007_LDV-V'!G35:G37) -> 6798 | AC6: =SUM('22007_LDV-V'!I35:I37) -> 15 | AD6: =SUM('22007_LDV-V'!H35:H37) -> 2899.27 | AE6: =SUM('22007_LDV-V'!G38:G40) -> 9254 | AF6: =SUM('22007_LDV-V'!I38:I40) -> 8 | AG6: =SUM('22007_LDV-V'!I38:I40) -> 8
A7: 23018 | B7: IBIMIRIM | D7: 4 | E7: ATIVA | F7: =SUM(H7+K7+N7+Q7+T7+W7+Z7+AC7+AF7+AI7+AL7+AO7) -> 217 | G7: =SUM('23018_IBIMIRIM'!G3:G7) -> 13920 | H7: =SUM('23018_IBIMIRIM'!I3:I7) -> 39 | I7: =SUM('23018_IBIMIRIM'!H3:H7) -> 7822 | J7: =SUM('23018_IBIMIRIM'!G8:G13) -> 9298 | K7: =SUM('23018_IBIMIRIM'!I8:I13) -> 28 | L7: =SUM('23018_IBIMIRIM'!H8:H13) -> 6023.17 | M7: =SUM('23018_IBIMIRIM'!G14:G21) -> 13843 | N7: =SUM('23018_IBIMIRIM'!I14:I21) -> 23 | O7: =SUM('23018_IBIMIRIM'!H14:H21) -> 5401.18 | P7: =SUM('23018_IBIMIRIM'!G22:G26) -> 10038 | Q7: =SUM('23018_IBIMIRIM'!I22:I26) -> 20 | R7: =SUM('23018_IBIMIRIM'!H22:H26) -> 3627.57 | S7: =SUM('23018_IBIMIRIM'!G27:G31) -> 7338 | T7: =SUM('23018_IBIMIRIM'!I27:I31) -> 24 | U7: =SUM('23018_IBIMIRIM'!H27:H31) -> 4469.63 | V7: =SUM('23018_IBIMIRIM'!G32:G35) -> 7489 | W7: =SUM('23018_IBIMIRIM'!I32:I35) -> 20 | X7: =SUM('23018_IBIMIRIM'!H32:H35) -> 3574.37 | Y7: =SUM('23018_IBIMIRIM'!G36:G40) -> 8352 | Z7: =SUM('23018_IBIMIRIM'!I36:I40) -> 20 | AA7: =SUM('23018_IBIMIRIM'!H36:H40) -> 3725.82 | AB7: =SUM('23018_IBIMIRIM'!G41:G44) -> 9716 | AC7: =SUM('23018_IBIMIRIM'!I41:I44) -> 22 | AD7: =SUM('23018_IBIMIRIM'!H41:H44) -> 3875.31 | AE7: =SUM('23018_IBIMIRIM'!G45:G48) -> 6178 | AF7: =SUM('23018_IBIMIRIM'!I45:I48) -> 21 | AG7: =SUM('23018_IBIMIRIM'!H45:H48) -> 3597.97
A8: 23026 | B8: RETROFIT LAGOA CGN | D8: =COUNTIF('23026_LAGOA_CGN'!D3:D13,"ATIVO") -> 0 | E8: ATIVA | F8: =SUM(H8+K8+N8+Q8+T8+W8+Z8+AC8+AF8+AI8+AL8+AO8) -> 85 | G8: =SUM('23026_LAGOA_CGN'!G3:G5) -> 9806 | H8: =SUM('23026_LAGOA_CGN'!I3:I5) -> 13 | I8: =SUM('23026_LAGOA_CGN'!H3:H5) -> 3159.99 | J8: =SUM('23026_LAGOA_CGN'!G6:G7) -> 6733 | K8: =SUM('23026_LAGOA_CGN'!I6:I7) -> 14 | L8: =SUM('23026_LAGOA_CGN'!H6:H7) -> 3037.36 | M8: =SUM('23026_LAGOA_CGN'!G8:G9) -> 7358 | N8: =SUM('23026_LAGOA_CGN'!I8:I9) -> 14 | O8: =SUM('23026_LAGOA_CGN'!H8:H9) -> 2870.45 | P8: =SUM('23026_LAGOA_CGN'!G10) -> 3327 | Q8: =SUM('23026_LAGOA_CGN'!I10) -> 10 | R8: =SUM('23026_LAGOA_CGN'!H10) -> 1798.46 | S8: =SUM('23026_LAGOA_CGN'!G12) -> 3148 | T8: =SUM('23026_LAGOA_CGN'!I12) -> 10 | U8: =SUM('23026_LAGOA_CGN'!H12) -> 1562.64 | V8: =SUM('23026_LAGOA_CGN'!G13) -> 2997 | W8: =SUM('23026_LAGOA_CGN'!I13) -> 9 | X8: =SUM('23026_LAGOA_CGN'!H13) -> 2053.27 | Y8: =SUM('23026_LAGOA_CGN'!G14:G15) -> 6808 | Z8: =SUM('23026_LAGOA_CGN'!I14:I15) -> 10 | AA8: =SUM('23026_LAGOA_CGN'!H14:H15) -> 2290.77 | AB8: =SUM('23026_LAGOA_CGN'!H6) -> 1777.53 | AC8: 5 | AD8: =SUM('23026_LAGOA_CGN'!G16) -> 1298
A9: 22005 | B9: MAPEAMENTO DE IMÓVEIS | D9: =COUNTIF('22005_MAPEAMENTO'!D5:D14,"ATIVO") -> 0 | E9: ATIVA | F9: =SUM(H9+K9+N9+Q9+T9+W9+Z9+AC9+AF9+AI9+AL9+AO9) -> 40 | G9: =SUM('22005_MAPEAMENTO'!G5:G7) -> 6790 | H9: =SUM('22005_MAPEAMENTO'!K5:K7) -> 15 | I9: =SUM('22005_MAPEAMENTO'!H5:H7) -> 3110.47 | J9: =SUM('22005_MAPEAMENTO'!G8:G9) -> 3600 | K9: =SUM('22005_MAPEAMENTO'!K8:K9) -> 8 | L9: =SUM('22005_MAPEAMENTO'!H8:H9) -> 2126.45 | M9: =SUM('22005_MAPEAMENTO'!G10:G11) -> 5422 | N9: =SUM('22005_MAPEAMENTO'!K10:K11) -> 10 | O9: =SUM('22005_MAPEAMENTO'!H10:H11) -> 2274.21 | P9: =SUM('22005_MAPEAMENTO'!G12:G13) -> 3024 | Q9: =SUM('22005_MAPEAMENTO'!K12:K13) -> 6 | R9: =SUM('22005_MAPEAMENTO'!H12:H13) -> 1594.26 | S9: =SUM('22005_MAPEAMENTO'!H12:H13) -> 1594.26 | T9: =SUM('22005_MAPEAMENTO'!K14) -> 1 | U9: =SUM('22005_MAPEAMENTO'!H14) -> 276.97
A10: 21029 | B10: ENEL GOIANIA | D10: 2 | E10: ATIVA | F10: =SUM(H10+K10+N10+Q10+T10+W10+Z10+AC10+AF10+AI10+AL10+AO10) -> 45 | G10: =SUM('21029_ENEL GOIANIA'!G5:G6) -> 1993 | H10: =SUM('21029_ENEL GOIANIA'!K5:K6) -> 8 | I10: =SUM('21029_ENEL GOIANIA'!H5:H6) -> 966.71 | J10: =SUM('21029_ENEL GOIANIA'!G7:G8) -> 1074 | K10: =SUM('21029_ENEL GOIANIA'!K7:K8) -> 4 | L10: =SUM('21029_ENEL GOIANIA'!H7:H8) -> 505.1 | M10: =SUM('21029_ENEL GOIANIA'!G9:G10) -> 2139 | N10: =SUM('21029_ENEL GOIANIA'!K9:K10) -> 6 | O10: =SUM('21029_ENEL GOIANIA'!H9:H10) -> 955.29 | P10: =SUM('21029_ENEL GOIANIA'!G11:G12) -> 1899 | Q10: =SUM('21029_ENEL GOIANIA'!K11:K12) -> 8 | R10: =SUM('21029_ENEL GOIANIA'!H11:H12) -> 1310.95 | S10: =SUM('21029_ENEL GOIANIA'!G13:G14) -> 1520 | T10: =SUM('21029_ENEL GOIANIA'!K13:K14) -> 4 | U10: =SUM('21029_ENEL GOIANIA'!H13:H14) -> 430.12 | V10: =SUM('21029_ENEL GOIANIA'!G15:G16) -> 1055 | W10: =SUM('21029_ENEL GOIANIA'!K15:K16) -> 3 | X10: =SUM('21029_ENEL GOIANIA'!H15:H16) -> 540.89 | Y10: =SUM('21029_ENEL GOIANIA'!G17:G18) -> 1633 | Z10: =SUM('21029_ENEL GOIANIA'!K17:K18) -> 4 | AA10: =SUM('21029_ENEL GOIANIA'!H17:H18) -> 996.91 | AB10: =SUM('21029_ENEL GOIANIA'!G19:G20) -> 1806 | AC10: =SUM('21029_ENEL GOIANIA'!K19:K20) -> 5 | AD10: =SUM('21029_ENEL GOIANIA'!H19:H20) -> 916.668 | AE10: =SUM('21029_ENEL GOIANIA'!G21:G22) -> 1130 | AF10: =SUM('21029_ENEL GOIANIA'!K21:K22) -> 3 | AG10: =SUM('21029_ENEL GOIANIA'!H21:H22) -> 541.6
A11: 19018 | B11: FURNAS ANGRA | D11: =COUNTIF('19018_F.Angra'!D5:D17,"ATIVO") -> 0 | E11: ATIVA | F11: =SUM(H11+K11+N11+Q11+T11+W11+Z11+AC11+AF11+AI11+AL11+AO11) -> 35 | G11: =SUM('19018_F.Angra'!G5:G6) -> 4222 | H11: =SUM('19018_F.Angra'!K5:K6) -> 6 | I11: =SUM('19018_F.Angra'!H5:H6) -> 1800 | J11: =('19018_F.Angra'!G7) -> 2768 | K11: =('19018_F.Angra'!K7) -> 5 | L11: =('19018_F.Angra'!H7) -> 1200.01 | M11: =('19018_F.Angra'!G8) -> 2655 | N11: =('19018_F.Angra'!K8) -> 6 | O11: =('19018_F.Angra'!H8) -> 1250 | P11: =('19018_F.Angra'!G9) -> 1727 | Q11: =('19018_F.Angra'!K9) -> 4 | R11: =('19018_F.Angra'!H9) -> 950 | S11: =('19018_F.Angra'!G10) -> 2135 | T11: =('19018_F.Angra'!K10) -> 3 | U11: =('19018_F.Angra'!H10) -> 1000 | V11: =('19018_F.Angra'!G11) -> 1832 | W11: =('19018_F.Angra'!K11) -> 4 | X11: =('19018_F.Angra'!H11) -> 1000 | Y11: =('19018_F.Angra'!G12) -> 1983 | Z11: =('19018_F.Angra'!K12) -> 5 | AA11: =('19018_F.Angra'!H12) -> 1080.1 | AB11: =('19018_F.Angra'!G13) -> 1517 | AC11: =('19018_F.Angra'!K13) -> 2 | AD11: =('19018_F.Angra'!H13) -> 700
A12: 20017 | B12: DNIT | D12: =COUNTIF('20017_DNIT'!D5:D28,"ATIVO") -> 0 | E12: DESATIVADA | F12: =SUM(H12+K12+N12+Q12+T12+W12+Z12+AC12+AF12+AI12+AL12+AO12) -> 14 | G12: =SUM('20017_DNIT'!G5:G6) -> 2582 | H12: =SUM('20017_DNIT'!K5:K6) -> 0 | I12: =SUM('20017_DNIT'!H5:H6) -> 1035.58 | J12: =SUM('20017_DNIT'!G7:G8) -> 2663 | K12: 4 | L12: =SUM('20017_DNIT'!H7:H8) -> 1037.74 | M12: =SUM('23026_LAGOA_CGN'!G12:G12) -> 3148 | N12: =SUM('23026_LAGOA_CGN'!I12:I12) -> 10 | O12: =SUM('23026_LAGOA_CGN'!H12:H12) -> 1562.64
A13: - | B13: ARO | D13: =COUNTIF('0000_ARO'!D3:D33,"ATIVO") -> 0 | E13: DESATIVADA | F13: =SUM(H13+K13+N13+Q13+T13+W13+Z13+AC13+AF13+AI13+AL13+AO13) -> 7070 | G13: =SUM('0000_ARO'!D3:D3) -> 0 | H13: =SUM('0000_ARO'!F3:F3) -> 7062 | I13: =SUM('0000_ARO'!E3:E3) -> 4907 | J13: =('0000_ARO'!G3) -> 2155 | K13: =('0000_ARO'!I3) -> 4 | L13: =('0000_ARO'!H3) -> 1141.65 | M13: =('0000_ARO'!G4) -> 2038 | N13: =('0000_ARO'!I4) -> 4 | O13: =('0000_ARO'!H4) -> 987.56
A14: - | B14: OBRA_LABORATÓRIO | E14: ATIVA | F14: =SUM(H14+K14+N14+Q14+T14+W14+Z14+AC14+AF14+AI14+AL14+AO14) -> 9 | M14: =SUM('23026_LAGOA_CGN'!G13:G13) -> 2997 | N14: =SUM('23026_LAGOA_CGN'!I13:I13) -> 9 | O14: =SUM('23026_LAGOA_CGN'!H13:H13) -> 2053.27
A15: TOTAL GERAL | F15: =SUBTOTAL(9,F5:F14) -> 7742 | G15: =SUBTOTAL(9,G5:G14) -> 64726 | H15: =SUBTOTAL(9,H5:H14) -> 7174 | I15: =SUBTOTAL(9,I5:I14) -> 30618.86 | J15: =SUBTOTAL(9,J5:J14) -> 45831 | K15: =SUBTOTAL(9,K5:K14) -> 92 | L15: =SUBTOTAL(9,L5:L14) -> 20928.31 | M15: =SUBTOTAL(9,M5:M14) -> 55057 | N15: =SUBTOTAL(9,N5:N14) -> 110 | O15: =SUM(O5:O14) -> 23372.98 | P15: =SUBTOTAL(9,P5:P14) -> 34031 | Q15: =SUBTOTAL(9,Q5:Q14) -> 78 | R15: =SUM(R5:R14) -> 15477.24 | S15: =SUBTOTAL(9,S5:S14) -> 29368.26 | T15: =SUBTOTAL(9,T5:T14) -> 65 | U15: =SUM(U5:U14) -> 12626.43 | V15: =SUBTOTAL(9,V5:V14) -> 23936 | W15: =SUBTOTAL(9,W5:W14) -> 55 | X15: =SUM(X5:X14) -> 11416.01 | Y15: =SUBTOTAL(9,Y5:Y14) -> 32378 | Z15: =SUBTOTAL(9,Z5:Z14) -> 61 | AA15: =SUM(AA5:AA14) -> 13994.86 | AB15: =SUBTOTAL(9,AB5:AB14) -> 28069.53 | AC15: =SUBTOTAL(9,AC5:AC14) -> 62 | AD15: =SUM(AD5:AD14) -> 14083.498 | AE15: =SUBTOTAL(9,AE5:AE14) -> 21465 | AF15: =SUBTOTAL(9,AF5:AF14) -> 45 | AG15: =SUM(AG5:AG14) -> 8137.671 | AH15: =SUBTOTAL(9,AH5:AH14) -> 0 | AI15: =SUBTOTAL(9,AI5:AI14) -> 0 | AJ15: =SUM(AJ5:AJ14) -> 0 | AK15: =SUM(AK5:AK14) -> 0 | AL15: =SUM(AL5:AL14) -> 0 | AM15: =SUM(AM5:AM14) -> 0 | AN15: =SUM(AN5:AN12) -> 0 | AO15: =SUM(AO5:AO12) -> 0 | AP15: =SUM(AP5:AP12) -> 0
A16: TOTAL ACUMULADO DE DESPESAS 2024 | G16: =I15+L15+O15+R15+U15+X15+AA15+AD15+AG15+AJ15+AM15+AQ15 -> 150655.86
A17: ECONOMIA NO MÊS | G17: =I15/L15-1 -> 0.46303548

Sheet 22039_ARINOS
A4: CONDUTOR | B4: VEICULO | C4: PLACA | D4: STATUS | E4: KM INICIAL | F4: KM FINAL | G4: KM PERCORRIDA | H4: CONSUMO | I4: QTD LITROS | J4: ABASTECIMENTO MÊS | K4: CONSUMO DE 01 A 15 | L4: CONSUMO DE 16 A 31 | M4: MÊS | N4: OBS
A5: AUGUSTO | B5: L200 | C5: RMJ6B86 | D5: - | E5: 66265 | F5: 68739 | G5: =F5-E5 -> 2474 | H5: 1 | I5: 52.561 | J5: =SUM(K5:L5) -> 335.86 | K5: 335.86 | M5: Janeiro
A6: GUSTAVO | B6: TRACKER | C6: SIM2I94 | D6: - | E6: 7968 | F6: 8927 | G6: =F6-E6 -> 959 | H6: 1 | I6: 69.74 | J6: =SUM(K6:L6) -> 410.09 | K6: 215.16 | L6: 194.93 | M6: Janeiro
A7: AUGUSTO | B7: L200 | C7: RMJ6B86 | D7: - | E7: 68739 | F7: 70689 | G7: =F7-E7 -> 1950 | H7: 3 | I7: 156.26 | J7: =SUM(K7:L7) -> 1017.65 | K7: 297.25 | L7: 720.4 | M7: Fevereiro
A8: GUSTAVO | B8: TRACKER | C8: SIM2I94 | D8: - | E8: 8927 | F8: 10296 | G8: =F8-E8 -> 1369 | H8: 4 | I8: 109.95 | J8: =SUM(K8:L8) -> 666.07 | K8: 277.68 | L8: 388.39 | M8: Fevereiro
A9: AUGUSTO | B9: L200 | C9: RMJ6B86 | D9: - | E9: 70689 | F9: 73837 | G9: =F9-E9 -> 3148 | H9: 5 | I9: 233.21 | J9: =SUM(K9:L9) -> 1518.21 | K9: 1025.46 | L9: 492.75 | M9: Março
A10: GUSTAVO | B10: TRACKER | C10: SIM2I94 | D10: - | E10: 10296 | F10: 11821 | G10: =F10-E10 -> 1525 | H10: 4 | I10: 134.73 | J10: =SUM(K10:L10) -> 825.91 | K10: 450.51 | L10: 375.4 | M10: Março
A11: AUGUSTO | B11: L200 | C11: RMJ6B86 | D11: - | E11: 73837 | F11: 76390 | G11: =F11-E11 -> 2553 | H11: 5 | I11: 108.4 | J11: =SUM(K11:L11) -> 1529.46 | K11: 692.53 | L11: 836.93 | M11: Abril
A12: GUSTAVO | B12: TRACKER | C12: SIM2I94 | D12: - | E12: 11821 | F12: 12874 | G12: =F12-E12 -> 1053 | H12: 3 | I12: 101.28 | J12: =SUM(K12:L12) -> 602.69 | K12: 406.17 | L12: 196.52 | M12: Abril
A13: GUSTAVO | B13: TCROSS | C13: SHX9G91 | D13: - | E13: 24047 | F13: 24363 | G13: =F13-E13 -> 316 | H13: 3 | I13: 98.31 | J13: =SUM(K13:L13) -> 602.68 | K13: 406.16 | L13: 196.52 | M13: Abril
A14: AUGUSTO | B14: L200 | C14: RMJ6B86 | D14: - | E14: 76390 | F14: 80350 | G14: =F14-E14 -> 3960 | H14: 3 | I14: 161.06 | J14: 998.76 | K14: 710.09 | L14: 288.67 | M14: Maio
A15: GUSTAVO | B15: TCROSS | C15: SHX9G91 | D15: - | E15: 24363 | F15: 25407 | G15: =F15-E15 -> 1044 | H15: 2 | I15: 92.01 | J15: 604.58 | K15: 0 | L15: 604.58 | M15: Maio
A16: AUGUSTO | B16: L200 | C16: RMJ6B86 | D16: - | E16: 80350 | F16: 82960 | G16: =F16-E16 -> 2610 | H16: 4 | I16: 235.32 | J16: 1458.97 | K16: 726.93 | L16: 732.04 | M16: Junho
A17: AUGUSTO | B17: L200 | C17: RMJ6B86 | D17: - | E17: 82960 | F17: 85402 | G17: =F17-E17 -> 2442 | H17: 2 | I17: 243.64 | J17: 1511.64 | K17: 641.95 | L17: 869.69 | M17: Julho
A18: EZEQUIAS | B18: RENEGADE | C18: SIH5G62 | D18: - | E18: 43742 | F18: 45486 | G18: =F18-E18 -> 1744 | H18: 4 | I18: 185.56 | J18: 1200.48 | K18: 582.8 | L18: 617.68 | M18: Julho
A19: AUGUSTO | B19: L200 | C19: SEO0D82 | D19: - | E19: 85402 | F19: 89968 | G19: =F19-E19 -> 4566 | H19: 8 | I19: 373.19 | J19: =SUM(K19+L19) -> 2338.87 | K19: 1057.8 | L19: 1281.07 | M19: Agosto
A20: EZEQUIAS | B20: RENEGADE | C20: SIH5G62 | D20: - | E20: 45486 | F20: 47375 | G20: =F20-E20 -> 1889 | H20: 5 | I20: 219.92 | J20: =SUM(K20+L20) -> 1449.27 | K20: 952.98 | L20: 496.29 | M20: Agosto
A21: AUGUSTO | B21: L200 | C21: RMJ6B86 | D21: - | E21: 89968 | F21: 93345 | G21: =F21-E21 -> 3377 | H21: 8 | I21: 329 | J21: =SUM(K21+L21) -> 2053.4 | K21: 827.28 | L21: 1226.12 | M21: Setembro
A22: EZEQUIAS | B22: RENEGADE | C22: SIH5G62 | D22: - | E22: 47375 | F22: 48901 | G22: =F22-E22 -> 1526 | H22: 5 | I22: 210.081 | J22: =SUM(K22+L22) -> 1384.62 | K22: 624.14 | L22: 760.48 | M22: Setembro
A23: AUGUSTO | B23: L200 | C23: RMJ6B86 | G23: =F23-E23 -> 0 | J23: =SUM(K23+L23) -> 0 | M23: Outubro
A24: AUGUSTO | B24: L200 | C24: RMJ6B86 | E24: 96977 | F24: 100925 | G24: =F24-E24 -> 3948 | J24: =SUM(K24+L24) -> 0 | M24: Novembro

Sheet 22007_LDV-V
A1: QTD DE VEICULOS ATIVO | B1: =COUNTIF(D3:D47,"ATIVO") -> 2 | C1: CONTROLE DE KM - 2024 - 22007_LDV-V | M1: ABASTECIMENTO | P1: ABASTECIMENTO | S1: ABASTECIMENTO | V1: ABASTECIMENTO | Y1: ABASTECIMENTO | AB1: ABASTECIMENTO | AE1: ABASTECIMENTO | AH1: ABASTECIMENTO | AK1: ABASTECIMENTO | AN1: ABASTECIMENTO | AQ1: ABASTECIMENTO | AT1: ABASTECIMENTO | AW1: ABASTECIMENTO | AZ1: ABASTECIMENTO | BC1: ABASTECIMENTO | BF1: ABASTECIMENTO | BI1: ABASTECIMENTO | BL1: ABASTECIMENTO | BO1: ABASTECIMENTO | BR1: ABASTECIMENTO | BU1: ABASTECIMENTO | BX1: ABASTECIMENTO | CA1: ABASTECIMENTO | CD1: ABASTECIMENTO | CG1: ABASTECIMENTO | CJ1: ABASTECIMENTO | CM1: ABASTECIMENTO | CP1: ABASTECIMENTO | CS1: ABASTECIMENTO | CV1: ABASTECIMENTO | CY1: ABASTECIMENTO | DB1: OBS | DC1: Folga
A2: CONDUTOR | B2: VEICULO | C2: PLACA | D2: STATUS | E2: KM INICIAL | F2: KM FINAL | G2: KM PERCORRIDA | H2: CONSUMO TOTAL | I2: ABASTECIMENTO MÊS | J2: POSTO SANTA RITA | K2: POSTO VIP | L2: MÊS | M2: 1º DIA VALOR | N2: QTD LITROS | O2: POSTO | P2: 2º DIA VALOR | Q2: QTD LITROS | R2: POSTO | S2: 3º DIA VALOR | T2: QTD LITROS | U2: POSTO | V2: 4º DIA VALOR | W2: QTD LITROS | X2: POSTO | Y2: 5º DIA VALOR | Z2: QTD LITROS | AA2: POSTO | AB2: 6º DIA VALOR | AC2: QTD LITROS | AD2: POSTO | AE2: 7º DIA VALOR | AF2: QTD LITROS | AG2: POSTO | AH2: 8º DIA VALOR | AI2: QTD LITROS | AJ2: POSTO | AK2: 9º DIA VALOR | AL2: QTD LITROS | AM2: POSTO | AN2: 10º DIA VALOR | AO2: QTD LITROS | AP2: POSTO | AQ2: 11º DIA VALOR | AR2: QTD LITROS | AS2: POSTO | AT2: 12º DIA VALOR | AU2: QTD LITROS | AV2: POSTO | AW2: 13º DIA VALOR | AX2: QTD LITROS | AY2: POSTO | AZ2: 14º DIA VALOR | BA2: QTD LITROS | BB2: POSTO | BC2: 15º DIA VALOR | BD2: QTD LITROS | BE2: POSTO | BF2: 16º DIA VALOR | BG2: QTD LITROS | BH2: POSTO | BI2: 17º DIA VALOR | BJ2: QTD LITROS | BK2: POSTO | BL2: 18º DIA VALOR | BM2: QTD LITROS | BN2: POSTO | BO2: 19º DIA VALOR | BP2: QTD LITROS | BQ2: POSTO | BR2: 20º DIA VALOR | BS2: QTD LITROS | BT2: POSTO | BU2: 21º DIA VALOR | BV2: QTD LITROS | BW2: POSTO | BX2: 22º DIA VALOR | BY2: QTD LITROS | BZ2: POSTO | CA2: 23º DIA VALOR | CB2: QTD LITROS | CC2: POSTO | CD2: 24º DIA VALOR | CE2: QTD LITROS | CF2: POSTO | CG2: 25º DIA VALOR | CH2: QTD LITROS | CI2: POSTO | CJ2: 26º DIA VALOR | CK2: QTD LITROS | CL2: POSTO | CM2: 27º DIA VALOR | CN2: QTD LITROS | CO2: POSTO | CP2: 28º DIA VALOR | CQ2: QTD LITROS | CR2: POSTO | CS2: 29º DIA VALOR | CT2: QTD LITROS | CU2: POSTO | CV2: 30º DIA VALOR | CW2: QTD LITROS | CX2: POSTO | CY2: 31º DIA VALOR | CZ2: QTD LITROS | DA2: POSTO
A3: ADEMIR DOMINGOS | B3: ARGO | C3: SHW6C40 | D3: - | E3: 13603 | F3: 14931 | G3: =F3-E3 -> 1328 | H3: =SUM(M3+P3+S3+V3+Y3+AB3+AE3+AH3+AK3+AN3+AQ3+AT3+AW3+AZ3+BC3+BF3+BI3+BL3+BO3+BR3+BU3+BX3+CA3+CD3+CG3+CJ3+CM3+CP3+CS3+CV3+CY3) -> 625.52 | I3: =COUNTA(N3,Q3,T3,W3,Z3,AC3,AF3,AI3,AL3,AO3,AR3,AU3,AX3,BA3,BD3,BG3,BJ3,BM3,BP3,BS3,BV3,BY3,CB3,CE3,CH3,CK3,CN3,CQ3,CT3,CW3,CZ3) -> 3 | J3: =COUNTIF(M3:DC3,"POSTO SANTA RITA") -> 2 | K3: =COUNTIF(M3:DD3,"POSTO VIP") -> 1 | L3: Janeiro | AQ3: 223.17 | AR3: 38.114 | AS3: POSTO VIP | BX3: 223.05 | BY3: 38.59 | BZ3: POSTO SANTA RITA | CV3: 179.3 | CW3: 30.65 | CX3: POSTO SANTA RITA
A4: FRANCISCO EDILSON | B4: RENEGADE | C4: SHY2C77 | D4: - | E4: 29041 | F4: 33321 | G4: =F4-E4 -> 4280 | H4: =SUM(M4+P4+S4+V4+Y4+AB4+AE4+AH4+AK4+AN4+AQ4+AT4+AW4+AZ4+BC4+BF4+BI4+BL4+BO4+BR4+BU4+BX4+CA4+CD4+CG4+CJ4+CM4+CP4+CS4+CV4+CY4) -> 1925.93 | I4: =COUNTA(N4,Q4,T4,W4,Z4,AC4,AF4,AI4,AL4,AO4,AR4,AU4,AX4,BA4,BD4,BG4,BJ4,BM4,BP4,BS4,BV4,BY4,CB4,CE4,CH4,CK4,CN4,CQ4,CT4,CW4,CZ4) -> 8 | J4: =COUNTIF(M4:DC4,"POSTO SANTA RITA") -> 0 | K4: =COUNTIF(N4:DD4,"POSTO VIP") -> 8 | L4: Janeiro | P4: 299.52 | Q4: 51.2 | R4: POSTO VIP | AB4: 180.76 | AC4: 30.9 | AD4: POSTO VIP | AK4: 179.71 | AL4: 30.72 | AM4: POSTO VIP | AW4: 228.2 | AX4: 39.009 | AY4: POSTO VIP | BF4: 286.82 | BG4: 49.03 | BH4: POSTO VIP | BR4: 219.58 | BS4: 37.19 | BT4: POSTO VIP | CD4: 219.64 | CE4: 38 | CF4: POSTO VIP | CS4: 311.7 | CT4: 53.94 | CU4: POSTO VIP
A5: RAIMUNDO GERSON | B5: S10 | C5: RVS1B18 | D5: - | E5: 33422 | F5: 36626 | G5: =F5-E5 -> 3204 | H5: =SUM(M5+P5+S5+V5+Y5+AB5+AE5+AH5+AK5+AN5+AQ5+AT5+AW5+AZ5+BC5+BF5+BI5+BL5+BO5+BR5+BU5+BX5+CA5+CD5+CG5+CJ5+CM5+CP5+CS5+CV5+CY5) -> 1930.61 | I5: =COUNTA(N5,Q5,T5,W5,Z5,AC5,AF5,AI5,AL5,AO5,AR5,AU5,AX5,BA5,BD5,BG5,BJ5,BM5,BP5,BS5,BV5,BY5,CB5,CE5,CH5,CK5,CN5,CQ5,CT5,CW5,CZ5) -> 6 | J5: =COUNTIF(M5:DC5,"POSTO SANTA RITA") -> 4 | K5: =COUNTIF(N5:DD5,"POSTO VIP") -> 2 | L5: Janeiro | P5: 244.5 | Q5: 39.12 | R5: POSTO SANTA RITA | AB5: 314.37 | AC5: 50.3 | AD5: POSTO VIP | AQ5: 326.98 | AR5: 53.17 | AS5: POSTO VIP | AW5: 159.96 | AX5: 26.01 | AY5: POSTO SANTA RITA | BR5: 457.8 | BS5: 75.08 | BT5: POSTO SANTA RITA | CM5: 427 | CN5: 70 | CO5: POSTO SANTA RITA
A6: ANTONIO VAGNER | B6: TRACKER | C6: RVJ0I15 | D6: DESMOBILIZADO | E6: 34811 | F6: 41722 | G6: =F6-E6 -> 6911 | H6: =SUM(M6+P6+S6+V6+Y6+AB6+AE6+AH6+AK6+AN6+AQ6+AT6+AW6+AZ6+BC6+BF6+BI6+BL6+BO6+BR6+BU6+BX6+CA6+CD6+CG6+CJ6+CM6+CP6+CS6+CV6+CY6) -> 335.78 | I6: =COUNTA(N6,Q6,T6,W6,Z6,AC6,AF6,AI6,AL6,AO6,AR6,AU6,AX6,BA6,BD6,BG6,BJ6,BM6,BP6,BS6,BV6,BY6,CB6,CE6,CH6,CK6,CN6,CQ6,CT6,CW6,CZ6) -> 2 | J6: =COUNTIF(M6:DC6,"POSTO SANTA RITA") -> 0 | K6: =COUNTIF(N6:DD6,"POSTO VIP") -> 1 | L6: Janeiro | AK6: 202.23 | AL6: 34.57 | AM6: POSTO VIP | AT6: 133.55 | AU6: 22.33 | AV6: POTO VIP
A7: ANTONIO VAGNER | B7: RENEGADE | C7: SIG2E24 | D7: - | E7: 19768 | F7: 21340 | G7: =F7-E7 -> 1572 | H7: =SUM(M7+P7+S7+V7+Y7+AB7+AE7+AH7+AK7+AN7+AQ7+AT7+AW7+AZ7+BC7+BF7+BI7+BL7+BO7+BR7+BU7+BX7+CA7+CD7+CG7+CJ7+CM7+CP7+CS7+CV7+CY7) -> 261.77 | I7: =COUNTA(N7,Q7,T7,W7,Z7,AC7,AF7,AI7,AL7,AO7,AR7,AU7,AX7,BA7,BD7,BG7,BJ7,BM7,BP7,BS7,BV7,BY7,CB7,CE7,CH7,CK7,CN7,CQ7,CT7,CW7,CZ7) -> 1 | J7: =COUNTIF(M7:DC7,"POSTO SANTA RITA") -> 0 | K7: =COUNTIF(N7:DD7,"POSTO VIP") -> 1 | L7: Janeiro | CA7: 261.77 | CB7: 45.29 | CC7: POSTO VIP
A8: SAMILA RIBEIRO | B8: ONIX | C8: SIT1G63 | D8: - | E8: 3373 | F8: 5051 | G8: =F8-E8 -> 1678 | H8: =SUM(M8+P8+S8+V8+Y8+AB8+AE8+AH8+AK8+AN8+AQ8+AT8+AW8+AZ8+BC8+BF8+BI8+BL8+BO8+BR8+BU8+BX8+CA8+CD8+CG8+CJ8+CM8+CP8+CS8+CV8+CY8) -> 659.47 | I8: =COUNTA(N8,Q8,T8,W8,Z8,AC8,AF8,AI8,AL8,AO8,AR8,AU8,AX8,BA8,BD8,BG8,BJ8,BM8,BP8,BS8,BV8,BY8,CB8,CE8,CH8,CK8,CN8,CQ8,CT8,CW8,CZ8) -> 4 | J8: =COUNTIF(M8:DC8,"POSTO SANTA RITA") -> 4 | K8: =COUNTIF(N8:DD8,"POSTO VIP") -> 0 | L8: Janeiro | AQ8: 234.53 | AR8: 40.09 | AS8: POSTO SANTA RITA | BI8: 219.58 | BJ8: 37.99 | BK8: POSTO SANTA RITA | BO8: 114.27 | BP8: 19.77 | BQ8: POSTO SANTA RITA | CM8: 91.09 | CN8: 15.76 | CO8: POSTO SANTA RITA
A9: FABIO SIQUEIRA | B9: RENEGADE | C9: RNX9A52 | D9: - | E9: 44491 | F9: 47015 | G9: =F9-E9 -> 2524 | H9: =SUM(M9+P9+S9+V9+Y9+AB9+AE9+AH9+AK9+AN9+AQ9+AT9+AW9+AZ9+BC9+BF9+BI9+BL9+BO9+BR9+BU9+BX9+CA9+CD9+CG9+CJ9+CM9+CP9+CS9+CV9+CY9) -> 1099.96 | I9: =COUNTA(N9,Q9,T9,W9,Z9,AC9,AF9,AI9,AL9,AO9,AR9,AU9,AX9,BA9,BD9,BG9,BJ9,BM9,BP9,BS9,BV9,BY9,CB9,CE9,CH9,CK9,CN9,CQ9,CT9,CW9,CZ9) -> 4 | J9: =COUNTIF(M9:DC9,"POSTO SANTA RITA") -> 0 | K9: =COUNTIF(N9:DD9,"POSTO VIP") -> 4 | L9: Janeiro | P9: 312.97 | Q9: 53.5 | R9: POSTO VIP | AT9: 198.6 | AU9: 33.95 | AV9: POSTO VIP | BO9: 294.54 | BP9: 50.059 | BQ9: POSTO VIP | CG9: 293.85 | CH9: 50.84 | CI9: POSTO VIP
A10: HERMES XAVIER | B10: ONIX | C10: SIU5B06 | D10: - | E10: 1529 | F10: 2012 | G10: =F10-E10 -> 483 | H10: =SUM(M10+P10+S10+V10+Y10+AB10+AE10+AH10+AK10+AN10+AQ10+AT10+AW10+AZ10+BC10+BF10+BI10+BL10+BO10+BR10+BU10+BX10+CA10+CD10+CG10+CJ10+CM10+CP10+CS10+CV10+CY10) -> 232.12 | I10: =COUNTA(N10,Q10,T10,W10,Z10,AC10,AF10,AI10,AL10,AO10,AR10,AU10,AX10,BA10,BD10,BG10,BJ10,BM10,BP10,BS10,BV10,BY10,CB10,CE10,CH10,CK10,CN10,CQ10,CT10,CW10,CZ10) -> 1 | J10: =COUNTIF(M10:DC10,"POSTO SANTA RITA") -> 0 | K10: =COUNTIF(N10:DD10,"POSTO VIP") -> 1 | L10: Janeiro | CA10: 232.12 | CB10: 40.164 | CC10: POSTO VIP
A11: ADEMIR DOMINGOS | B11: ARGO | C11: SHW6C40 | D11: - | E11: 14931 | F11: 16318 | G11: =F11-E11 -> 1387 | H11: =SUM(M11+P11+S11+V11+Y11+AB11+AE11+AH11+AK11+AN11+AQ11+AT11+AW11+AZ11+BC11+BF11+BI11+BL11+BO11+BR11+BU11+BX11+CA11+CD11+CG11+CJ11+CM11+CP11+CS11+CV11+CY11) -> 620.75 | I11: =COUNTA(N11,Q11,T11,W11,Z11,AC11,AF11,AI11,AL11,AO11,AR11,AU11,AX11,BA11,BD11,BG11,BJ11,BM11,BP11,BS11,BV11,BY11,CB11,CE11,CH11,CK11,CN11,CQ11,CT11,CW11,CZ11) -> 3 | J11: =COUNTIF(M11:DC11,"POSTO SANTA RITA") -> 0 | K11: =COUNTIF(M11:DD11,"POSTO VIP") -> 3 | L11: Fevereiro | S11: 222.76 | T11: 38.54 | U11: POSTO VIP | AN11: 167.49 | AO11: 28.68 | AP11: POSTO VIP | CD11: 230.5 | CE11: 39.47 | CF11: POSTO VIP
A12: FRANCISCO EDILSON | B12: RENEGADE | C12: SHY2C77 | D12: - | E12: 33321 | F12: 34867 | G12: =F12-E12 -> 1546 | H12: =SUM(M12+P12+S12+V12+Y12+AB12+AE12+AH12+AK12+AN12+AQ12+AT12+AW12+AZ12+BC12+BF12+BI12+BL12+BO12+BR12+BU12+BX12+CA12+CD12+CG12+CJ12+CM12+CP12+CS12+CV12+CY12) -> 438.15 | I12: =COUNTA(N12,Q12,T12,W12,Z12,AC12,AF12,AI12,AL12,AO12,AR12,AU12,AX12,BA12,BD12,BG12,BJ12,BM12,BP12,BS12,BV12,BY12,CB12,CE12,CH12,CK12,CN12,CQ12,CT12,CW12,CZ12) -> 2 | J12: =COUNTIF(M12:DC12,"POSTO SANTA RITA") -> 0 | K12: =COUNTIF(N12:DD12,"POSTO VIP") -> 2 | L12: Fevereiro | P12: 231.54 | Q12: 40.059 | R12: POSTO VIP | AH12: 206.61 | AI12: 35.379 | AJ12: POSTO VIP
A13: RAIMUNDO GERSON | B13: S10 | C13: RVS1B18 | D13: - | E13: 36626 | F13: 37704 | G13: =F13-E13 -> 1078 | H13: =SUM(M13+P13+S13+V13+Y13+AB13+AE13+AH13+AK13+AN13+AQ13+AT13+AW13+AZ13+BC13+BF13+BI13+BL13+BO13+BR13+BU13+BX13+CA13+CD13+CG13+CJ13+CM13+CP13+CS13+CV13+CY13) -> 713.82 | I13: =COUNTA(N13,Q13,T13,W13,Z13,AC13,AF13,AI13,AL13,AO13,AR13,AU13,AX13,BA13,BD13,BG13,BJ13,BM13,BP13,BS13,BV13,BY13,CB13,CE13,CH13,CK13,CN13,CQ13,CT13,CW13,CZ13) -> 2 | J13: =COUNTIF(M13:DC13,"POSTO SANTA RITA") -> 2 | K13: =COUNTIF(N13:DD13,"POSTO VIP") -> 0 | L13: Fevereiro | S13: 439.26 | T13: 72.01 | U13: POSTO SANTA RITA | AH13: 274.56 | AI13: 45.01 | AJ13: POSTO SANTA RITA
A14: SAMILA RIBEIRO | B14: ONIX | C14: SIT1G63 | D14: - | E14: 5051 | F14: 6205 | G14: =F14-E14 -> 1154 | H14: =SUM(M14+P14+S14+V14+Y14+AB14+AE14+AH14+AK14+AN14+AQ14+AT14+AW14+AZ14+BC14+BF14+BI14+BL14+BO14+BR14+BU14+BX14+CA14+CD14+CG14+CJ14+CM14+CP14+CS14+CV14+CY14) -> 387.56 | I14: =COUNTA(N14,Q14,T14,W14,Z14,AC14,AF14,AI14,AL14,AO14,AR14,AU14,AX14,BA14,BD14,BG14,BJ14,BM14,BP14,BS14,BV14,BY14,CB14,CE14,CH14,CK14,CN14,CQ14,CT14,CW14,CZ14) -> 3 | J14: =COUNTIF(M14:DC14,"POSTO SANTA RITA") -> 3 | K14: =COUNTIF(N14:DD14,"POSTO VIP") -> 0 | L14: Fevereiro | P14: 116.06 | Q14: 20.08 | R14: POSTO SANTA RITA | BI14: 186.88 | BJ14: 32 | BK14: POSTO SANTA RITA | CD14: 84.62 | CE14: 14.49 | CF14: POSTO SANTA RITA
A15: FABIO SIQUEIRA | B15: RENEGADE | C15: RNX9A52 | D15: - | E15: 47015 | F15: 48852 | G15: =F15-E15 -> 1837 | H15: =SUM(M15+P15+S15+V15+Y15+AB15+AE15+AH15+AK15+AN15+AQ15+AT15+AW15+AZ15+BC15+BF15+BI15+BL15+BO15+BR15+BU15+BX15+CA15+CD15+CG15+CJ15+CM15+CP15+CS15+CV15+CY15) -> 489.27 | I15: =COUNTA(N15,Q15,T15,W15,Z15,AC15,AF15,AI15,AL15,AO15,AR15,AU15,AX15,BA15,BD15,BG15,BJ15,BM15,BP15,BS15,BV15,BY15,CB15,CE15,CH15,CK15,CN15,CQ15,CT15,CW15,CZ15) -> 2 | J15: =COUNTIF(M15:DC15,"POSTO SANTA RITA") -> 1 | K15: =COUNTIF(N15:DD15,"POSTO VIP") -> 1 | L15: Fevereiro | M15: 179.58 | N15: 31.07 | O15: POSTO SANTA RITA | AK15: 309.69 | AL15: 53.03 | AM15: POSTO VIP
A16: HERMES XAVIER | B16: ONIX | C16: SIU5B06 | D16: - | E16: 2012 | F16: 2497 | G16: =F16-E16 -> 485 | H16: =SUM(M16+P16+S16+V16+Y16+AB16+AE16+AH16+AK16+AN16+AQ16+AT16+AW16+AZ16+BC16+BF16+BI16+BL16+BO16+BR16+BU16+BX16+CA16+CD16+CG16+CJ16+CM16+CP16+CS16+CV16+CY16) -> 130.23 | I16: =COUNTA(N16,Q16,T16,W16,Z16,AC16,AF16,AI16,AL16,AO16,AR16,AU16,AX16,BA16,BD16,BG16,BJ16,BM16,BP16,BS16,BV16,BY16,CB16,CE16,CH16,CK16,CN16,CQ16,CT16,CW16,CZ16) -> 1 | J16: =COUNTIF(M16:DC16,"POSTO SANTA RITA") -> 0 | K16: =COUNTIF(N16:DD16,"POSTO VIP") -> 1 | L16: Fevereiro | CD16: 130.23 | CE16: 22.3 | CF16: POSTO VIP
A17: ANTONIO VAGNER | B17: RENEGADE | C17: SIG2E24 | D17: - | E17: 21340 | F17: 28074 | G17: =F17-E17 -> 6734 | H17: =SUM(M17+P17+S17+V17+Y17+AB17+AE17+AH17+AK17+AN17+AQ17+AT17+AW17+AZ17+BC17+BF17+BI17+BL17+BO17+BR17+BU17+BX17+CA17+CD17+CG17+CJ17+CM17+CP17+CS17+CV17+CY17) -> 1393.33 | I17: =COUNTA(N17,Q17,T17,W17,Z17,AC17,AF17,AI17,AL17,AO17,AR17,AU17,AX17,BA17,BD17,BG17,BJ17,BM17,BP17,BS17,BV17,BY17,CB17,CE17,CH17,CK17,CN17,CQ17,CT17,CW17,CZ17) -> 5 | J17: =COUNTIF(M17:DC17,"POSTO SANTA RITA") -> 0 | K17: =COUNTIF(N17:DD17,"POSTO VIP") -> 5 | L17: Fevereiro | S17: 240.29 | T17: 41.919 | U17: POSTO VIP | AK17: 294.1 | AL17: 50.36 | AM17: POSTO VIP | AN17: 301.81 | AO17: 51.68 | AP17: POSTO VIP | BI17: 257.6 | BJ17: 44.1 | BK17: POSTO VIP | CP17: 299.53 | CQ17: 51.29 | CR17: POSTO VIP
A18: ADEMIR DOMINGOS | B18: ARGO | C18: SHW6C40 | D18: - | E18: 16318 | F18: 17648 | G18: =F18-E18 -> 1330 | H18: =SUM(M18+P18+S18+V18+Y18+AB18+AE18+AH18+AK18+AN18+AQ18+AT18+AW18+AZ18+BC18+BF18+BI18+BL18+BO18+BR18+BU18+BX18+CA18+CD18+CG18+CJ18+CM18+CP18+CS18+CV18+CY18) -> 667.86 | I18: =COUNTA(N18,Q18,T18,W18,Z18,AC18,AF18,AI18,AL18,AO18,AR18,AU18,AX18,BA18,BD18,BG18,BJ18,BM18,BP18,BS18,BV18,BY18,CB18,CE18,CH18,CK18,CN18,CQ18,CT18,CW18,CZ18) -> 3 | J18: =COUNTIF(M18:DC18,"POSTO SANTA RITA") -> 2 | K18: =COUNTIF(N18:DD18,"POSTO VIP") -> 1 | L18: Março | P18: 210.65 | Q18: 36.07 | R18: POSTO SANTA RITA | BF18: 232.37 | BG18: 39.79 | BH18: POSTO VIP | CJ18: 224.84 | CK18: 38.5 | CL18: POSTO SANTA RITA
A19: SAMILA RIBEIRO | B19: ONIX | C19: SIT1G63 | D19: - | E19: 6119 | F19: 9198 | G19: =F19-E19 -> 3079 | H19: =SUM(M19+P19+S19+V19+Y19+AB19+AE19+AH19+AK19+AN19+AQ19+AT19+AW19+AZ19+BC19+BF19+BI19+BL19+BO19+BR19+BU19+BX19+CA19+CD19+CG19+CJ19+CM19+CP19+CS19+CV19+CY19) -> 1373.17 | I19: =COUNTA(N19,Q19,T19,W19,Z19,AC19,AF19,AI19,AL19,AO19,AR19,AU19,AX19,BA19,BD19,BG19,BJ19,BM19,BP19,BS19,BV19,BY19,CB19,CE19,CH19,CK19,CN19,CQ19,CT19,CW19,CZ19) -> 8 | J19: =COUNTIF(M19:DC19,"POSTO SANTA RITA") -> 7 | K19: =COUNTIF(N19:DD19,"POSTO VIP") -> 1 | L19: Março | P19: 221.1 | Q19: 37.86 | R19: POSTO VIP | Y19: 195 | Z19: 33.39 | AA19: POSTO SANTA RITA | AK19: 183.73 | AL19: 31.46 | AM19: POSTO SANTA RITA | AT19: 153.07 | AU19: 26.21 | AV19: POSTO SANTA RITA | BF19: 139.05 | BG19: 23.81 | BH19: POSTO SANTA RITA | BR19: 142.32 | BS19: 24.37 | BT19: POSTO SANTA RITA | CJ19: 185.13 | CK19: 31.7 | CL19: POSTO SANTA RITA | CP19: 153.77 | CQ19: 26.33 | CR19: POSTO SANTA RITA
A20: HERMES XAVIER | B20: ONIX | C20: SIU5B06 | D20: - | E20: 2497 | F20: 5378 | G20: =F20-E20 -> 2881 | H20: =SUM(M20+P20+S20+V20+Y20+AB20+AE20+AH20+AK20+AN20+AQ20+AT20+AW20+AZ20+BC20+BF20+BI20+BL20+BO20+BR20+BU20+BX20+CA20+CD20+CG20+CJ20+CM20+CP20+CS20+CV20+CY20) -> 271.73 | I20: =COUNTA(N20,Q20,T20,W20,Z20,AC20,AF20,AI20,AL20,AO20,AR20,AU20,AX20,BA20,BD20,BG20,BJ20,BM20,BP20,BS20,BV20,BY20,CB20,CE20,CH20,CK20,CN20,CQ20,CT20,CW20,CZ20) -> 2 | J20: =COUNTIF(M20:DC20,"POSTO SANTA RITA") -> 0 | K20: =COUNTIF(N20:DD20,"POSTO VIP") -> 2 | L20: Março | AW20: 217.83 | AX20: 37.3 | AY20: POSTO VIP | BC20: 53.9 | BD20: 9.23 | BE20: POSTO VIP
A21: ANTONIO VAGNER | B21: RENEGADE | C21: SIG2E24 | D21: - | E21: 28047 | F21: 31541 | G21: =F21-E21 -> 3494 | H21: =SUM(M21+P21+S21+V21+Y21+AB21+AE21+AH21+AK21+AN21+AQ21+AT21+AW21+AZ21+BC21+BF21+BI21+BL21+BO21+BR21+BU21+BX21+CA21+CD21+CG21+CJ21+CM21+CP21+CS21+CV21+CY21) -> 1361.5 | I21: =COUNTA(N21,Q21,T21,W21,Z21,AC21,AF21,AI21,AL21,AO21,AR21,AU21,AX21,BA21,BD21,BG21,BJ21,BM21,BP21,BS21,BV21,BY21,CB21,CE21,CH21,CK21,CN21,CQ21,CT21,CW21,CZ21) -> 6 | J21: =COUNTIF(M21:DC21,"POSTO SANTA RITA") -> 2 | K21: =COUNTIF(N21:DD21,"POSTO VIP") -> 4 | L21: Março | S21: 285.63 | T21: 48.91 | U21: POSTO SANTA RITA | Y21: 39.53 | Z21: 6.76 | AA21: POSTO VIP | AT21: 288.2 | AU21: 49.35 | AV21: POSTO SANTA RITA | BF21: 292.17 | BG21: 50.03 | BH21: POSTO VIP | CJ21: 226.7 | CK21: 38.819 | CL21: POSTO VIP | CM21: 229.27 | CN21: 29.26 | CO21: POSTO VIP
A22: ADEMIR DOMINGOS | B22: ARGO | C22: SHW6C40 | D22: - | E22: 17648 | F22: 19990 | G22: =F22-E22 -> 2342 | H22: =SUM(M22+P22+S22+V22+Y22+AB22+AE22+AH22+AK22+AN22+AQ22+AT22+AW22+AZ22+BC22+BF22+BI22+BL22+BO22+BR22+BU22+BX22+CA22+CD22+CG22+CJ22+CM22+CP22+CS22+CV22+CY22) -> 1004.81 | I22: =COUNTA(N22,Q22,T22,W22,Z22,AC22,AF22,AI22,AL22,AO22,AR22,AU22,AX22,BA22,BD22,BG22,BJ22,BM22,BP22,BS22,BV22,BY22,CB22,CE22,CH22,CK22,CN22,CQ22,CT22,CW22,CZ22) -> 6 | J22: =COUNTIF(M22:DC22,"POSTO SANTA RITA") -> 5 | K22: =COUNTIF(N22:DD22,"POSTO VIP") -> 1 | L22: Abril | P22: 122.87 | Q22: 21.04 | R22: POSTO SANTA RITA | V22: 128.24 | W22: 21.959 | X22: POSTO VIP | BF22: 173.47 | BG22: 29.01 | BH22: POSTO SANTA RITA | BR22: 179.63 | BS22: 30.04 | BT22: POSTO SANTA RITA | CG22: 229.33 | CH22: 38.35 | CI22: POSTO SANTA RITA | CV22: 171.27 | CW22: 28.64 | CX22: POSTO SANTA RITA
A23: SAMILA RIBEIRO | B23: ONIX | C23: SIT1G63 | D23: - | E23: 9198 | F23: 11150 | G23: =F23-E23 -> 1952 | H23: =SUM(M23+P23+S23+V23+Y23+AB23+AE23+AH23+AK23+AN23+AQ23+AT23+AW23+AZ23+BC23+BF23+BI23+BL23+BO23+BR23+BU23+BX23+CA23+CD23+CG23+CJ23+CM23+CP23+CS23+CV23+CY23) -> 1204.39 | I23: =COUNTA(N23,Q23,T23,W23,Z23,AC23,AF23,AI23,AL23,AO23,AR23,AU23,AX23,BA23,BD23,BG23,BJ23,BM23,BP23,BS23,BV23,BY23,CB23,CE23,CH23,CK23,CN23,CQ23,CT23,CW23,CZ23) -> 7 | J23: =COUNTIF(M23:DC23,"POSTO SANTA RITA") -> 6 | K23: =COUNTIF(N23:DD23,"POSTO VIP") -> 1 | L23: Abril | P23: 227.35 | Q23: 38.93 | R23: POSTO SANTA RITA | AB23: 143.02 | AC23: 24.49 | AD23: POSTO VIP | AQ23: 152.07 | AR23: 26.04 | AS23: POSTO SANTA RITA | AW23: 112.47 | AX23: 19.25 | AY23: POSTO SANTA RITA | BO23: 219.35 | BP23: 36.68 | BQ23: POSTO SANTA RITA | CG23: 182.09 | CH23: 30.45 | CI23: POSTO SANTA RITA | CV23: 168.04 | CW23: 28.1 | CX23: POSTO SANTA RITA
A24: HERMES XAVIER | B24: ONIX | C24: SIU5B06 | D24: - | E24: 5378 | F24: 9249 | G24: =F24-E24 -> 3871 | H24: =SUM(M24+P24+S24+V24+Y24+AB24+AE24+AH24+AK24+AN24+AQ24+AT24+AW24+AZ24+BC24+BF24+BI24+BL24+BO24+BR24+BU24+BX24+CA24+CD24+CG24+CJ24+CM24+CP24+CS24+CV24+CY24) -> 771.23 | I24: =COUNTA(N24,Q24,T24,W24,Z24,AC24,AF24,AI24,AL24,AO24,AR24,AU24,AX24,BA24,BD24,BG24,BJ24,BM24,BP24,BS24,BV24,BY24,CB24,CE24,CH24,CK24,CN24,CQ24,CT24,CW24,CZ24) -> 4 | J24: =COUNTIF(M24:DC24,"POSTO SANTA RITA") -> 3 | K24: =COUNTIF(N24:DD24,"POSTO VIP") -> 1 | L24: Abril | AB24: 142.08 | AC24: 24.33 | AD24: POSTO VIP | AW24: 151.89 | AX24: 26 | AY24: POSTO SANTA RITA | BF24: 263.12 | BG24: 44 | BH24: POSTO SANTA RITA | CV24: 214.14 | CW24: 35.81 | CX24: POSTO SANTA RITA
A25: ANTONIO VAGNER | B25: RENEGADE | C25: SIG2E24 | D25: - | E25: 31541 | F25: 33470 | G25: =F25-E25 -> 1929 | H25: =SUM(M25+P25+S25+V25+Y25+AB25+AE25+AH25+AK25+AN25+AQ25+AT25+AW25+AZ25+BC25+BF25+BI25+BL25+BO25+BR25+BU25+BX25+CA25+CD25+CG25+CJ25+CM25+CP25+CS25+CV25+CY25) -> 480.74 | I25: =COUNTA(N25,Q25,T25,W25,Z25,AC25,AF25,AI25,AL25,AO25,AR25,AU25,AX25,BA25,BD25,BG25,BJ25,BM25,BP25,BS25,BV25,BY25,CB25,CE25,CH25,CK25,CN25,CQ25,CT25,CW25,CZ25) -> 2 | J25: =COUNTIF(M25:DC25,"POSTO SANTA RITA") -> 0 | K25: =COUNTIF(N25:DD25,"POSTO VIP") -> 2 | L25: Abril | S25: 232.54 | T25: 29.82 | U25: POSTO VIP | AH25: 248.2 | AI25: 42.5 | AJ25: POSTO VIP
A26: ADEMIR DOMINGOS | B26: ARGO | C26: SHW6C40 | D26: - | E26: 19990 | F26: 23199 | G26: =F26-E26 -> 3209 | H26: =SUM(M26+P26+S26+V26+Y26+AB26+AE26+AH26+AK26+AN26+AQ26+AT26+AW26+AZ26+BC26+BF26+BI26+BL26+BO26+BR26+BU26+BX26+CA26+CD26+CG26+CJ26+CM26+CP26+CS26+CV26+CY26) -> 1198.49 | I26: =COUNTA(N26,Q26,T26,W26,Z26,AC26,AF26,AI26,AL26,AO26,AR26,AU26,AX26,BA26,BD26,BG26,BJ26,BM26,BP26,BS26,BV26,BY26,CB26,CE26,CH26,CK26,CN26,CQ26,CT26,CW26,CZ26) -> 7 | J26: =COUNTIF(M26:DC26,"POSTO SANTA RITA") -> 7 | K26: =COUNTIF(N26:DD26,"POSTO VIP") -> 0 | L26: Maio | P26: 152.55 | Q26: 25.51 | R26: POSTO SANTA RITA | V26: 137.6 | W26: 23.01 | X26: POSTO SANTA RITA | AK26: 194.45 | AL26: 33.01 | AM26: POSTO SANTA RITA | AZ26: 147.17 | BA26: 24.61 | BB26: POSTO SANTA RITA | BL26: 198.35 | BM26: 33.16 | BN26: POSTO SANTA RITA | BU26: 156.67 | BV26: 26.19 | BW26: POSTO SANTA RITA | CD26: 211.7 | CE26: 35.58 | CF26: POSTO SANTA RITA
A27: SAMILA RIBEIRO | B27: ONIX | C27: SIT1G63 | D27: - | E27: 11150 | F27: 13674 | G27: =F27-E27 -> 2524 | H27: =SUM(M27+P27+S27+V27+Y27+AB27+AE27+AH27+AK27+AN27+AQ27+AT27+AW27+AZ27+BC27+BF27+BI27+BL27+BO27+BR27+BU27+BX27+CA27+CD27+CG27+CJ27+CM27+CP27+CS27+CV27+CY27) -> 951.99 | I27: =COUNTA(N27,Q27,T27,W27,Z27,AC27,AF27,AI27,AL27,AO27,AR27,AU27,AX27,BA27,BD27,BG27,BJ27,BM27,BP27,BS27,BV27,BY27,CB27,CE27,CH27,CK27,CN27,CQ27,CT27,CW27,CZ27) -> 6 | J27: =COUNTIF(M27:DC27,"POSTO SANTA RITA") -> 6 | K27: =COUNTIF(N27:DD27,"POSTO VIP") -> 0 | L27: Maio | V27: 153.09 | W27: 25.06 | X27: POSTO SANTA RITA | AQ27: 162.3 | AR27: 27.14 | AS27: POSTO SANTA RITA | BL27: 131.56 | BM27: 22.06 | BN27: POSTO SANTA RITA | BX27: 174.02 | BY27: 29.1 | BZ27: POSTO SANTA RITA | CG27: 127.05 | CH27: 21.35 | CI27: POSTO SANTA RITA | CV27: 203.97 | CW27: 34.28 | CX27: POSTO SANTA RITA
A28: HERMES XAVIER | B28: ONIX | C28: SIU5B06 | D28: - | E28: 9249 | F28: 12145 | G28: =F28-E28 -> 2896 | H28: =SUM(M28+P28+S28+V28+Y28+AB28+AE28+AH28+AK28+AN28+AQ28+AT28+AW28+AZ28+BC28+BF28+BI28+BL28+BO28+BR28+BU28+BX28+CA28+CD28+CG28+CJ28+CM28+CP28+CS28+CV28+CY28) -> 1133.25 | I28: =COUNTA(N28,Q28,T28,W28,Z28,AC28,AF28,AI28,AL28,AO28,AR28,AU28,AX28,BA28,BD28,BG28,BJ28,BM28,BP28,BS28,BV28,BY28,CB28,CE28,CH28,CK28,CN28,CQ28,CT28,CW28,CZ28) -> 5 | J28: =COUNTIF(M28:DC28,"POSTO SANTA RITA") -> 5 | K28: =COUNTIF(N28:DD28,"POSTO VIP") -> 0 | L28: Maio | AE28: 227.24 | AF28: 38 | AG28: POSTO SANTA RITA | AZ28: 248.7 | BA28: 41.589 | BB28: POSTO SANTA RITA | BF28: 191.48 | BG28: 32.02 | BH28: POSTO SANTA RITA | BL28: 215.93 | BM28: 36.11 | BN28: POSTO SANTA RITA | CP28: 249.9 | CQ28: 42 | CR28: POSTO SANTA RITA
A29: ADEMIR DOMINGOS | B29: ARGO | C29: SHW6C40 | D29: - | E29: 23199 | F29: 25593 | G29: =F29-E29 -> 2394 | H29: =SUM(M29+P29+S29+V29+Y29+AB29+AE29+AH29+AK29+AN29+AQ29+AT29+AW29+AZ29+BC29+BF29+BI29+BL29+BO29+BR29+BU29+BX29+CA29+CD29+CG29+CJ29+CM29+CP29+CS29+CV29+CY29) -> 794.44 | I29: =COUNTA(N29,Q29,T29,W29,Z29,AC29,AF29,AI29,AL29,AO29,AR29,AU29,AX29,BA29,BD29,BG29,BJ29,BM29,BP29,BS29,BV29,BY29,CB29,CE29,CH29,CK29,CN29,CQ29,CT29,CW29,CZ29) -> 5 | J29: =COUNTIF(M29:DC29,"POSTO SANTA RITA") -> 4 | K29: =COUNTIF(N29:DD29,"POSTO VIP") -> 1 | L29: Junho | AT29: 193.08 | AU29: 32.45 | AV29: POSTO SANTA RITA | BC29: 176.71 | BD29: 29.7 | BE29: POSTO VIP | BL29: 158.98 | BM29: 26.72 | BN29: POSTO SANTA RITA | BO29: 140.84 | BP29: 23.67 | BQ29: POSTO SANTA RITA | BX29: 124.83 | BY29: 20.98 | BZ29: POSTO SANTA RITA
A30: SAMILA RIBEIRO | B30: ONIX | C30: SIT1G63 | D30: - | E30: 13674 | F30: 16292 | G30: =F30-E30 -> 2618 | H30: =SUM(M30+P30+S30+V30+Y30+AB30+AE30+AH30+AK30+AN30+AQ30+AT30+AW30+AZ30+BC30+BF30+BI30+BL30+BO30+BR30+BU30+BX30+CA30+CD30+CG30+CJ30+CM30+CP30+CS30+CV30+CY30) -> 1366.78 | I30: =COUNTA(N30,Q30,T30,W30,Z30,AC30,AF30,AI30,AL30,AO30,AR30,AU30,AX30,BA30,BD30,BG30,BJ30,BM30,BP30,BS30,BV30,BY30,CB30,CE30,CH30,CK30,CN30,CQ30,CT30,CW30,CZ30) -> 7 | J30: =COUNTIF(M30:DC30,"POSTO SANTA RITA") -> 7 | K30: =COUNTIF(N30:DD30,"POSTO VIP") -> 0 | L30: Junho | AE30: 229.37 | AF30: 38.55 | AG30: POSTO SANTA RITA | AW30: 202.66 | AX30: 34.06 | AY30: POSTO SANTA RITA | BL30: 218.13 | BM30: 36.66 | BN30: POSTO SANTA RITA | BR30: 168.86 | BS30: 28.38 | BT30: POSTO SANTA RITA | BX30: 169.16 | BY30: 28.43 | BZ30: POSTO SANTA RITA | CJ30: 166.18 | CK30: 27.93 | CL30: POSTO SANTA RITA | CM30: 212.42 | CN30: 35.701 | CO30: POSTO SANTA RITA
A31: HERMES XAVIER | B31: ONIX | C31: SIU5B06 | D31: - | E31: 12145 | F31: 15086 | G31: =F31-E31 -> 2941 | H31: =SUM(M31+P31+S31+V31+Y31+AB31+AE31+AH31+AK31+AN31+AQ31+AT31+AW31+AZ31+BC31+BF31+BI31+BL31+BO31+BR31+BU31+BX31+CA31+CD31+CG31+CJ31+CM31+CP31+CS31+CV31+CY31) -> 627.29 | I31: =COUNTA(N31,Q31,T31,W31,Z31,AC31,AF31,AI31,AL31,AO31,AR31,AU31,AX31,BA31,BD31,BG31,BJ31,BM31,BP31,BS31,BV31,BY31,CB31,CE31,CH31,CK31,CN31,CQ31,CT31,CW31,CZ31) -> 3 | J31: =COUNTIF(M31:DC31,"POSTO SANTA RITA") -> 3 | K31: =COUNTIF(N31:DD31,"POSTO VIP") -> 0 | L31: Junho | M31: 102.45 | N31: 17.21 | O31: POSTO SANTA RITA | BL31: 262.15 | BM31: 44.06 | BN31: POSTO SANTA RITA | CS31: 262.69 | CT31: 43.42 | CU31: POSTO SANTA RITA
A32: ADEMIR DOMINGOS | B32: ARGO | C32: SHW6C40 | D32: - | E32: 25593 | F32: 28640 | G32: =F32-E32 -> 3047 | H32: =SUM(M32+P32+S32+V32+Y32+AB32+AE32+AH32+AK32+AN32+AQ32+AT32+AW32+AZ32+BC32+BF32+BI32+BL32+BO32+BR32+BU32+BX32+CA32+CD32+CG32+CJ32+CM32+CP32+CS32+CV32+CY32) -> 1273.04 | I32: =COUNTA(N32,Q32,T32,W32,Z32,AC32,AF32,AI32,AL32,AO32,AR32,AU32,AX32,BA32,BD32,BG32,BJ32,BM32,BP32,BS32,BV32,BY32,CB32,CE32,CH32,CK32,CN32,CQ32,CT32,CW32,CZ32) -> 7 | J32: =COUNTIF(M32:DC32,"POSTO SANTA RITA") -> 7 | K32: =COUNTIF(N32:DD32,"POSTO VIP") -> 0 | L32: Julho | P32: 177.99 | Q32: 29.42 | R32: POSTO SANTA RITA | Y32: 187.08 | Z32: 30.72 | AA32: POSTO SANTA RITA | AN32: 171.1 | AO32: 27.42 | AP32: POSTO SANTA RITA | AW32: 188.38 | AX32: 30.19 | AY32: POSTO SANTA RITA | BO32: 202.49 | BP32: 32.451 | BQ32: POSTO SANTA RITA | CD32: 192.87 | CE32: 30.909 | CF32: POSTO SANTA RITA | CM32: 153.13 | CN32: 24.541 | CO32: POSTO SANTA RITA
A33: SAMILA RIBEIRO | B33: ONIX | C33: SIT1G63 | D33: - | E33: 16292 | F33: 18896 | G33: =F33-E33 -> 2604 | H33: =SUM(M33+P33+S33+V33+Y33+AB33+AE33+AH33+AK33+AN33+AQ33+AT33+AW33+AZ33+BC33+BF33+BI33+BL33+BO33+BR33+BU33+BX33+CA33+CD33+CG33+CJ33+CM33+CP33+CS33+CV33+CY33) -> 1145.9 | I33: =COUNTA(N33,Q33,T33,W33,Z33,AC33,AF33,AI33,AL33,AO33,AR33,AU33,AX33,BA33,BD33,BG33,BJ33,BM33,BP33,BS33,BV33,BY33,CB33,CE33,CH33,CK33,CN33,CQ33,CT33,CW33,CZ33) -> 6 | J33: =COUNTIF(M33:DC33,"POSTO SANTA RITA") -> 6 | K33: =COUNTIF(N33:DD33,"POSTO VIP") -> 0 | L33: Julho | P33: 200.26 | Q33: 33.101 | R33: POSTO SANTA RITA | AB33: 189.79 | AC33: 30.711 | AD33: POSTO SANTA RITA | AQ33: 238.06 | AR33: 38.151 | AS33: POSTO SANTA RITA | AW33: 102.27 | AX33: 16.39 | AY33: POSTO SANTA RITA | BL33: 187.7 | BM33: 30.08 | BN33: POSTO SANTA RITA | CD33: 227.82 | CE33: 36.51 | CF33: POSTO SANTA RITA
A34: HERMES XAVIER | B34: ONIX | C34: SIU5B06 | D34: - | E34: 15086 | F34: 18851 | G34: =F34-E34 -> 3765 | H34: =SUM(M34+P34+S34+V34+Y34+AB34+AE34+AH34+AK34+AN34+AQ34+AT34+AW34+AZ34+BC34+BF34+BI34+BL34+BO34+BR34+BU34+BX34+CA34+CD34+CG34+CJ34+CM34+CP34+CS34+CV34+CY34) -> 770.2 | I34: =COUNTA(N34,Q34,T34,W34,Z34,AC34,AF34,AI34,AL34,AO34,AR34,AU34,AX34,BA34,BD34,BG34,BJ34,BM34,BP34,BS34,BV34,BY34,CB34,CE34,CH34,CK34,CN34,CQ34,CT34,CW34,CZ34) -> 3 | J34: =COUNTIF(M34:DC34,"POSTO SANTA RITA") -> 3 | K34: =COUNTIF(N34:DD34,"POSTO VIP") -> 0 | L34: Julho | AK34: 249.6 | AL34: 40 | AM34: POSTO SANTA RITA | BI34: 249.6 | BJ34: 40 | BK34: POSTO SANTA RITA | CV34: 271 | CW34: 43.43 | CX34: POSTO SANTA RITA
A35: ADEMIR DOMINGOS | B35: ARGO | C35: SHW6C40 | D35: - | E35: 28640 | F35: 30643 | G35: =F35-E35 -> 2003 | H35: =SUM(M35+P35+S35+V35+Y35+AB35+AE35+AH35+AK35+AN35+AQ35+AT35+AW35+AZ35+BC35+BF35+BI35+BL35+BO35+BR35+BU35+BX35+CA35+CD35+CG35+CJ35+CM35+CP35+CS35+CV35+CY35) -> 846.08 | I35: =COUNTA(N35,Q35,T35,W35,Z35,AC35,AF35,AI35,AL35,AO35,AR35,AU35,AX35,BA35,BD35,BG35,BJ35,BM35,BP35,BS35,BV35,BY35,CB35,CE35,CH35,CK35,CN35,CQ35,CT35,CW35,CZ35) -> 5 | J35: =COUNTIF(M35:DC35,"POSTO SANTA RITA") -> 4 | K35: =COUNTIF(N35:DD35,"POSTO VIP") -> 1 | L35: Agosto | P35: 188.26 | Q35: 30.17 | R35: POSTO SANTA RITA | AE35: 193 | AF35: 30.93 | AG35: POSTO SANTA RITA | AT35: 146.39 | AU35: 23.46 | AV35: POSTO SANTA RITA | BC35: 107.64 | BD35: 17.25 | BE35: POSTO VIP | CP35: 210.79 | CQ35: 33.78 | CR35: POSTO SANTA RITA
A36: SAMILA RIBEIRO | B36: ONIX | C36: SIT1G63 | D36: - | E36: 18896 | F36: 20292 | G36: =F36-E36 -> 1396 | H36: =SUM(M36+P36+S36+V36+Y36+AB36+AE36+AH36+AK36+AN36+AQ36+AT36+AW36+AZ36+BC36+BF36+BI36+BL36+BO36+BR36+BU36+BX36+CA36+CD36+CG36+CJ36+CM36+CP36+CS36+CV36+CY36) -> 932.32 | I36: =COUNTA(N36,Q36,T36,W36,Z36,AC36,AF36,AI36,AL36,AO36,AR36,AU36,AX36,BA36,BD36,BG36,BJ36,BM36,BP36,BS36,BV36,BY36,CB36,CE36,CH36,CK36,CN36,CQ36,CT36,CW36,CZ36) -> 5 | J36: =COUNTIF(M36:DC36,"POSTO SANTA RITA") -> 5 | K36: =COUNTIF(N36:DD36,"POSTO VIP") -> 0 | L36: Agosto | S36: 219.77 | T36: 35.22 | U36: POSTO SANTA RITA | AT36: 244.11 | AU36: 39.12 | AV36: POSTO SANTA RITA | BF36: 94.41 | BG36: 15.13 | BH36: POSTO SANTA RITA | CD36: 140.03 | CE36: 22.44 | CF36: POSTO SANTA RITA | CY36: 234 | CZ36: 37.5 | DA36: POSTO SANTA RITA
A37: HERMES XAVIER | B37: ONIX | C37: SIU5B06 | D37: - | E37: 18851 | F37: 22250 | G37: =F37-E37 -> 3399 | H37: =SUM(M37+P37+S37+V37+Y37+AB37+AE37+AH37+AK37+AN37+AQ37+AT37+AW37+AZ37+BC37+BF37+BI37+BL37+BO37+BR37+BU37+BX37+CA37+CD37+CG37+CJ37+CM37+CP37+CS37+CV37+CY37) -> 1120.87 | I37: =COUNTA(N37,Q37,T37,W37,Z37,AC37,AF37,AI37,AL37,AO37,AR37,AU37,AX37,BA37,BD37,BG37,BJ37,BM37,BP37,BS37,BV37,BY37,CB37,CE37,CH37,CK37,CN37,CQ37,CT37,CW37,CZ37) -> 5 | J37: =COUNTIF(M37:DC37,"POSTO SANTA RITA") -> 5 | K37: =COUNTIF(N37:DD37,"POSTO VIP") -> 0 | L37: Agosto | S37: 215.4 | T37: 34.52 | U37: POSTO SANTA RITA | AK37: 225.57 | AL37: 36.15 | AM37: POSTO SANTA RITA | BF37: 245.6 | BG37: 39.35 | BH37: POSTO SANTA RITA | CA37: 242.11 | CB37: 38.8 | CC37: POSTO SANTA RITA | CY37: 192.19 | CZ37: 30.8 | DA37: POSTO SANTA RITA
A38: ADEMIR DOMINGOS | B38: ARGO | C38: SHW6C40 | D38: ATIVO | E38: 30643 | F38: 32424 | G38: =F38-E38 -> 1781 | H38: =SUM(M38+P38+S38+V38+Y38+AB38+AE38+AH38+AK38+AN38+AQ38+AT38+AW38+AZ38+BC38+BF38+BI38+BL38+BO38+BR38+BU38+BX38+CA38+CD38+CG38+CJ38+CM38+CP38+CS38+CV38+CY38) -> 660.74 | I38: =COUNTA(N38,Q38,T38,W38,Z38,AC38,AF38,AI38,AL38,AO38,AR38,AU38,AX38,BA38,BD38,BG38,BJ38,BM38,BP38,BS38,BV38,BY38,CB38,CE38,CH38,CK38,CN38,CQ38,CT38,CW38,CZ38) -> 4 | J38: =COUNTIF(M38:DC38,"POSTO S. RITA") -> 0 | K38: =COUNTIF(N38:DD38,"POSTO VIP") -> 0 | L38: Setembro | AB38: 206.66 | AC38: 33.11 | AD38: POSTO SANTA RITA | AQ38: 230.88 | AR38: 37 | AS38: POSTO SANTA RITA | BI38: 153.19 | BJ38: 24.55 | BK38: POSTO SANTA RITA | BO38: 70.01 | BP38: 11.22 | BQ38: POSTO SANTA RITA
A39: SAMILA RIBEIRO | B39: ONIX | C39: SIT1G63 | D39: ATIVO | E39: 20292 | F39: 24366 | G39: =F39-E39 -> 4074 | H39: =SUM(M39+P39+S39+V39+Y39+AB39+AE39+AH39+AK39+AN39+AQ39+AT39+AW39+AZ39+BC39+BF39+BI39+BL39+BO39+BR39+BU39+BX39+CA39+CD39+CG39+CJ39+CM39+CP39+CS39+CV39+CY39) -> 819.61 | I39: =COUNTA(N39,Q39,T39,W39,Z39,AC39,AF39,AI39,AL39,AO39,AR39,AU39,AX39,BA39,BD39,BG39,BJ39,BM39,BP39,BS39,BV39,BY39,CB39,CE39,CH39,CK39,CN39,CQ39,CT39,CW39,CZ39) -> 4 | J39: =COUNTIF(M39:DC39,"POSTO S. RITA") -> 0 | K39: =COUNTIF(N39:DD39,"POSTO VIP") -> 0 | L39: Setembro | V39: 237.3 | W39: 38.02 | X39: POSTO SANTA RITA | BL39: 222.21 | BM39: 35.61 | BN39: POSTO SANTA RITA | BU39: 150 | BV39: 24.04 | BW39: POSTO SANTA RITA | CP39: 210.1 | CQ39: 33.67 | CR39: POSTO SANTA RITA
A40: HERMES XAVIER | B40: ONIX | C40: SIU5B06 | D40: - | E40: 18851 | F40: 22250 | G40: =F40-E40 -> 3399 | H40: =SUM(M40+P40+S40+V40+Y40+AB40+AE40+AH40+AK40+AN40+AQ40+AT40+AW40+AZ40+BC40+BF40+BI40+BL40+BO40+BR40+BU40+BX40+CA40+CD40+CG40+CJ40+CM40+CP40+CS40+CV40+CY40) -> 0 | I40: =COUNTA(N40,Q40,T40,W40,Z40,AC40,AF40,AI40,AL40,AO40,AR40,AU40,AX40,BA40,BD40,BG40,BJ40,BM40,BP40,BS40,BV40,BY40,CB40,CE40,CH40,CK40,CN40,CQ40,CT40,CW40,CZ40) -> 0 | J40: =COUNTIF(M40:DC40,"POSTO S. RITA") -> 0 | K40: =COUNTIF(N40:DD40,"POSTO VIP") -> 0 | L40: Setembro
A41: SAMILA RIBEIRO | B41: ONIX | C41: SIT1G63 | D41: - | E41: 24366 | F41: 27800 | G41: =F41-E41 -> 3434 | H41: =SUM(M41+P41+S41+V41+Y41+AB41+AE41+AH41+AK41+AN41+AQ41+AT41+AW41+AZ41+BC41+BF41+BI41+BL41+BO41+BR41+BU41+BX41+CA41+CD41+CG41+CJ41+CM41+CP41+CS41+CV41+CY41) -> 0 | I41: =COUNTA(N41,Q41,T41,W41,Z41,AC41,AF41,AI41,AL41,AO41,AR41,AU41,AX41,BA41,BD41,BG41,BJ41,BM41,BP41,BS41,BV41,BY41,CB41,CE41,CH41,CK41,CN41,CQ41,CT41,CW41,CZ41) -> 0 | J41: =COUNTIF(M41:DC41,"POSTO S. RITA") -> 0 | K41: =COUNTIF(N41:DD41,"POSTO VIP") -> 0 | L41: Outubro
A42: ADEMIR DOMINGOS | B42: RANGER | C42: RMQ2C16 | D42: - | G42: =F42-E42 -> 0 | H42: =SUM(M42+P42+S42+V42+Y42+AB42+AE42+AH42+AK42+AN42+AQ42+AT42+AW42+AZ42+BC42+BF42+BI42+BL42+BO42+BR42+BU42+BX42+CA42+CD42+CG42+CJ42+CM42+CP42+CS42+CV42+CY42) -> 0 | I42: =COUNTA(N42,Q42,T42,W42,Z42,AC42,AF42,AI42,AL42,AO42,AR42,AU42,AX42,BA42,BD42,BG42,BJ42,BM42,BP42,BS42,BV42,BY42,CB42,CE42,CH42,CK42,CN42,CQ42,CT42,CW42,CZ42) -> 0 | J42: =COUNTIF(M42:DC42,"POSTO S. RITA") -> 0 | K42: =COUNTIF(N42:DD42,"POSTO VIP") -> 0 | L42: Novembro
A43: SAMILA RIBEIRO | B43: RENEGADE | C43: RFY4F46 | D43: - | G43: =F43-E43 -> 0 | H43: =SUM(M43+P43+S43+V43+Y43+AB43+AE43+AH43+AK43+AN43+AQ43+AT43+AW43+AZ43+BC43+BF43+BI43+BL43+BO43+BR43+BU43+BX43+CA43+CD43+CG43+CJ43+CM43+CP43+CS43+CV43+CY43) -> 0 | I43: =COUNTA(N43,Q43,T43,W43,Z43,AC43,AF43,AI43,AL43,AO43,AR43,AU43,AX43,BA43,BD43,BG43,BJ43,BM43,BP43,BS43,BV43,BY43,CB43,CE43,CH43,CK43,CN43,CQ43,CT43,CW43,CZ43) -> 0 | J43: =COUNTIF(M43:DC43,"POSTO S. RITA") -> 0 | K43: =COUNTIF(N43:DD43,"POSTO VIP") -> 0 | L43: Novembro
A44: HERMES XAVIER | B44: S10 | C44: RTF5A73 | D44: - | G44: =F44-E44 -> 0 | H44: =SUM(M44+P44+S44+V44+Y44+AB44+AE44+AH44+AK44+AN44+AQ44+AT44+AW44+AZ44+BC44+BF44+BI44+BL44+BO44+BR44+BU44+BX44+CA44+CD44+CG44+CJ44+CM44+CP44+CS44+CV44+CY44) -> 0 | I44: =COUNTA(N44,Q44,T44,W44,Z44,AC44,AF44,AI44,AL44,AO44,AR44,AU44,AX44,BA44,BD44,BG44,BJ44,BM44,BP44,BS44,BV44,BY44,CB44,CE44,CH44,CK44,CN44,CQ44,CT44,CW44,CZ44) -> 0 | J44: =COUNTIF(M44:DC44,"POSTO S. RITA") -> 0 | K44: =COUNTIF(N44:DD44,"POSTO VIP") -> 0 | L44: Novembro
A45: ADEMIR DOMINGOS | B45: RANGER | C45: RMQ2C16 | D45: - | G45: =F45-E45 -> 0 | H45: =SUM(M45+P45+S45+V45+Y45+AB45+AE45+AH45+AK45+AN45+AQ45+AT45+AW45+AZ45+BC45+BF45+BI45+BL45+BO45+BR45+BU45+BX45+CA45+CD45+CG45+CJ45+CM45+CP45+CS45+CV45+CY45) -> 0 | I45: =COUNTA(N45,Q45,T45,W45,Z45,AC45,AF45,AI45,AL45,AO45,AR45,AU45,AX45,BA45,BD45,BG45,BJ45,BM45,BP45,BS45,BV45,BY45,CB45,CE45,CH45,CK45,CN45,CQ45,CT45,CW45,CZ45) -> 0 | J45: =COUNTIF(M45:DC45,"POSTO S. RITA") -> 0 | K45: =COUNTIF(N45:DD45,"POSTO VIP") -> 0 | L45: Dezembro
A46: SAMILA RIBEIRO | B46: RENEGADE | C46: RFY4F46 | D46: - | G46: =F46-E46 -> 0 | H46: =SUM(M46+P46+S46+V46+Y46+AB46+AE46+AH46+AK46+AN46+AQ46+AT46+AW46+AZ46+BC46+BF46+BI46+BL46+BO46+BR46+BU46+BX46+CA46+CD46+CG46+CJ46+CM46+CP46+CS46+CV46+CY46) -> 0 | I46: =COUNTA(N46,Q46,T46,W46,Z46,AC46,AF46,AI46,AL46,AO46,AR46,AU46,AX46,BA46,BD46,BG46,BJ46,BM46,BP46,BS46,BV46,BY46,CB46,CE46,CH46,CK46,CN46,CQ46,CT46,CW46,CZ46) -> 0 | J46: =COUNTIF(M46:DC46,"POSTO S. RITA") -> 0 | K46: =COUNTIF(N46:DD46,"POSTO VIP") -> 0 | L46: Dezembro
A47: HERMES XAVIER | B47: S10 | C47: RTF5A73 | D47: - | G47: =F47-E47 -> 0 | H47: =SUM(M47+P47+S47+V47+Y47+AB47+AE47+AH47+AK47+AN47+AQ47+AT47+AW47+AZ47+BC47+BF47+BI47+BL47+BO47+BR47+BU47+BX47+CA47+CD47+CG47+CJ47+CM47+CP47+CS47+CV47+CY47) -> 0 | I47: =COUNTA(N47,Q47,T47,W47,Z47,AC47,AF47,AI47,AL47,AO47,AR47,AU47,AX47,BA47,BD47,BG47,BJ47,BM47,BP47,BS47,BV47,BY47,CB47,CE47,CH47,CK47,CN47,CQ47,CT47,CW47,CZ47) -> 0 | J47: =COUNTIF(M47:DC47,"POSTO S. RITA") -> 0 | K47: =COUNTIF(N47:DD47,"POSTO VIP") -> 0 | L47: Dezembro

Sheet 23018_IBIMIRIM
A1: QTD DE VEICULOS ATIVO | B1: =COUNTIF(D3:D32,"ATIVO") -> 0 | C1: CONTROLE DE KM - 2023/2024_23018_IBIMIRIM | K1: ABASTECIMENTO | N1: ABASTECIMENTO | Q1: ABASTECIMENTO | T1: ABASTECIMENTO | W1: ABASTECIMENTO | Z1: ABASTECIMENTO | AC1: ABASTECIMENTO | AF1: ABASTECIMENTO | AI1: ABASTECIMENTO | AL1: ABASTECIMENTO | AO1: ABASTECIMENTO | AR1: ABASTECIMENTO | AU1: ABASTECIMENTO | AX1: ABASTECIMENTO | BA1: ABASTECIMENTO | BD1: ABASTECIMENTO | BG1: ABASTECIMENTO | BJ1: ABASTECIMENTO | BM1: ABASTECIMENTO | BP1: ABASTECIMENTO | BS1: ABASTECIMENTO | BV1: ABASTECIMENTO | BY1: ABASTECIMENTO | CB1: ABASTECIMENTO | CE1: ABASTECIMENTO | CH1: ABASTECIMENTO | CK1: ABASTECIMENTO | CN1: ABASTECIMENTO | CQ1: ABASTECIMENTO | CT1: ABASTECIMENTO | CW1: ABASTECIMENTO | CZ1: OBS | DA1: FOLGA
A2: CONDUTOR | B2: PLACA | C2: VEICULO | D2: STATUS | E2: KM INICIAL | F2: KM FINAL | G2: KM PERCORRIDA | H2: CONSUMO TOTAL | I2: ABASTECIMENTO MÊS | J2: MÊS | K2: 1º DIA VALOR | L2: QTD LITROS | M2: POSTO | N2: 2º DIA VALOR | O2: QTD LITROS | P2: POSTO | Q2: 3º DIA VALOR | R2: QTD LITROS | S2: POSTO | T2: 4º DIA VALOR | U2: QTD LITROS | V2: POSTO | W2: 5º DIA VALOR | X2: QTD LITROS | Y2: POSTO | Z2: 6º DIA VALOR | AA2: QTD LITROS | AB2: POSTO | AC2: 7º DIA VALOR | AD2: QTD LITROS | AE2: POSTO | AF2: 8º DIA VALOR | AG2: QTD LITROS | AH2: POSTO | AI2: 9º DIA VALOR | AJ2: QTD LITROS | AK2: POSTO | AL2: 10º DIA VALOR | AM2: QTD LITROS | AN2: POSTO | AO2: 11º DIA VALOR | AP2: QTD LITROS | AQ2: POSTO | AR2: 12º DIA VALOR | AS2: QTD LITROS | AT2: POSTO | AU2: 13º DIA VALOR | AV2: QTD LITROS | AW2: POSTO | AX2: 14º DIA VALOR | AY2: QTD LITROS | AZ2: POSTO | BA2: 15º DIA VALOR | BB2: QTD LITROS | BC2: POSTO | BD2: 16º DIA VALOR | BE2: QTD LITROS | BF2: POSTO | BG2: 17º DIA VALOR | BH2: QTD LITROS | BI2: POSTO | BJ2: 18º DIA VALOR | BK2: QTD LITROS | BL2: POSTO | BM2: 19º DIA VALOR | BN2: QTD LITROS | BO2: POSTO | BP2: 20º DIA VALOR | BQ2: QTD LITROS | BR2: POSTO | BS2: 21º DIA VALOR | BT2: QTD LITROS | BU2: POSTO | BV2: 22º DIA VALOR | BW2: QTD LITROS | BX2: POSTO | BY2: 23º DIA VALOR | BZ2: QTD LITROS | CA2: POSTO | CB2: 24º DIA VALOR | CC2: QTD LITROS | CD2: POSTO | CE2: 25º DIA VALOR | CF2: QTD LITROS | CG2: POSTO | CH2: 26º DIA VALOR | CI2: QTD LITROS | CJ2: POSTO | CK2: 27º DIA VALOR | CL2: QTD LITROS | CM2: POSTO | CN2: 28º DIA VALOR | CO2: QTD LITROS | CP2: POSTO | CQ2: 29º DIA VALOR | CR2: QTD LITROS | CS2: POSTO | CT2: 30º DIA VALOR | CU2: QTD LITROS | CV2: POSTO | CW2: 31º DIA VALOR | CX2: QTD LITROS | CY2: POSTO
A3: ANDRE / UALACE | B3: SJB3G42 | C3: C3 LIVE | D3: - | E3: 5118 | F3: 6852 | G3: =F3-E3 -> 1734 | H3: =SUM(K3+N3+Q3+T3+W3+Z3+AC3+AF3+AI3+AL3+AO3+AR3+AU3+AX3+BA3+BD3+BG3+BJ3+BM3+BP3+BS3+BV3+BY3+CB3+CE3+CH3+CK3+CN3+CQ3+CT3+CW3) -> 939.87 | I3: =COUNTA(L3,O3,R3,U3,X3,AA3,AD3,AG3,AJ3,AM3,AP3,AS3,AV3,AY3,BB3,BE3,BH3,BK3,BN3,BQ3,BT3,BW3,BZ3,CC3,CF3,CI3,CL3,CO3,CR3,CU3,CX3) -> 4 | J3: Janeiro | T3: 234.72 | U3: 41.991 | V3: VALE DO MOXOTÓ | AI3: 248.03 | AJ3: 44.372 | AK3: VALE DO MOXOTÓ | BM3: 225.04 | BN3: 40.259 | BO3: VALE DO MOXOTÓ | CK3: 232.08 | CL3: 41.517 | CM3: VALE DO MOXOTÓ
A4: JOAO PAULO / JOSE CARLOS | B4: SIH5F91 | C4: JEEP RENEGADE | D4: - | E4: 9480 | F4: 12392 | G4: =F4-E4 -> 2912 | H4: =SUM(K4+N4+Q4+T4+W4+Z4+AC4+AF4+AI4+AL4+AO4+AR4+AU4+AX4+BA4+BD4+BG4+BJ4+BM4+BP4+BS4+BV4+BY4+CB4+CE4+CH4+CK4+CN4+CQ4+CT4+CW4) -> 1771.14 | I4: =COUNTA(L4,O4,R4,U4,X4,AA4,AD4,AG4,AJ4,AM4,AP4,AS4,AV4,AY4,BB4,BE4,BH4,BK4,BN4,BQ4,BT4,BW4,BZ4,CC4,CF4,CI4,CL4,CO4,CR4,CU4,CX4) -> 9 | J4: Janeiro | T4: 251.07 | U4: 44.915 | V4: VALE DO MOXOTÓ | Z4: 161 | AA4: 28.802 | AB4: VALE DO MOXOTÓ | AI4: 41.46 | AJ4: 7.417 | AK4: VALE DO MOXOTÓ | AL4: 228.46 | AM4: 40.871 | AN4: VALE DO MOXOTÓ | AU4: 266.64 | AV4: 47.701 | AW4: VALE DO MOXOTÓ | BJ4: 243.84 | BK4: 43.621 | BL4: VALE DO MOXOTÓ | BM4: 85.64 | BN4: 15.322 | BO4: VALE DO MOXOTÓ | CB4: 248.38 | CC4: 44.434 | CD4: VALE DO MOXOTÓ | CT4: 244.65 | CU4: 43.76 | CV4: VALE DO MOXOTÓ
A5: ALAIN/DEVALDO | B5: SEA2D46 | C5: GOL | D5: - | E5: 28299 | F5: 31590 | G5: =F5-E5 -> 3291 | H5: =SUM(K5+N5+Q5+T5+W5+Z5+AC5+AF5+AI5+AL5+AO5+AR5+AU5+AX5+BA5+BD5+BG5+BJ5+BM5+BP5+BS5+BV5+BY5+CB5+CE5+CH5+CK5+CN5+CQ5+CT5+CW5) -> 1617.06 | I5: =COUNTA(L5,O5,R5,U5,X5,AA5,AD5,AG5,AJ5,AM5,AP5,AS5,AV5,AY5,BB5,BE5,BH5,BK5,BN5,BQ5,BT5,BW5,BZ5,CC5,CF5,CI5,CL5,CO5,CR5,CU5,CX5) -> 7 | J5: Janeiro | Q5: 210.02 | R5: 37.572 | S5: VALE DO MOXOTÓ | Z5: 243.16 | AA5: 43.5 | AB5: VALE DO MOXOTÓ | AI5: 249.42 | AJ5: 44.62 | AK5: VALE DO MOXOTÓ | AU5: 174.27 | AV5: 31.176 | AW5: VALE DO MOXOTÓ | BJ5: 275 | BK5: 49.196 | BL5: VALE DO MOXOTÓ | CB5: 272.17 | CC5: 48.689 | CD5: VALE DO MOXOTÓ | CK5: 193.02 | CL5: 34.531 | CM5: VALE DO MOXOTÓ
A6: FAUSTO ALENCAR | B6: SIM6A02 | C6: ONIX | D6: - | E6: 7930 | F6: 10990 | G6: =F6-E6 -> 3060 | H6: =SUM(K6+N6+Q6+T6+W6+Z6+AC6+AF6+AI6+AL6+AO6+AR6+AU6+AX6+BA6+BD6+BG6+BJ6+BM6+BP6+BS6+BV6+BY6+CB6+CE6+CH6+CK6+CN6+CQ6+CT6+CW6) -> 1380.48 | I6: =COUNTA(L6,O6,R6,U6,X6,AA6,AD6,AG6,AJ6,AM6,AP6,AS6,AV6,AY6,BB6,BE6,BH6,BK6,BN6,BQ6,BT6,BW6,BZ6,CC6,CF6,CI6,CL6,CO6,CR6,CU6,CX6) -> 10 | J6: Janeiro | K6: 181.06 | L6: 32.39 | M6: VALE DO MOXOTÓ | AI6: 168.09 | AJ6: 30.071 | AK6: VALE DO MOXOTÓ | AR6: 197.16 | AS6: 35.271 | AT6: VALE DO MOXOTÓ | BD6: 110 | BE6: 19.679 | BF6: VALE DO MOXOTÓ | BJ6: 197.1 | BK6: 35.26 | BL6: VALE DO MOXOTÓ | BM6: 68.83 | BN6: 12.31 | BO6: VALE DO MOXOTÓ | BV6: 50 | BW6: 8.955 | BX6: VALE DO MOXOTÓ | BY6: 188.62 | BZ6: 33.743 | CA6: VALE DO MOXOTÓ | CB6: 129.29 | CC6: 23.129 | CD6: VALE DO MOXOTÓ | CT6: 90.33 | CU6: 34.04 | CV6: VALE DO MOXOTÓ
A7: LÁZARO FARIA | B7: SIG2C14 | C7: FIAT TORO | D7: - | E7: 9906 | F7: 12829 | G7: =F7-E7 -> 2923 | H7: =SUM(K7+N7+Q7+T7+W7+Z7+AC7+AF7+AI7+AL7+AO7+AR7+AU7+AX7+BA7+BD7+BG7+BJ7+BM7+BP7+BS7+BV7+BY7+CB7+CE7+CH7+CK7+CN7+CQ7+CT7+CW7) -> 2113.45 | I7: =COUNTA(L7,O7,R7,U7,X7,AA7,AD7,AG7,AJ7,AM7,AP7,AS7,AV7,AY7,BB7,BE7,BH7,BK7,BN7,BQ7,BT7,BW7,BZ7,CC7,CF7,CI7,CL7,CO7,CR7,CU7,CX7) -> 9 | J7: Janeiro | N7: 290 | O7: 51.88 | P7: VALE DO MOXOTÓ | Z7: 181.06 | AA7: 32.39 | AB7: VALE DO MOXOTÓ | AL7: 170.36 | AM7: 30.476 | AN7: VALE DO MOXOTÓ | AR7: 251.53 | AS7: 45.006 | AT7: VALE DO MOXOTÓ | BG7: 240 | BH7: 42.943 | BI7: VALE DO MOXOTÓ | BM7: 250.01 | BN7: 44.725 | BO7: VALE DO MOXOTÓ | BY7: 226.31 | BZ7: 40.48 | CA7: VALE DO MOXOTÓ | CH7: 244.12 | CI7: 43.672 | CJ7: VALE DO MOXOTÓ | CT7: 260.06 | CU7: 46.523 | CV7: VALE DO MOXOTÓ
A8: ANDRE / UALACE | B8: SJB3G42 | C8: C3 LIVE | D8: INATIVO | E8: 6852 | F8: 7238 | G8: =F8-E8 -> 386 | H8: =SUM(K8+N8+Q8+T8+W8+Z8+AC8+AF8+AI8+AL8+AO8+AR8+AU8+AX8+BA8+BD8+BG8+BJ8+BM8+BP8+BS8+BV8+BY8+CB8+CE8+CH8+CK8+CN8+CQ8+CT8+CW8) -> 192.06 | I8: =COUNTA(L8,O8,R8,U8,X8,AA8,AD8,AG8,AJ8,AM8,AP8,AS8,AV8,AY8,BB8,BE8,BH8,BK8,BN8,BQ8,BT8,BW8,BZ8,CC8,CF8,CI8,CL8,CO8,CR8,CU8,CX8) -> 1 | J8: Fevereiro | K8: 192.06 | L8: 34.359 | M8: VALE DO MOXOTÓ
A9: ANDRE / UALACE | B9: SIM5H02 | C9: ONIX | D9: - | E9: 8977 | F9: 10936 | G9: =F9-E9 -> 1959 | H9: =SUM(K9+N9+Q9+T9+W9+Z9+AC9+AF9+AI9+AL9+AO9+AR9+AU9+AX9+BA9+BD9+BG9+BJ9+BM9+BP9+BS9+BV9+BY9+CB9+CE9+CH9+CK9+CN9+CQ9+CT9+CW9) -> 722.11 | I9: =COUNTA(L9,O9,R9,U9,X9,AA9,AD9,AG9,AJ9,AM9,AP9,AS9,AV9,AY9,BB9,BE9,BH9,BK9,BN9,BQ9,BT9,BW9,BZ9,CC9,CF9,CI9,CL9,CO9,CR9,CU9,CX9) -> 4 | J9: Fevereiro | Z9: 217.26 | AA9: 38.866 | AB9: VALE DO MOXOTÓ | AU9: 215.01 | AV9: 38.465 | AW9: VALE DO MOXOTÓ | BA9: 92 | BB9: 16.43 | BC9: VALE DO MOXOTÓ | BP9: 197.84 | BQ9: 35.329 | BR9: VALE DO MOXOTÓ
A10: JOAO PAULO / JOSE CARLOS | B10: SIH5F91 | C10: JEEP RENEGADE | D10: - | E10: 12392 | F10: 14177 | G10: =F10-E10 -> 1785 | H10: =SUM(K10+N10+Q10+T10+W10+Z10+AC10+AF10+AI10+AL10+AO10+AR10+AU10+AX10+BA10+BD10+BG10+BJ10+BM10+BP10+BS10+BV10+BY10+CB10+CE10+CH10+CK10+CN10+CQ10+CT10+CW10) -> 1360.15 | I10: =COUNTA(L10,O10,R10,U10,X10,AA10,AD10,AG10,AJ10,AM10,AP10,AS10,AV10,AY10,BB10,BE10,BH10,BK10,BN10,BQ10,BT10,BW10,BZ10,CC10,CF10,CI10,CL10,CO10,CR10,CU10,CX10) -> 6 | J10: Fevereiro | Z10: 258.94 | AA10: 46.323 | AB10: VALE DO MOXOTÓ | AF10: 210.1 | AG10: 37.586 | AH10: VALE DO MOXOTÓ | AU10: 226.06 | AV10: 40.441 | AW10: VALE DO MOXOTÓ | BA10: 160 | BB10: 28.576 | BC10: VALE DO MOXOTÓ | BP10: 267 | BQ10: 47.686 | BR10: VALE DO MOXOTÓ | CK10: 238.05 | CL10: 42.505 | CM10: VALE DO MOXOTÓ
A11: ALAIN/DEVALDO | B11: SEA2D46 | C11: GOL | D11: - | E11: 31590 | F11: 33337 | G11: =F11-E11 -> 1747 | H11: =SUM(K11+N11+Q11+T11+W11+Z11+AC11+AF11+AI11+AL11+AO11+AR11+AU11+AX11+BA11+BD11+BG11+BJ11+BM11+BP11+BS11+BV11+BY11+CB11+CE11+CH11+CK11+CN11+CQ11+CT11+CW11) -> 1118.26 | I11: =COUNTA(L11,O11,R11,U11,X11,AA11,AD11,AG11,AJ11,AM11,AP11,AS11,AV11,AY11,BB11,BE11,BH11,BK11,BN11,BQ11,BT11,BW11,BZ11,CC11,CF11,CI11,CL11,CO11,CR11,CU11,CX11) -> 5 | J11: Fevereiro | K11: 272.13 | L11: 48.68 | M11: VALE DO MOXOTÓ | AF11: 175.08 | AG11: 31.332 | AH11: VALE DO MOXOTÓ | BP11: 225.04 | BQ11: 40.185 | BR11: VALE DO MOXOTÓ | BV11: 176.01 | BW11: 31.431 | BX11: VALE DO MOXOTÓ | CQ11: 270 | CR11: 48.219 | CS11: VALE DO MOXOTÓ
A12: FAUSTO ALENCAR | B12: SIM6A02 | C12: ONIX | D12: - | E12: 10990 | F12: 11827 | G12: =F12-E12 -> 837 | H12: =SUM(K12+N12+Q12+T12+W12+Z12+AC12+AF12+AI12+AL12+AO12+AR12+AU12+AX12+BA12+BD12+BG12+BJ12+BM12+BP12+BS12+BV12+BY12+CB12+CE12+CH12+CK12+CN12+CQ12+CT12+CW12) -> 619.15 | I12: =COUNTA(L12,O12,R12,U12,X12,AA12,AD12,AG12,AJ12,AM12,AP12,AS12,AV12,AY12,BB12,BE12,BH12,BK12,BN12,BQ12,BT12,BW12,BZ12,CC12,CF12,CI12,CL12,CO12,CR12,CU12,CX12) -> 3 | J12: Fevereiro | K12: 183.03 | L12: 32.744 | M12: VALE DO MOXOTÓ | AF12: 210.02 | AG12: 37.572 | AH12: VALE DO MOXOTÓ | CK12: 226.1 | CL12: 40.376 | CM12: VALE DO MOXOTÓ
A13: LÁZARO FARIA | B13: SIG2C14 | C13: FIAT TORO | D13: - | E13: 12829 | F13: 15413 | G13: =F13-E13 -> 2584 | H13: =SUM(K13+N13+Q13+T13+W13+Z13+AC13+AF13+AI13+AL13+AO13+AR13+AU13+AX13+BA13+BD13+BG13+BJ13+BM13+BP13+BS13+BV13+BY13+CB13+CE13+CH13+CK13+CN13+CQ13+CT13+CW13) -> 2011.44 | I13: =COUNTA(L13,O13,R13,U13,X13,AA13,AD13,AG13,AJ13,AM13,AP13,AS13,AV13,AY13,BB13,BE13,BH13,BK13,BN13,BQ13,BT13,BW13,BZ13,CC13,CF13,CI13,CL13,CO13,CR13,CU13,CX13) -> 9 | J13: Fevereiro | Q13: 240.11 | R13: 42.954 | S13: VALE DO MOXOTÓ | AC13: 257.41 | AD13: 46.049 | AE13: VALE DO MOXOTÓ | AF13: 86.03 | AG13: 15.391 | AH13: VALE DO MOXOTÓ | AU13: 250.03 | AV13: 44.729 | AW13: VALE DO MOXOTÓ | BA13: 220.08 | BB13: 39.3 | BC13: VALE DO MOXOTÓ | BP13: 256.01 | BQ13: 45.717 | BR13: VALE DO MOXOTÓ | BV13: 195.04 | BW13: 34.83 | BX13: VALE DO MOXOTÓ | CK13: 288.83 | CL13: 51.577 | CM13: VALE DO MOXOTÓ | CQ13: 217.9 | CR13: 38.822 | CS13: VALE DO MOXOTÓ
A14: DANIEL | B14: SIN6B14 | C14: ONIX | D14: - | E14: 13854 | F14: 15662 | G14: =F14-E14 -> 1808 | H14: =SUM(K14+N14+Q14+T14+W14+Z14+AC14+AF14+AI14+AL14+AO14+AR14+AU14+AX14+BA14+BD14+BG14+BJ14+BM14+BP14+BS14+BV14+BY14+CB14+CE14+CH14+CK14+CN14+CQ14+CT14+CW14) -> 849.72 | I14: =COUNTA(L14,O14,R14,U14,X14,AA14,AD14,AG14,AJ14,AM14,AP14,AS14,AV14,AY14,BB14,BE14,BH14,BK14,BN14,BQ14,BT14,BW14,BZ14,CC14,CF14,CI14,CL14,CO14,CR14,CU14,CX14) -> 4 | J14: Março | W14: 180.09 | X14: 31.876 | Y14: VALE DO MOXOTÓ | AR14: 247.01 | AS14: 38.44 | AT14: VALE DO MOXOTÓ | BJ14: 200 | BK14: 35.402 | BL14: VALE DO MOXOTÓ | CH14: 222.62 | CI14: 39.402 | CJ14: VALE DO MOXOTÓ
A15: JOAO PAULO / JOSE CARLOS | B15: SIH5F91 | C15: JEEP RENEGADE | D15: - | E15: 14177 | F15: 16988 | G15: =F15-E15 -> 2811 | H15: =SUM(K15+N15+Q15+T15+W15+Z15+AC15+AF15+AI15+AL15+AO15+AR15+AU15+AX15+BA15+BD15+BG15+BJ15+BM15+BP15+BS15+BV15+BY15+CB15+CE15+CH15+CK15+CN15+CQ15+CT15+CW15) -> 1177.71 | I15: =COUNTA(L15,O15,R15,U15,X15,AA15,AD15,AG15,AJ15,AM15,AP15,AS15,AV15,AY15,BB15,BE15,BH15,BK15,BN15,BQ15,BT15,BW15,BZ15,CC15,CF15,CI15,CL15,CO15,CR15,CU15,CX15) -> 5 | J15: Março | W15: 185 | X15: 32.744 | Y15: VALE DO MOXOTÓ | AR15: 269.05 | AS15: 47.62 | AT15: VALE DO MOXOTÓ | AX15: 171.09 | AY15: 30.283 | AZ15: VALE DO MOXOTÓ | BM15: 290.44 | BN15: 51.406 | BO15: VALE DO MOXOTÓ | CH15: 262.13 | CI15: 46.392 | CJ15: VALE DO MOXOTÓ
A16: ALAIN/DEVALDO | B16: SAQ6E86 | C16: ONIX | D16: - | E16: 8252 | F16: 9227 | G16: =F16-E16 -> 975 | H16: =SUM(K16+N16+Q16+T16+W16+Z16+AC16+AF16+AI16+AL16+AO16+AR16+AU16+AX16+BA16+BD16+BG16+BJ16+BM16+BP16+BS16+BV16+BY16+CB16+CE16+CH16+CK16+CN16+CQ16+CT16+CW16) -> 233.2 | I16: =COUNTA(L16,O16,R16,U16,X16,AA16,AD16,AG16,AJ16,AM16,AP16,AS16,AV16,AY16,BB16,BE16,BH16,BK16,BN16,BQ16,BT16,BW16,BZ16,CC16,CF16,CI16,CL16,CO16,CR16,CU16,CX16) -> 1 | J16: Março | CH16: 233.2 | CI16: 41.276 | CJ16: VALE DO MOXOTÓ
A17: ALAIN/DEVALDO | B17: SEA2D46 | C17: GOL | D17: - | E17: 33337 | F17: 35349 | G17: =F17-E17 -> 2012 | H17: =SUM(K17+N17+Q17+T17+W17+Z17+AC17+AF17+AI17+AL17+AO17+AR17+AU17+AX17+BA17+BD17+BG17+BJ17+BM17+BP17+BS17+BV17+BY17+CB17+CE17+CH17+CK17+CN17+CQ17+CT17+CW17) -> 636.8 | I17: =COUNTA(L17,O17,R17,U17,X17,AA17,AD17,AG17,AJ17,AM17,AP17,AS17,AV17,AY17,BB17,BE17,BH17,BK17,BN17,BQ17,BT17,BW17,BZ17,CC17,CF17,CI17,CL17,CO17,CR17,CU17,CX17) -> 2 | J17: Março | AC17: 323.6 | AD17: 57.006 | AE17: VALE DO MOXOTÓ | BM17: 313.2 | BN17: 55.43 | BO17: VALE DO MOXOTÓ
A18: FAUSTO ALENCAR | B18: SIM6A02 | C18: ONIX | D18: - | E18: 11827 | F18: 12891 | G18: =F18-E18 -> 1064 | H18: =SUM(K18+N18+Q18+T18+W18+Z18+AC18+AF18+AI18+AL18+AO18+AR18+AU18+AX18+BA18+BD18+BG18+BJ18+BM18+BP18+BS18+BV18+BY18+CB18+CE18+CH18+CK18+CN18+CQ18+CT18+CW18) -> 118 | I18: =COUNTA(L18,O18,R18,U18,X18,AA18,AD18,AG18,AJ18,AM18,AP18,AS18,AV18,AY18,BB18,BE18,BH18,BK18,BN18,BQ18,BT18,BW18,BZ18,CC18,CF18,CI18,CL18,CO18,CR18,CU18,CX18) -> 1 | J18: Março | AF18: 118 | AG18: 20.88 | AH18: VALE DO MOXOTÓ
A19: LAZARO FARIA | B19: RVJ8D67 | C19: PULSE | D19: - | E19: 34271 | F19: 35621 | G19: =F19-E19 -> 1350 | H19: =SUM(K19+N19+Q19+T19+W19+Z19+AC19+AF19+AI19+AL19+AO19+AR19+AU19+AX19+BA19+BD19+BG19+BJ19+BM19+BP19+BS19+BV19+BY19+CB19+CE19+CH19+CK19+CN19+CQ19+CT19+CW19) -> 634.82 | I19: =COUNTA(L19,O19,R19,U19,X19,AA19,AD19,AG19,AJ19,AM19,AP19,AS19,AV19,AY19,BB19,BE19,BH19,BK19,BN19,BQ19,BT19,BW19,BZ19,CC19,CF19,CI19,CL19,CO19,CR19,CU19,CX19) -> 3 | J19: Março | BM19: 224.9 | BN19: 39.8 | BO19: VALE DO MOXOTÓ | BS19: 200.06 | BT19: 35.409 | BU19: VALE DO MOXOTÓ | CH19: 209.86 | CI19: 37.412 | CJ19: VALE DO MOXOTÓ
A20: ANDRE / UALACE | B20: RTG4C60 | C20: PEUGEOT 208 | D20: - | E20: 45795 | F20: 47531 | G20: =F20-E20 -> 1736 | H20: =SUM(K20+N20+Q20+T20+W20+Z20+AC20+AF20+AI20+AL20+AO20+AR20+AU20+AX20+BA20+BD20+BG20+BJ20+BM20+BP20+BS20+BV20+BY20+CB20+CE20+CH20+CK20+CN20+CQ20+CT20+CW20) -> 740.16 | I20: =COUNTA(L20,O20,R20,U20,X20,AA20,AD20,AG20,AJ20,AM20,AP20,AS20,AV20,AY20,BB20,BE20,BH20,BK20,BN20,BQ20,BT20,BW20,BZ20,CC20,CF20,CI20,CL20,CO20,CR20,CU20,CX20) -> 3 | J20: Março | AX20: 240.19 | AY20: 42.51 | AZ20: VALE DO MOXOTÓ | BP20: 246.12 | BQ20: 43.562 | BR20: VALE DO MOXOTÓ | CE20: 253.85 | CF20: 44.93 | CG20: VALE DO MOXOTÓ
A21: LÁZARO FARIA | B21: SIG2C14 | C21: FIAT TORO | D21: - | E21: 15413 | F21: 17500 | G21: =F21-E21 -> 2087 | H21: =SUM(K21+N21+Q21+T21+W21+Z21+AC21+AF21+AI21+AL21+AO21+AR21+AU21+AX21+BA21+BD21+BG21+BJ21+BM21+BP21+BS21+BV21+BY21+CB21+CE21+CH21+CK21+CN21+CQ21+CT21+CW21) -> 1010.77 | I21: =COUNTA(L21,O21,R21,U21,X21,AA21,AD21,AG21,AJ21,AM21,AP21,AS21,AV21,AY21,BB21,BE21,BH21,BK21,BN21,BQ21,BT21,BW21,BZ21,CC21,CF21,CI21,CL21,CO21,CR21,CU21,CX21) -> 4 | J21: Março | W21: 264.83 | X21: 46.87 | Y21: VALE DO MOXOTÓ | AC21: 208.05 | AD21: 36.824 | AE21: VALE DO MOXOTÓ | AR21: 265.8 | AS21: 47.04 | AT21: VALE DO MOXOTÓ | AX21: 272.09 | AY21: 48.159 | AZ21: VALE DO MOXOTÓ
A22: ANDRE / UALACE | B22: RTG4C60 | C22: PEUGEOT 208 | D22: - | E22: 47531 | F22: 49294 | G22: =F22-E22 -> 1763 | H22: =SUM(K22+N22+Q22+T22+W22+Z22+AC22+AF22+AI22+AL22+AO22+AR22+AU22+AX22+BA22+BD22+BG22+BJ22+BM22+BP22+BS22+BV22+BY22+CB22+CE22+CH22+CK22+CN22+CQ22+CT22+CW22) -> 765.1 | I22: =COUNTA(L22,O22,R22,U22,X22,AA22,AD22,AG22,AJ22,AM22,AP22,AS22,AV22,AY22,BB22,BE22,BH22,BK22,BN22,BQ22,BT22,BW22,BZ22,CC22,CF22,CI22,CL22,CO22,CR22,CU22,CX22) -> 4 | J22: Abril | N22: 205.04 | O22: 36.29 | P22: VALE DO MOXOTÓ | AI22: 231.04 | AJ22: 40.893 | AK22: VALE DO MOXOTÓ | CE22: 80.11 | CF22: 13.51 | CG22: VALE DO MOXOTÓ | CT22: 248.91 | CU22: 41.97 | CV22: VALE DO MOXOTÓ
A23: JOAO PAULO / JOSE CARLOS | B23: SIH5F91 | C23: JEEP RENEGADE | D23: - | E23: 16988 | F23: 18807 | G23: =F23-E23 -> 1819 | H23: =SUM(K23+N23+Q23+T23+W23+Z23+AC23+AF23+AI23+AL23+AO23+AR23+AU23+AX23+BA23+BD23+BG23+BJ23+BM23+BP23+BS23+BV23+BY23+CB23+CE23+CH23+CK23+CN23+CQ23+CT23+CW23) -> 884.81 | I23: =COUNTA(L23,O23,R23,U23,X23,AA23,AD23,AG23,AJ23,AM23,AP23,AS23,AV23,AY23,BB23,BE23,BH23,BK23,BN23,BQ23,BT23,BW23,BZ23,CC23,CF23,CI23,CL23,CO23,CR23,CU23,CX23) -> 4 | J23: Abril | N23: 242.23 | O23: 42.87 | P23: VALE DO MOXOTÓ | T23: 182.03 | U23: 32.21 | V23: VALE DO MOXOTÓ | AI23: 192.58 | AJ23: 34.08 | AK23: VALE DO MOXOTÓ | CT23: 267.97 | CU23: 45.18 | CV23: VALE DO MOXOTÓ
A24: ALAIN/DEVALDO | B24: SHQ6E86 | C24: ONIX | D24: - | E24: 9227 | F24: 11962 | G24: =F24-E24 -> 2735 | H24: =SUM(K24+N24+Q24+T24+W24+Z24+AC24+AF24+AI24+AL24+AO24+AR24+AU24+AX24+BA24+BD24+BG24+BJ24+BM24+BP24+BS24+BV24+BY24+CB24+CE24+CH24+CK24+CN24+CQ24+CT24+CW24) -> 677.2 | I24: =COUNTA(L24,O24,R24,U24,X24,AA24,AD24,AG24,AJ24,AM24,AP24,AS24,AV24,AY24,BB24,BE24,BH24,BK24,BN24,BQ24,BT24,BW24,BZ24,CC24,CF24,CI24,CL24,CO24,CR24,CU24,CX24) -> 4 | J24: Abril | N24: 235.82 | O24: 41.73 | P24: VALE DO MOXOTÓ | T24: 120.06 | U24: 21.25 | V24: VALE DO MOXOTÓ | CE24: 85.01 | CF24: 14.33 | CG24: VALE DO MOXOTÓ | CT24: 236.31 | CU24: 39.85 | CV24: VALE DO MOXOTÓ
A25: DANIEL | B25: SIN6B14 | C25: ONIX | D25: - | E25: 15662 | F25: 17158 | G25: =F25-E25 -> 1496 | H25: =SUM(K25+N25+Q25+T25+W25+Z25+AC25+AF25+AI25+AL25+AO25+AR25+AU25+AX25+BA25+BD25+BG25+BJ25+BM25+BP25+BS25+BV25+BY25+CB25+CE25+CH25+CK25+CN25+CQ25+CT25+CW25) -> 533.93 | I25: =COUNTA(L25,O25,R25,U25,X25,AA25,AD25,AG25,AJ25,AM25,AP25,AS25,AV25,AY25,BB25,BE25,BH25,BK25,BN25,BQ25,BT25,BW25,BZ25,CC25,CF25,CI25,CL25,CO25,CR25,CU25,CX25) -> 3 | J25: Abril | N25: 157.08 | O25: 27.8 | P25: VALE DO MOXOTÓ | AI25: 161.88 | AJ25: 29.65 | AK25: VALE DO MOXOTÓ | CT25: 214.97 | CU25: 36.25 | CV25: VALE DO MOXOTÓ
A26: LÁZARO FARIA | B26: RVJ8D67 | C26: PULSE | D26: - | E26: 35621 | F26: 37846 | G26: =F26-E26 -> 2225 | H26: =SUM(K26+N26+Q26+T26+W26+Z26+AC26+AF26+AI26+AL26+AO26+AR26+AU26+AX26+BA26+BD26+BG26+BJ26+BM26+BP26+BS26+BV26+BY26+CB26+CE26+CH26+CK26+CN26+CQ26+CT26+CW26) -> 766.53 | I26: =COUNTA(L26,O26,R26,U26,X26,AA26,AD26,AG26,AJ26,AM26,AP26,AS26,AV26,AY26,BB26,BE26,BH26,BK26,BN26,BQ26,BT26,BW26,BZ26,CC26,CF26,CI26,CL26,CO26,CR26,CU26,CX26) -> 5 | J26: Abril | N26: 201 | O26: 32.58 | P26: VALE DO MOXOTÓ | T26: 119.01 | U26: 21.06 | V26: VALE DO MOXOTÓ | AI26: 135.49 | AJ26: 23.98 | AK26: VALE DO MOXOTÓ | CE26: 193.13 | CF26: 32.56 | CG26: VALE DO MOXOTÓ | CT26: 117.9 | CU26: 19.88 | CV26: VALE DO MOXOTÓ
A27: CLAUDIO | B27: SIN6B14 | C27: ONIX | D27: - | E27: 17158 | F27: 18781 | G27: =F27-E27 -> 1623 | H27: =SUM(K27+N27+Q27+T27+W27+Z27+AC27+AF27+AI27+AL27+AO27+AR27+AU27+AX27+BA27+BD27+BG27+BJ27+BM27+BP27+BS27+BV27+BY27+CB27+CE27+CH27+CK27+CN27+CQ27+CT27+CW27) -> 850.67 | I27: =COUNTA(L27,O27,R27,U27,X27,AA27,AD27,AG27,AJ27,AM27,AP27,AS27,AV27,AY27,BB27,BE27,BH27,BK27,BN27,BQ27,BT27,BW27,BZ27,CC27,CF27,CI27,CL27,CO27,CR27,CU27,CX27) -> 5 | J27: Maio | T27: 153.06 | U27: 25.81 | V27: VALE DO MOXOTÓ | AO27: 215.09 | AP27: 36.27 | AQ27: VALE DO MOXOTÓ | AX27: 185 | AY27: 31.19 | AZ27: VALE DO MOXOTÓ | BD27: 93 | BE27: 15.68 | BF27: VALE DO MOXOTÓ | CN27: 204.52 | CO27: 34.49 | CP27: VALE DO MOXOTÓ
A28: ANDRE / UALACE | B28: SIH5F91 | C28: JEEP RENEGADE | D28: - | E28: 18807 | F28: 20643 | G28: =F28-E28 -> 1836 | H28: =SUM(K28+N28+Q28+T28+W28+Z28+AC28+AF28+AI28+AL28+AO28+AR28+AU28+AX28+BA28+BD28+BG28+BJ28+BM28+BP28+BS28+BV28+BY28+CB28+CE28+CH28+CK28+CN28+CQ28+CT28+CW28) -> 1244.02 | I28: =COUNTA(L28,O28,R28,U28,X28,AA28,AD28,AG28,AJ28,AM28,AP28,AS28,AV28,AY28,BB28,BE28,BH28,BK28,BN28,BQ28,BT28,BW28,BZ28,CC28,CF28,CI28,CL28,CO28,CR28,CU28,CX28) -> 6 | J28: Maio | AC28: 146.02 | AD28: 24.62 | AE28: VALE DO MOXOTÓ | AX28: 291.45 | AY28: 49.14 | AZ28: VALE DO MOXOTÓ | BD28: 163.83 | BE28: 27.62 | BF28: VALE DO MOXOTÓ | BS28: 227.64 | BT28: 38.39 | BU28: VALE DO MOXOTÓ | BY28: 132.02 | BZ28: 22.25 | CA28: VALE DO MOXOTÓ | CN28: 283.06 | CO28: 47.03 | CP28: VALE DO MOXOTÓ
A29: LÁZARO FARIA | B29: RVJ8D67 | C29: PULSE | D29: - | G29: =F29-E29 -> 0 | H29: =SUM(K29+N29+Q29+T29+W29+Z29+AC29+AF29+AI29+AL29+AO29+AR29+AU29+AX29+BA29+BD29+BG29+BJ29+BM29+BP29+BS29+BV29+BY29+CB29+CE29+CH29+CK29+CN29+CQ29+CT29+CW29) -> 192.07 | I29: =COUNTA(L29,O29,R29,U29,X29,AA29,AD29,AG29,AJ29,AM29,AP29,AS29,AV29,AY29,BB29,BE29,BH29,BK29,BN29,BQ29,BT29,BW29,BZ29,CC29,CF29,CI29,CL29,CO29,CR29,CU29,CX29) -> 1 | J29: Maio | T29: 192.07 | U29: 32.39 | V29: VALE DO MOXOTÓ
A30: JOSE CARLOS | B30: SYU1D42 | C30: ONIX | D30: - | E30: 1079 | F30: 2534 | G30: =F30-E30 -> 1455 | H30: =SUM(K30+N30+Q30+T30+W30+Z30+AC30+AF30+AI30+AL30+AO30+AR30+AU30+AX30+BA30+BD30+BG30+BJ30+BM30+BP30+BS30+BV30+BY30+CB30+CE30+CH30+CK30+CN30+CQ30+CT30+CW30) -> 982.94 | I30: =COUNTA(L30,O30,R30,U30,X30,AA30,AD30,AG30,AJ30,AM30,AP30,AS30,AV30,AY30,BB30,BE30,BH30,BK30,BN30,BQ30,BT30,BW30,BZ30,CC30,CF30,CI30,CL30,CO30,CR30,CU30,CX30) -> 6 | J30: Maio | AC30: 232.78 | AD30: 39.25 | AE30: VALE DO MOXOTÓ | AX30: 220.3 | AY30: 37.1 | AZ30: VALE DO MOXOTÓ | BD30: 84.69 | BE30: 14.28 | BF30: VALE DO MOXOTÓ | BY30: 170.14 | BZ30: 28.6 | CA30: VALE DO MOXOTÓ | CN30: 190.03 | CO30: 32.47 | CP30: VALE DO MOXOTÓ | CT30: 85 | CU30: 20.24 | CV30: VALE DO MOXOTÓ
A31: ALAIN | B31: SHQ6E86 | C31: ONIX | D31: - | E31: 11962 | F31: 14386 | G31: =F31-E31 -> 2424 | H31: =SUM(K31+N31+Q31+T31+W31+Z31+AC31+AF31+AI31+AL31+AO31+AR31+AU31+AX31+BA31+BD31+BG31+BJ31+BM31+BP31+BS31+BV31+BY31+CB31+CE31+CH31+CK31+CN31+CQ31+CT31+CW31) -> 1199.93 | I31: =COUNTA(L31,O31,R31,U31,X31,AA31,AD31,AG31,AJ31,AM31,AP31,AS31,AV31,AY31,BB31,BE31,BH31,BK31,BN31,BQ31,BT31,BW31,BZ31,CC31,CF31,CI31,CL31,CO31,CR31,CU31,CX31) -> 6 | J31: Maio | AC31: 245.85 | AD31: 41.32 | AE31: VALE DO MOXOTÓ | AL31: 182.79 | AM31: 30.82 | AN31: VALE DO MOXOTÓ | BD31: 105 | BE31: 17.72 | BF31: VALE DO MOXOTÓ | BG31: 160.87 | BH31: 27.12 | BI31: VALE DO MOXOTÓ | BY31: 255.77 | BZ31: 43.13 | CA31: VALE DO MOXOTÓ | CN31: 249.65 | CO31: 42.1 | CP31: VALE DO MOXOTÓ
A32: CLAUDIO | B32: SIN6B14 | C32: ONIX | D32: - | E32: 18781 | F32: 19835 | G32: =F32-E32 -> 1054 | H32: =SUM(K32+N32+Q32+T32+W32+Z32+AC32+AF32+AI32+AL32+AO32+AR32+AU32+AX32+BA32+BD32+BG32+BJ32+BM32+BP32+BS32+BV32+BY32+CB32+CE32+CH32+CK32+CN32+CQ32+CT32+CW32) -> 777.82 | I32: =COUNTA(L32,O32,R32,U32,X32,AA32,AD32,AG32,AJ32,AM32,AP32,AS32,AV32,AY32,BB32,BE32,BH32,BK32,BN32,BQ32,BT32,BW32,BZ32,CC32,CF32,CI32,CL32,CO32,CR32,CU32,CX32) -> 5 | J32: Junho | T32: 100.04 | U32: 16.871 | V32: VALE DO MOXOTÓ | Z32: 195.42 | AA32: 32.95 | AB32: VALE DO MOXOTÓ | AO32: 163.57 | AP32: 27.58 | AQ32: VALE DO MOXOTÓ | CE32: 225.93 | CF32: 38.359 | CG32: VALE DO MOXOTÓ | CK32: 92.86 | CL32: 14.88 | CM32: VALE DO MOXOTÓ
A33: ANDRE / UALACE | B33: SIH5F91 | C33: JEEP RENEGADE | D33: - | E33: 20643 | F33: 23591 | G33: =F33-E33 -> 2948 | H33: =SUM(K33+N33+Q33+T33+W33+Z33+AC33+AF33+AI33+AL33+AO33+AR33+AU33+AX33+BA33+BD33+BG33+BJ33+BM33+BP33+BS33+BV33+BY33+CB33+CE33+CH33+CK33+CN33+CQ33+CT33+CW33) -> 948.32 | I33: =COUNTA(L33,O33,R33,U33,X33,AA33,AD33,AG33,AJ33,AM33,AP33,AS33,AV33,AY33,BB33,BE33,BH33,BK33,BN33,BQ33,BT33,BW33,BZ33,CC33,CF33,CI33,CL33,CO33,CR33,CU33,CX33) -> 5 | J33: Junho | Z33: 251.5 | AA33: 42.414 | AB33: VALE DO MOXOTÓ | AU33: 275.01 | AV33: 40.37 | AW33: VALE DO MOXOTÓ | BJ33: 258 | BK33: 43.5 | BL33: VALE DO MOXOTÓ | BP33: 68.81 | BQ33: 11.683 | BR33: VALE DO MOXOTÓ | CK33: 95 | CL33: 16.142 | CM33: VALE DO MOXOTÓ
A34: JOSE CARLOS | B34: SYU1D42 | C34: ONIX | D34: - | E34: 2534 | F34: 3680 | G34: =F34-E34 -> 1146 | H34: =SUM(K34+N34+Q34+T34+W34+Z34+AC34+AF34+AI34+AL34+AO34+AR34+AU34+AX34+BA34+BD34+BG34+BJ34+BM34+BP34+BS34+BV34+BY34+CB34+CE34+CH34+CK34+CN34+CQ34+CT34+CW34) -> 683.36 | I34: =COUNTA(L34,O34,R34,U34,X34,AA34,AD34,AG34,AJ34,AM34,AP34,AS34,AV34,AY34,BB34,BE34,BH34,BK34,BN34,BQ34,BT34,BW34,BZ34,CC34,CF34,CI34,CL34,CO34,CR34,CU34,CX34) -> 4 | J34: Junho | T34: 125.06 | U34: 21.09 | V34: VALE DO MOXOTÓ | AO34: 190.24 | AP34: 32.077 | AQ34: VALE DO MOXOTÓ | BJ34: 181 | BK34: 30.52 | BL34: VALE DO MOXOTÓ | CK34: 187.06 | CL34: 31.759 | CM34: VALE DO MOXOTÓ
A35: ALAIN | B35: SHQ6E86 | C35: ONIX | D35: - | E35: 14386 | F35: 16727 | G35: =F35-E35 -> 2341 | H35: =SUM(K35+N35+Q35+T35+W35+Z35+AC35+AF35+AI35+AL35+AO35+AR35+AU35+AX35+BA35+BD35+BG35+BJ35+BM35+BP35+BS35+BV35+BY35+CB35+CE35+CH35+CK35+CN35+CQ35+CT35+CW35) -> 1164.87 | I35: =COUNTA(L35,O35,R35,U35,X35,AA35,AD35,AG35,AJ35,AM35,AP35,AS35,AV35,AY35,BB35,BE35,BH35,BK35,BN35,BQ35,BT35,BW35,BZ35,CC35,CF35,CI35,CL35,CO35,CR35,CU35,CX35) -> 6 | J35: Junho | T35: 200 | U35: 33 | V35: VALE DO MOXOTÓ | Z35: 130.01 | AA35: 21.925 | AB35: VALE DO MOXOTÓ | AO35: 235.1 | AP35: 39.646 | AQ35: VALE DO MOXOTÓ | BJ35: 252.2 | BK35: 42.531 | BL35: VALE DO MOXOTÓ | BP35: 95 | BQ35: 16.12 | BR35: VALE DO MOXOTÓ | CK35: 252.56 | CL35: 42.88 | CM35: VALE DO MOXOTÓ
A36: CLAUDIO | B36: SIN6B14 | C36: ONIX | D36: - | E36: 19835 | F36: 22725 | G36: =F36-E36 -> 2890 | H36: =SUM(K36+N36+Q36+T36+W36+Z36+AC36+AF36+AI36+AL36+AO36+AR36+AU36+AX36+BA36+BD36+BG36+BJ36+BM36+BP36+BS36+BV36+BY36+CB36+CE36+CH36+CK36+CN36+CQ36+CT36+CW36) -> 868.36 | I36: =COUNTA(L36,O36,R36,U36,X36,AA36,AD36,AG36,AJ36,AM36,AP36,AS36,AV36,AY36,BB36,BE36,BH36,BK36,BN36,BQ36,BT36,BW36,BZ36,CC36,CF36,CI36,CL36,CO36,CR36,CU36,CX36) -> 7 | J36: Julho | AI36: 216.99 | AJ36: 36.226 | AK36: VALE DO MOXOTÓ | AO36: 97.3 | AP36: 15.745 | AQ36: VALE DO MOXOTÓ | BD36: 125.73 | BE36: 30.346 | BF36: VALE DO MOXOTÓ | BJ36: 75.69 | BK36: 12.248 | BL36: VALE DO MOXOTÓ | BY36: 137.7 | BZ36: 22.283 | CA36: VALE DO MOXOTÓ | CE36: 56.04 | CF36: 9.068 | CG36: VALE DO MOXOTÓ | CT36: 158.91 | CU36: 25.714 | CV36: VALE DO MOXOTÓ
A37: ANDRE / UALACE | B37: SIH5F91 | C37: JEEP RENEGADE | D37: - | E37: 23591 | F37: 24968 | G37: =F37-E37 -> 1377 | H37: =SUM(K37+N37+Q37+T37+W37+Z37+AC37+AF37+AI37+AL37+AO37+AR37+AU37+AX37+BA37+BD37+BG37+BJ37+BM37+BP37+BS37+BV37+BY37+CB37+CE37+CH37+CK37+CN37+CQ37+CT37+CW37) -> 841.64 | I37: =COUNTA(L37,O37,R37,U37,X37,AA37,AD37,AG37,AJ37,AM37,AP37,AS37,AV37,AY37,BB37,BE37,BH37,BK37,BN37,BQ37,BT37,BW37,BZ37,CC37,CF37,CI37,CL37,CO37,CR37,CU37,CX37) -> 4 | J37: Julho | T37: 227.82 | U37: 38.68 | V37: VALE DO MOXOTÓ | AI37: 186.87 | AJ37: 31.198 | AK37: VALE DO MOXOTÓ | BJ37: 212.29 | BK37: 34.352 | BL37: VALE DO MOXOTÓ | CE37: 214.66 | CF37: 34.735 | CG37: VALE DO MOXOTÓ
A38: ANDRE / UALACE | B38: EZ01E92 | C38: TCROSS | D38: - | E38: 39967 | F38: 40418 | G38: =F38-E38 -> 451 | H38: =SUM(K38+N38+Q38+T38+W38+Z38+AC38+AF38+AI38+AL38+AO38+AR38+AU38+AX38+BA38+BD38+BG38+BJ38+BM38+BP38+BS38+BV38+BY38+CB38+CE38+CH38+CK38+CN38+CQ38+CT38+CW38) -> 245.01 | I38: =COUNTA(L38,O38,R38,U38,X38,AA38,AD38,AG38,AJ38,AM38,AP38,AS38,AV38,AY38,BB38,BE38,BH38,BK38,BN38,BQ38,BT38,BW38,BZ38,CC38,CF38,CI38,CL38,CO38,CR38,CU38,CX38) -> 1 | J38: Julho | CT38: 245.01 | CU38: 39.646 | CV38: VALE DO MOXOTÓ
A39: JOSE CARLOS | B39: SYU1D42 | C39: ONIX | D39: - | E39: 3680 | F39: 5102 | G39: =F39-E39 -> 1422 | H39: =SUM(K39+N39+Q39+T39+W39+Z39+AC39+AF39+AI39+AL39+AO39+AR39+AU39+AX39+BA39+BD39+BG39+BJ39+BM39+BP39+BS39+BV39+BY39+CB39+CE39+CH39+CK39+CN39+CQ39+CT39+CW39) -> 657.06 | I39: =COUNTA(L39,O39,R39,U39,X39,AA39,AD39,AG39,AJ39,AM39,AP39,AS39,AV39,AY39,BB39,BE39,BH39,BK39,BN39,BQ39,BT39,BW39,BZ39,CC39,CF39,CI39,CL39,CO39,CR39,CU39,CX39) -> 3 | J39: Julho | T39: 200.01 | U39: 33.958 | V39: VALE DO MOXOTÓ | AO39: 220.04 | AP39: 35.606 | AQ39: VALE DO MOXOTÓ | BY39: 237.01 | BZ39: 38.352 | CA39: VALE DO MOXOTÓ
A40: ALAIN | B40: SHQ6E86 | C40: ONIX | D40: - | E40: 16727 | F40: 18939 | G40: =F40-E40 -> 2212 | H40: =SUM(K40+N40+Q40+T40+W40+Z40+AC40+AF40+AI40+AL40+AO40+AR40+AU40+AX40+BA40+BD40+BG40+BJ40+BM40+BP40+BS40+BV40+BY40+CB40+CE40+CH40+CK40+CN40+CQ40+CT40+CW40) -> 1113.75 | I40: =COUNTA(L40,O40,R40,U40,X40,AA40,AD40,AG40,AJ40,AM40,AP40,AS40,AV40,AY40,BB40,BE40,BH40,BK40,BN40,BQ40,BT40,BW40,BZ40,CC40,CF40,CI40,CL40,CO40,CR40,CU40,CX40) -> 5 | J40: Julho | T40: 240.11 | U40: 40.766 | V40: VALE DO MOXOTÓ | AO40: 268.96 | AP40: 43.522 | AQ40: VALE DO MOXOTÓ | BJ40: 218.11 | BK40: 35.293 | BL40: VALE DO MOXOTÓ | BY40: 284.77 | BZ40: 43.016 | CA40: VALE DO MOXOTÓ | CH40: 101.8 | CI40: 16.474 | CJ40: VALE DO MOXOTÓ
A41: CLAUDIO | B41: SIN6B14 | C41: ONIX | D41: - | E41: 22932 | F41: 25760 | G41: =F41-E41 -> 2828 | H41: =SUM(K41+N41+Q41+T41+W41+Z41+AC41+AF41+AI41+AL41+AO41+AR41+AU41+AX41+BA41+BD41+BG41+BJ41+BM41+BP41+BS41+BV41+BY41+CB41+CE41+CH41+CK41+CN41+CQ41+CT41+CW41) -> 911.06 | I41: =COUNTA(L41,O41,R41,U41,X41,AA41,AD41,AG41,AJ41,AM41,AP41,AS41,AV41,AY41,BB41,BE41,BH41,BK41,BN41,BQ41,BT41,BW41,BZ41,CC41,CF41,CI41,CL41,CO41,CR41,CU41,CX41) -> 6 | J41: Agosto | K41: 69.92 | L41: 11.31 | M41: VALE DO MOXOTÓ | Z41: 202.49 | AA41: 32.766 | AB41: VALE DO MOXOTÓ | AF41: 73.02 | AG41: 11.818 | AH41: VALE DO MOXOTÓ | BP41: 210 | BQ41: 33.987 | BR41: VALE DO MOXOTÓ | CK41: 210.6 | CL41: 34.07 | CM41: VALE DO MOXOTÓ | CQ41: 145.03 | CR41: 23.468 | CS41: VALE DO MOXOTÓ
A42: ANDRE / UALACE | B42: EZ01E92 | C42: TCROSS | D42: - | E42: 40418 | F42: 43102 | G42: =F42-E42 -> 2684 | H42: =SUM(K42+N42+Q42+T42+W42+Z42+AC42+AF42+AI42+AL42+AO42+AR42+AU42+AX42+BA42+BD42+BG42+BJ42+BM42+BP42+BS42+BV42+BY42+CB42+CE42+CH42+CK42+CN42+CQ42+CT42+CW42) -> 1038.27 | I42: =COUNTA(L42,O42,R42,U42,X42,AA42,AD42,AG42,AJ42,AM42,AP42,AS42,AV42,AY42,BB42,BE42,BH42,BK42,BN42,BQ42,BT42,BW42,BZ42,CC42,CF42,CI42,CL42,CO42,CR42,CU42,CX42) -> 6 | J42: Agosto | K42: 98.36 | L42: 15.91 | M42: VALE DO MOXOTÓ | Z42: 225.61 | AA42: 26.5 | AB42: VALE DO MOXOTÓ | BA42: 166.27 | BB42: 26.87 | BC42: VALE DO MOXOTÓ | BV42: 150 | BW42: 24.288 | BX42: VALE DO MOXOTÓ | CK42: 217.99 | CL42: 35.277 | CM42: VALE DO MOXOTÓ | CQ42: 180.04 | CR42: 29.134 | CS42: VALE DO MOXOTÓ
A43: JOSE CARLOS | B43: SYU1D42 | C43: ONIX | D43: - | E43: 5102 | F43: 6444 | G43: =F43-E43 -> 1342 | H43: =SUM(K43+N43+Q43+T43+W43+Z43+AC43+AF43+AI43+AL43+AO43+AR43+AU43+AX43+BA43+BD43+BG43+BJ43+BM43+BP43+BS43+BV43+BY43+CB43+CE43+CH43+CK43+CN43+CQ43+CT43+CW43) -> 782.99 | I43: =COUNTA(L43,O43,R43,U43,X43,AA43,AD43,AG43,AJ43,AM43,AP43,AS43,AV43,AY43,BB43,BE43,BH43,BK43,BN43,BQ43,BT43,BW43,BZ43,CC43,CF43,CI43,CL43,CO43,CR43,CU43,CX43) -> 4 | J43: Agosto | K43: 196.02 | L43: 31.71 | M43: VALE DO MOXOTÓ | AF43: 246.02 | AG43: 39.81 | AH43: VALE DO MOXOTÓ | BA43: 153.9 | BB43: 24.9 | BC43: VALE DO MOXOTÓ | CK43: 187.05 | CL43: 30.26 | CM43: VALE DO MOXOTÓ
A44: ALAIN | B44: SHQ6E86 | C44: ONIX | D44: - | E44: 18939 | F44: 21801 | G44: =F44-E44 -> 2862 | H44: =SUM(K44+N44+Q44+T44+W44+Z44+AC44+AF44+AI44+AL44+AO44+AR44+AU44+AX44+BA44+BD44+BG44+BJ44+BM44+BP44+BS44+BV44+BY44+CB44+CE44+CH44+CK44+CN44+CQ44+CT44+CW44) -> 1142.99 | I44: =COUNTA(L44,O44,R44,U44,X44,AA44,AD44,AG44,AJ44,AM44,AP44,AS44,AV44,AY44,BB44,BE44,BH44,BK44,BN44,BQ44,BT44,BW44,BZ44,CC44,CF44,CI44,CL44,CO44,CR44,CU44,CX44) -> 6 | J44: Agosto | K44: 220 | L44: 35.59 | M44: VALE DO MOXOTÓ | Z44: 247.03 | AA44: 39.97 | AB44: VALE DO MOXOTÓ | AF44: 70.01 | AG44: 11.329 | AH44: VALE DO MOXOTÓ | AU44: 92.7 | AV44: 15 | AW44: VALE DO MOXOTÓ | BA44: 245.03 | BB44: 39.65 | BC44: VALE DO MOXOTÓ | CK44: 268.22 | CL44: 43.4 | CM44: VALE DO MOXOTÓ
A45: CLAUDIO | B45: SIN6B14 | C45: ONIX | D45: - | E45: 25760 | F45: 27811 | G45: =F45-E45 -> 2051 | H45: =SUM(K45+N45+Q45+T45+W45+Z45+AC45+AF45+AI45+AL45+AO45+AR45+AU45+AX45+BA45+BD45+BG45+BJ45+BM45+BP45+BS45+BV45+BY45+CB45+CE45+CH45+CK45+CN45+CQ45+CT45+CW45) -> 1240.49 | I45: =COUNTA(L45,O45,R45,U45,X45,AA45,AD45,AG45,AJ45,AM45,AP45,AS45,AV45,AY45,BB45,BE45,BH45,BK45,BN45,BQ45,BT45,BW45,BZ45,CC45,CF45,CI45,CL45,CO45,CR45,CU45,CX45) -> 8 | J45: Setembro | Q45: 218.11 | R45: 35.29 | S45: VALE DO MOXOTÓ | W45: 114.04 | X45: 18.46 | Y45: VALE DO MOXOTÓ | AL45: 160.06 | AM45: 25.9 | AN45: VALE DO MOXOTÓ | AR45: 118 | AS45: 19.01 | AT45: VALE DO MOXOTÓ | BG45: 165.06 | BH45: 26.7 | BI45: VALE DO MOXOTÓ | BM45: 143.06 | BN45: 23.15 | BO45: VALE DO MOXOTÓ | CB45: 217.07 | CC45: 35.12 | CD45: VALE DO MOXOTÓ | CH45: 105.09 | CI45: 17 | CJ45: VALE DO MOXOTÓ
A46: ANDRE / UALACE | B46: SIX1B97 | C46: CRETA | D46: - | E46: 20050 | F46: 21493 | G46: =F46-E46 -> 1443 | H46: =SUM(K46+N46+Q46+T46+W46+Z46+AC46+AF46+AI46+AL46+AO46+AR46+AU46+AX46+BA46+BD46+BG46+BJ46+BM46+BP46+BS46+BV46+BY46+CB46+CE46+CH46+CK46+CN46+CQ46+CT46+CW46) -> 904.85 | I46: =COUNTA(L46,O46,R46,U46,X46,AA46,AD46,AG46,AJ46,AM46,AP46,AS46,AV46,AY46,BB46,BE46,BH46,BK46,BN46,BQ46,BT46,BW46,BZ46,CC46,CF46,CI46,CL46,CO46,CR46,CU46,CX46) -> 5 | J46: Setembro | AL46: 256.05 | AM46: 41.43 | AN46: VALE DO MOXOTÓ | BG46: 222.02 | BH46: 35.927 | BI46: VALE DO MOXOTÓ | BM46: 57.07 | BN46: 9.236 | BO46: VALE DO MOXOTÓ | CB46: 229.71 | CC46: 37.17 | CD46: VALE DO MOXOTÓ | CH46: 140 | CI46: 22.655 | CJ46: VALE DO MOXOTÓ
A47: JOSE CARLOS | B47: SYU1D42 | C47: ONIX | D47: - | E47: 6444 | F47: 6902 | G47: =F47-E47 -> 458 | H47: =SUM(K47+N47+Q47+T47+W47+Z47+AC47+AF47+AI47+AL47+AO47+AR47+AU47+AX47+BA47+BD47+BG47+BJ47+BM47+BP47+BS47+BV47+BY47+CB47+CE47+CH47+CK47+CN47+CQ47+CT47+CW47) -> 355.4 | I47: =COUNTA(L47,O47,R47,U47,X47,AA47,AD47,AG47,AJ47,AM47,AP47,AS47,AV47,AY47,BB47,BE47,BH47,BK47,BN47,BQ47,BT47,BW47,BZ47,CC47,CF47,CI47,CL47,CO47,CR47,CU47,CX47) -> 2 | J47: Setembro | W47: 150.39 | X47: 24.33 | Y47: VALE DO MOXOTÓ | CH47: 205.01 | CI47: 33.17 | CJ47: VALE DO MOXOTÓ
A48: ALAIN | B48: SHQ6E86 | C48: ONIX | D48: - | E48: 21801 | F48: 24027 | G48: =F48-E48 -> 2226 | H48: =SUM(K48+N48+Q48+T48+W48+Z48+AC48+AF48+AI48+AL48+AO48+AR48+AU48+AX48+BA48+BD48+BG48+BJ48+BM48+BP48+BS48+BV48+BY48+CB48+CE48+CH48+CK48+CN48+CQ48+CT48+CW48) -> 1097.23 | I48: =COUNTA(L48,O48,R48,U48,X48,AA48,AD48,AG48,AJ48,AM48,AP48,AS48,AV48,AY48,BB48,BE48,BH48,BK48,BN48,BQ48,BT48,BW48,BZ48,CC48,CF48,CI48,CL48,CO48,CR48,CU48,CX48) -> 6 | J48: Setembro | Q48: 287.29 | R48: 43.29 | S48: VALE DO MOXOTÓ | W48: 160.01 | X48: 25.69 | Y48: VALE DO MOXOTÓ | AL48: 227.07 | AM48: 36.74 | AN48: VALE DO MOXOTÓ | AR48: 103.79 | AS48: 16.78 | AT48: VALE DO MOXOTÓ | BG48: 254.02 | BH48: 41.1 | BI48: VALE DO MOXOTÓ | BM48: 65.05 | BN48: 10.04 | BO48: VALE DO MOXOTÓ
A49: CLAUDIO | B49: SIN6B14 | C49: ONIX | D49: - | E49: 27783 | F49: 30838 | G49: =F49-E49 -> 3055 | H49: =SUM(K49+N49+Q49+T49+W49+Z49+AC49+AF49+AI49+AL49+AO49+AR49+AU49+AX49+BA49+BD49+BG49+BJ49+BM49+BP49+BS49+BV49+BY49+CB49+CE49+CH49+CK49+CN49+CQ49+CT49+CW49) -> 748.69 | I49: =COUNTA(L49,O49,R49,U49,X49,AA49,AD49,AG49,AJ49,AM49,AP49,AS49,AV49,AY49,BB49,BE49,BH49,BK49,BN49,BQ49,BT49,BW49,BZ49,CC49,CF49,CI49,CL49,CO49,CR49,CU49,CX49) -> 4 | J49: Outubro | K49: 217.91 | L49: 35.26 | M49: VALE DO MOXOTÓ | AL49: 200.03 | AM49: 32.36 | AN49: VALE DO MOXOTÓ | BA49: 172.65 | BB49: 27.93 | BC49: VALE DO MOXOTÓ | CB49: 158.1 | CC49: 25.58 | CD49: VALE DO MOXOTÓ
A50: ANDRE / UALACE | B50: SIX1B97 | C50: CRETA | D50: - | G50: =F50-E50 -> 0 | H50: =SUM(K50+N50+Q50+T50+W50+Z50+AC50+AF50+AI50+AL50+AO50+AR50+AU50+AX50+BA50+BD50+BG50+BJ50+BM50+BP50+BS50+BV50+BY50+CB50+CE50+CH50+CK50+CN50+CQ50+CT50+CW50) -> 386.6 | I50: =COUNTA(L50,O50,R50,U50,X50,AA50,AD50,AG50,AJ50,AM50,AP50,AS50,AV50,AY50,BB50,BE50,BH50,BK50,BN50,BQ50,BT50,BW50,BZ50,CC50,CF50,CI50,CL50,CO50,CR50,CU50,CX50) -> 3 | J50: Outubro | K50: 175.16 | L50: 28.34 | M50: VALE DO MOXOTÓ | Q50: 100.03 | R50: 16.19 | S50: VALE DO MOXOTÓ | AF50: 111.41 | AG50: 18.02 | AH50: VALE DO MOXOTÓ
A51: JOSE CARLOS | B51: SYU1D42 | C51: ONIX | D51: - | E51: 6902 | F51: 7314 | G51: =F51-E51 -> 412 | H51: =SUM(K51+N51+Q51+T51+W51+Z51+AC51+AF51+AI51+AL51+AO51+AR51+AU51+AX51+BA51+BD51+BG51+BJ51+BM51+BP51+BS51+BV51+BY51+CB51+CE51+CH51+CK51+CN51+CQ51+CT51+CW51) -> 104.9 | I51: =COUNTA(L51,O51,R51,U51,X51,AA51,AD51,AG51,AJ51,AM51,AP51,AS51,AV51,AY51,BB51,BE51,BH51,BK51,BN51,BQ51,BT51,BW51,BZ51,CC51,CF51,CI51,CL51,CO51,CR51,CU51,CX51) -> 1 | J51: Outubro | Q51: 104.9 | R51: 16.97 | S51: VALE DO MOXOTÓ
A52: ALAIN | B52: SHQ6E86 | C52: ONIX | D52: - | G52: =F52-E52 -> 0 | H52: =SUM(K52+N52+Q52+T52+W52+Z52+AC52+AF52+AI52+AL52+AO52+AR52+AU52+AX52+BA52+BD52+BG52+BJ52+BM52+BP52+BS52+BV52+BY52+CB52+CE52+CH52+CK52+CN52+CQ52+CT52+CW52) -> 859.05 | I52: =COUNTA(L52,O52,R52,U52,X52,AA52,AD52,AG52,AJ52,AM52,AP52,AS52,AV52,AY52,BB52,BE52,BH52,BK52,BN52,BQ52,BT52,BW52,BZ52,CC52,CF52,CI52,CL52,CO52,CR52,CU52,CX52) -> 4 | J52: Outubro | K52: 267.17 | L52: 43.23 | M52: VALE DO MOXOTÓ | Q52: 80.04 | R52: 12.95 | S52: VALE DO MOXOTÓ | AL52: 250.76 | AM52: 40.57 | AN52: VALE DO MOXOTÓ | CB52: 261.08 | CC52: 42.24 | CD52: VALE DO MOXOTÓ
A53: ANDRE | B53: SIH9B68 | C53: CRONOS | D53: - | E53: 30004 | F53: 31231 | G53: =F53-E53 -> 1227 | H53: =SUM(K53+N53+Q53+T53+W53+Z53+AC53+AF53+AI53+AL53+AO53+AR53+AU53+AX53+BA53+BD53+BG53+BJ53+BM53+BP53+BS53+BV53+BY53+CB53+CE53+CH53+CK53+CN53+CQ53+CT53+CW53) -> 204.04 | I53: =COUNTA(L53,O53,R53,U53,X53,AA53,AD53,AG53,AJ53,AM53,AP53,AS53,AV53,AY53,BB53,BE53,BH53,BK53,BN53,BQ53,BT53,BW53,BZ53,CC53,CF53,CI53,CL53,CO53,CR53,CU53,CX53) -> 1 | J53: Outubro | CB53: 204.04 | CC53: 33.01 | CD53: VALE DO MOXOTÓ
A54: CLAUDIO | B54: SIN6B14 | C54: ONIX | D54: ATIVO | G54: =F54-E54 -> 0 | H54: =SUM(K54+N54+Q54+T54+W54+Z54+AC54+AF54+AI54+AL54+AO54+AR54+AU54+AX54+BA54+BD54+BG54+BJ54+BM54+BP54+BS54+BV54+BY54+CB54+CE54+CH54+CK54+CN54+CQ54+CT54+CW54) -> 226.45 | I54: =COUNTA(L54,O54,R54,U54,X54,AA54,AD54,AG54,AJ54,AM54,AP54,AS54,AV54,AY54,BB54,BE54,BH54,BK54,BN54,BQ54,BT54,BW54,BZ54,CC54,CF54,CI54,CL54,CO54,CR54,CU54,CX54) -> 1 | J54: Novembro | AC54: 226.45 | AD54: 37.8 | AE54: VALE DO MOXOTÓ
A55: ALAIN | B55: SHQ6E86 | C55: ONIX | D55: ATIVO | G55: =F55-E55 -> 0 | H55: =SUM(K55+N55+Q55+T55+W55+Z55+AC55+AF55+AI55+AL55+AO55+AR55+AU55+AX55+BA55+BD55+BG55+BJ55+BM55+BP55+BS55+BV55+BY55+CB55+CE55+CH55+CK55+CN55+CQ55+CT55+CW55) -> 253.38 | I55: =COUNTA(L55,O55,R55,U55,X55,AA55,AD55,AG55,AJ55,AM55,AP55,AS55,AV55,AY55,BB55,BE55,BH55,BK55,BN55,BQ55,BT55,BW55,BZ55,CC55,CF55,CI55,CL55,CO55,CR55,CU55,CX55) -> 1 | J55: Novembro | AC55: 253.38 | AD55: 42.3 | AE55: VALE DO MOXOTÓ
A56: ANDRE | B56: SIH9B68 | C56: CRONOS | D56: ATIVO | E56: 31231 | F56: 33942 | G56: =F56-E56 -> 2711 | H56: =SUM(K56+N56+Q56+T56+W56+Z56+AC56+AF56+AI56+AL56+AO56+AR56+AU56+AX56+BA56+BD56+BG56+BJ56+BM56+BP56+BS56+BV56+BY56+CB56+CE56+CH56+CK56+CN56+CQ56+CT56+CW56) -> 535.76 | I56: =COUNTA(L56,O56,R56,U56,X56,AA56,AD56,AG56,AJ56,AM56,AP56,AS56,AV56,AY56,BB56,BE56,BH56,BK56,BN56,BQ56,BT56,BW56,BZ56,CC56,CF56,CI56,CL56,CO56,CR56,CU56,CX56) -> 3 | J56: Novembro | AC56: =90.02+138.99 -> 229.01 | AD56: =15.03+23.2 -> 38.23 | AE56: VALE DO MOXOTÓ | AX56: 166.03 | AY56: 27.71 | AZ56: VALE DO MOXOTÓ | CN56: 140.72 | CO56: 23.49 | CP56: VALE DO MOXOTÓ
A57: ANDRE | B57: SIH9B68 | C57: CRONOS | D57: ATIVO | H57: =SUM(K57+N57+Q57+T57+W57+Z57+AC57+AF57+AI57+AL57+AO57+AR57+AU57+AX57+BA57+BD57+BG57+BJ57+BM57+BP57+BS57+BV57+BY57+CB57+CE57+CH57+CK57+CN57+CQ57+CT57+CW57) -> 516.8 | I57: =COUNTA(L57,O57,R57,U57,X57,AA57,AD57,AG57,AJ57,AM57,AP57,AS57,AV57,AY57,BB57,BE57,BH57,BK57,BN57,BQ57,BT57,BW57,BZ57,CC57,CF57,CI57,CL57,CO57,CR57,CU57,CX57) -> 3 | J57: Dezembro | Q57: 65.06 | R57: 10.86 | S57: VALE DO MOXOTÓ | AR57: 225.65 | AS57: 36.99 | AT57: VALE DO MOXOTÓ | BG57: 226.09 | BH57: 37.06 | BI57: VALE DO MOXOTÓ

Sheet 23026_LAGOA_CGN
A1: QTD DE VEICULOS ATIVO | B1: =COUNTIF(D3:D29,"ATIVO") -> 0 | C1: CONTROLE DE KM - 2023_23026_ENG PROPRIETARIO RETROFIT LAGOA DO BARRO_CGN | K1: ABASTECIMENTO | N1: ABASTECIMENTO | Q1: ABASTECIMENTO | T1: ABASTECIMENTO | W1: ABASTECIMENTO | Z1: ABASTECIMENTO | AC1: ABASTECIMENTO | AF1: ABASTECIMENTO | AI1: ABASTECIMENTO | AL1: ABASTECIMENTO | AO1: ABASTECIMENTO | AR1: ABASTECIMENTO | AU1: ABASTECIMENTO | AX1: ABASTECIMENTO | BA1: ABASTECIMENTO | BD1: ABASTECIMENTO | BG1: ABASTECIMENTO | BJ1: ABASTECIMENTO | BM1: ABASTECIMENTO | BP1: ABASTECIMENTO | BS1: ABASTECIMENTO | BV1: ABASTECIMENTO | BY1: ABASTECIMENTO | CB1: ABASTECIMENTO | CE1: ABASTECIMENTO | CH1: ABASTECIMENTO | CK1: ABASTECIMENTO | CN1: ABASTECIMENTO | CQ1: ABASTECIMENTO | CT1: ABASTECIMENTO | CW1: ABASTECIMENTO | CZ1: OBS | DA1: FOLGA
A2: CONDUTOR | B2: PLACA | C2: VEICULO | D2: STATUS | E2: KM INICIAL | F2: KM FINAL | G2: KM PERCORRIDA | H2: CONSUMO TOTAL | I2: ABASTECIMENTO MÊS | J2: MÊS | K2: 1º DIA VALOR | L2: QTD LITROS | M2: POSTO | N2: 2º DIA VALOR | O2: QTD LITROS | P2: POSTO | Q2: 3º DIA VALOR | R2: QTD LITROS | S2: POSTO | T2: 4º DIA VALOR | U2: QTD LITROS | V2: POSTO | W2: 5º DIA VALOR | X2: QTD LITROS | Y2: POSTO | Z2: 6º DIA VALOR | AA2: QTD LITROS | AB2: POSTO | AC2: 7º DIA VALOR | AD2: QTD LITROS | AE2: POSTO | AF2: 8º DIA VALOR | AG2: QTD LITROS | AH2: POSTO | AI2: 9º DIA VALOR | AJ2: QTD LITROS | AK2: POSTO | AL2: 10º DIA VALOR | AM2: QTD LITROS | AN2: POSTO | AO2: 11º DIA VALOR | AP2: QTD LITROS | AQ2: POSTO | AR2: 12º DIA VALOR | AS2: QTD LITROS | AT2: POSTO | AU2: 13º DIA VALOR | AV2: QTD LITROS | AW2: POSTO | AX2: 14º DIA VALOR | AY2: QTD LITROS | AZ2: POSTO | BA2: 15º DIA VALOR | BB2: QTD LITROS | BC2: POSTO | BD2: 16º DIA VALOR | BE2: QTD LITROS | BF2: POSTO | BG2: 17º DIA VALOR | BH2: QTD LITROS | BI2: POSTO | BJ2: 18º DIA VALOR | BK2: QTD LITROS | BL2: POSTO | BM2: 19º DIA VALOR | BN2: QTD LITROS | BO2: POSTO | BP2: 20º DIA VALOR | BQ2: QTD LITROS | BR2: POSTO | BS2: 21º DIA VALOR | BT2: QTD LITROS | BU2: POSTO | BV2: 22º DIA VALOR | BW2: QTD LITROS | BX2: POSTO | BY2: 23º DIA VALOR | BZ2: QTD LITROS | CA2: POSTO | CB2: 24º DIA VALOR | CC2: QTD LITROS | CD2: POSTO | CE2: 25º DIA VALOR | CF2: QTD LITROS | CG2: POSTO | CH2: 26º DIA VALOR | CI2: QTD LITROS | CJ2: POSTO | CK2: 27º DIA VALOR | CL2: QTD LITROS | CM2: POSTO | CN2: 28º DIA VALOR | CO2: QTD LITROS | CP2: POSTO | CQ2: 29º DIA VALOR | CR2: QTD LITROS | CS2: POSTO | CT2: 30º DIA VALOR | CU2: QTD LITROS | CV2: POSTO | CW2: 31º DIA VALOR | CX2: QTD LITROS | CY2: POSTO
A3: JERFFERSON MOREIRA | B3: SHV3E43 | C3: TRACKER | D3: - | E3: 26273 | F3: 30601 | G3: =F3-E3 -> 4328 | H3: =SUM(K3+N3+Q3+T3+W3+Z3+AC3+AF3+AI3+AL3+AO3+AR3+AU3+AX3+BA3+BD3+BG3+BJ3+BM3+BP3+BS3+BV3+BY3+CB3+CE3+CH3+CK3+CN3+CQ3+CT3+CW3) -> 1964.64 | I3: =COUNTA(L3,O3,R3,U3,X3,AA3,AD3,AG3,AJ3,AM3,AP3,AS3,AV3,AY3,BB3,BE3,BH3,BK3,BN3,BQ3,BT3,BW3,BZ3,CC3,CF3,CI3,CL3,CO3,CR3,CU3,CX3) -> 10 | J3: Janeiro | Q3: 222.32 | R3: 38 | S3: POSTO VIP | W3: 338.15 | X3: 57.89 | Y3: POSTO VIP | AI3: 230.84 | AJ3: 39.46 | AK3: POSTO VIP | AO3: 136.24 | AP3: 23.29 | AQ3: POSTO VIP | BD3: 198.9 | BE3: 34 | BF3: POSTO VIP | BM3: 153.34 | BN3: 26.53 | BO3: POSTO VIP | BP3: 236.92 | BQ3: 41 | BR3: POSTO VIP | BY3: 129.7 | BZ3: 22.44 | CA3: POSTO VIP | CH3: 147.67 | CI3: 25.55 | CJ3: POSTO VIP | CT3: 170.56 | CU3: 29.51 | CV3: POSTO VIP
A4: CARLOS EDUARDO | B4: SHG4A99 | C4: S10 | D4: - | E4: 16272 | F4: 17521 | G4: =F4-E4 -> 1249 | H4: =SUM(K4+N4+Q4+T4+W4+Z4+AC4+AF4+AI4+AL4+AO4+AR4+AU4+AX4+BA4+BD4+BG4+BJ4+BM4+BP4+BS4+BV4+BY4+CB4+CE4+CH4+CK4+CN4+CQ4+CT4+CW4) -> 205.57 | J4: Janeiro | CB4: 205.57 | CC4: 33.7 | CD4: POSTO VIP
A5: CARLOS EDUARDO | B5: RVS1B22 | C5: S10 | D5: - | E5: 22763 | F5: 26992 | G5: =F5-E5 -> 4229 | H5: =SUM(K5+N5+Q5+T5+W5+Z5+AC5+AF5+AI5+AL5+AO5+AR5+AU5+AX5+BA5+BD5+BG5+BJ5+BM5+BP5+BS5+BV5+BY5+CB5+CE5+CH5+CK5+CN5+CQ5+CT5+CW5) -> 989.78 | I5: =COUNTA(L5,O5,R5,U5,X5,AA5,AD5,AG5,AJ5,AM5,AP5,AS5,AV5,AY5,BB5,BE5,BH5,BK5,BN5,BQ5,BT5,BW5,BZ5,CC5,CF5,CI5,CL5,CO5,CR5,CU5,CX5) -> 3 | J5: Janeiro | T5: 338.62 | U5: 54.18 | V5: POSTO VIP | AL5: 321.95 | AM5: 52.35 | AN5: POSTO VIP | BG5: 329.21 | BH5: 53.97 | BI5: POSTO VIP
A6: JERFFERSON MOREIRA | B6: SHV3E43 | C6: TRACKER | D6: - | E6: 30601 | F6: 35214 | G6: =F6-E6 -> 4613 | H6: =SUM(K6+N6+Q6+T6+W6+Z6+AC6+AF6+AI6+AL6+AO6+AR6+AU6+AX6+BA6+BD6+BG6+BJ6+BM6+BP6+BS6+BV6+BY6+CB6+CE6+CH6+CK6+CN6+CQ6+CT6+CW6) -> 1777.53 | I6: =COUNTA(L6,O6,R6,U6,X6,AA6,AD6,AG6,AJ6,AM6,AP6,AS6,AV6,AY6,BB6,BE6,BH6,BK6,BN6,BQ6,BT6,BW6,BZ6,CC6,CF6,CI6,CL6,CO6,CR6,CU6,CX6) -> 10 | J6: Fevereiro | K6: 144.09 | L6: 24.93 | M6: POSTO VIP | N6: 152.76 | O6: 26.43 | P6: POSTO VIP | Q6: 80.05 | R6: 13.85 | S6: POSTO VIP | Z6: 202.74 | AA6: 35.08 | AB6: POSTO VIP | AF6: 178.17 | AG6: 30.51 | AH6: POSTO VIP | AL6: 172.28 | AM6: 29.5 | AN6: POSTO VIP | AU6: 166.32 | AV6: 28.47 | AW6: POSTO VIP | BD6: 150.02 | BE6: 25.69 | BF6: POSTO VIP | CB6: 329.45 | CC6: 55 | CD6: POSTO VIP | CK6: 201.65 | CL6: 34.53 | CM6: POSTO VIP
A7: CARLOS EDUARDO | B7: SHG4A99 | C7: S10 | D7: - | E7: 17521 | F7: 19641 | G7: =F7-E7 -> 2120 | H7: =SUM(K7+N7+Q7+T7+W7+Z7+AC7+AF7+AI7+AL7+AO7+AR7+AU7+AX7+BA7+BD7+BG7+BJ7+BM7+BP7+BS7+BV7+BY7+CB7+CE7+CH7+CK7+CN7+CQ7+CT7+CW7) -> 1259.83 | I7: =COUNTA(L7,O7,R7,U7,X7,AA7,AD7,AG7,AJ7,AM7,AP7,AS7,AV7,AY7,BB7,BE7,BH7,BK7,BN7,BQ7,BT7,BW7,BZ7,CC7,CF7,CI7,CL7,CO7,CR7,CU7,CX7) -> 4 | J7: Fevereiro | K7: 376.73 | L7: 61.76 | M7: POSTO VIP | AC7: 347.7 | AD7: 57 | AE7: POSTO VIP | BA7: 269.37 | BB7: 44.16 | BC7: POSTO VIP | BD7: 266.03 | BE7: 44.61 | BF7: POSTO VIP
A8: JERFFERSON MOREIRA | B8: SHV3E43 | C8: TRACKER | D8: - | E8: 35214 | F8: 39806 | G8: =F8-E8 -> 4592 | H8: =SUM(K8+N8+Q8+T8+W8+Z8+AC8+AF8+AI8+AL8+AO8+AR8+AU8+AX8+BA8+BD8+BG8+BJ8+BM8+BP8+BS8+BV8+BY8+CB8+CE8+CH8+CK8+CN8+CQ8+CT8+CW8) -> 1290.95 | I8: =COUNTA(L8,O8,R8,U8,X8,AA8,AD8,AG8,AJ8,AM8,AP8,AS8,AV8,AY8,BB8,BE8,BH8,BK8,BN8,BQ8,BT8,BW8,BZ8,CC8,CF8,CI8,CL8,CO8,CR8,CU8,CX8) -> 8 | J8: Março | K8: 175.66 | L8: 30.79 | M8: POSTO VIP | W8: 149.73 | X8: 25.64 | Y8: POSTO VIP | AC8: 141.21 | AD8: 24.18 | AE8: POSTO VIP | AI8: 134.9 | AJ8: 23.1 | AK8: POSTO VIP | AR8: 216.13 | AS8: 34.009 | AT8: POSTO VIP | AU8: 96.18 | AV8: 16.47 | AW8: POSTO VIP | CH8: 218.94 | CI8: 37.49 | CJ8: POSTO VIP | CK8: 158.2 | CL8: 27.09 | CM8: POSTO VIP
A9: CARLOS EDUARDO | B9: SHG4A99 | C9: S10 | D9: - | E9: 19641 | F9: 22407 | G9: =F9-E9 -> 2766 | H9: =SUM(K9+N9+Q9+T9+W9+Z9+AC9+AF9+AI9+AL9+AO9+AR9+AU9+AX9+BA9+BD9+BG9+BJ9+BM9+BP9+BS9+BV9+BY9+CB9+CE9+CH9+CK9+CN9+CQ9+CT9+CW9) -> 1579.5 | I9: =COUNTA(L9,O9,R9,U9,X9,AA9,AD9,AG9,AJ9,AM9,AP9,AS9,AV9,AY9,BB9,BE9,BH9,BK9,BN9,BQ9,BT9,BW9,BZ9,CC9,CF9,CI9,CL9,CO9,CR9,CU9,CX9) -> 6 | J9: Março | K9: 301.89 | L9: 50.39 | M9: POSTO VIP | AI9: 244.21 | AJ9: 40.599 | AK9: POSTO VIP | BA9: 351 | BB9: 60 | BC9: POSTO VIP | BV9: 308.35 | BW9: 52.8 | BX9: POSTO VIP | CK9: 182.85 | CL9: 31.8 | CM9: POSTO VIP | CT9: 191.2 | CU9: 32.74 | CV9: POSTO VIP
A10: JERFFERSON MOREIRA | B10: SHV3E43 | C10: TRACKER | D10: - | E10: 39806 | F10: 43133 | G10: =F10-E10 -> 3327 | H10: =SUM(K10+N10+Q10+T10+W10+Z10+AC10+AF10+AI10+AL10+AO10+AR10+AU10+AX10+BA10+BD10+BG10+BJ10+BM10+BP10+BS10+BV10+BY10+CB10+CE10+CH10+CK10+CN10+CQ10+CT10+CW10) -> 1798.46 | I10: =COUNTA(L10,O10,R10,U10,X10,AA10,AD10,AG10,AJ10,AM10,AP10,AS10,AV10,AY10,BB10,BE10,BH10,BK10,BN10,BQ10,BT10,BW10,BZ10,CC10,CF10,CI10,CL10,CO10,CR10,CU10,CX10) -> 10 | J10: Abril | T10: 134.37 | U10: 23.01 | V10: POSTO VIP | Z10: 162.99 | AA10: 27.91 | AB10: POSTO VIP | AI10: 179.4 | AJ10: 30.72 | AK10: POSTO VIP | AL10: 150.08 | AM10: 25.699 | AN10: POSTO VIP | AX10: 162.12 | AY10: 27.769 | AZ10: POSTO VIP | BG10: 240.63 | BH10: 40.24 | BI10: POSTO VIP | BP10: 201.7 | BQ10: 33.73 | BR10: POSTO VIP | CE10: 224.83 | CF10: 45.96 | CG10: POSTO VIP | CK10: 200.56 | CL10: 33.54 | CM10: POSTO VIP | CT10: 141.78 | CU10: 23.71 | CV10: POSTO VIP
A11: CARLOS EDUARDO | B11: SHG4A99 | C11: S10 | D11: - | F11: 46281 | G11: =F11-E11 -> 46281 | H11: =SUM(K11+N11+Q11+T11+W11+Z11+AC11+AF11+AI11+AL11+AO11+AR11+AU11+AX11+BA11+BD11+BG11+BJ11+BM11+BP11+BS11+BV11+BY11+CB11+CE11+CH11+CK11+CN11+CQ11+CT11+CW11) -> 0 | I11: =COUNTA(L11,O11,R11,U11,X11,AA11,AD11,AG11,AJ11,AM11,AP11,AS11,AV11,AY11,BB11,BE11,BH11,BK11,BN11,BQ11,BT11,BW11,BZ11,CC11,CF11,CI11,CL11,CO11,CR11,CU11,CX11) -> 0 | J11: Abril
A12: JERFFERSON MOREIRA | B12: SHV3E43 | C12: TRACKER | D12: - | E12: 43133 | F12: 46281 | G12: =F12-E12 -> 3148 | H12: =SUM(K12+N12+Q12+T12+W12+Z12+AC12+AF12+AI12+AL12+AO12+AR12+AU12+AX12+BA12+BD12+BG12+BJ12+BM12+BP12+BS12+BV12+BY12+CB12+CE12+CH12+CK12+CN12+CQ12+CT12+CW12) -> 1562.64 | I12: =COUNTA(L12,O12,R12,U12,X12,AA12,AD12,AG12,AJ12,AM12,AP12,AS12,AV12,AY12,BB12,BE12,BH12,BK12,BN12,BQ12,BT12,BW12,BZ12,CC12,CF12,CI12,CL12,CO12,CR12,CU12,CX12) -> 10 | J12: Maio | N12: 158.41 | O12: 26.43 | P12: POSTO VIP | T12: 179.69 | U12: 30.05 | V12: POSTO VIP | W12: 205.95 | X12: 34.44 | Y12: POSTO VIP | AC12: 147.7 | AD12: 24.7 | AE12: POSTO VIP | AI12: 207.14 | AJ12: 93.65 | AK12: POSTO VIP | AL12: 164.56 | AM12: 27.52 | AN12: POSTO VIP | AO12: 129.94 | AP12: 21.73 | AQ12: POSTO VIP | AX12: 155.48 | AY12: 26 | AZ12: POSTO VIP | BA12: 138.37 | BB12: 23.14 | BC12: POSTO VIP | BG12: 75.4 | BH12: 12.6 | BI12: POSTO VIP
A13: JERFFERSON MOREIRA | B13: RVU5A22 | C13: RENEGADE | D13: - | E13: 46018 | F13: 49015 | G13: =F13-E13 -> 2997 | H13: =SUM(K13+N13+Q13+T13+W13+Z13+AC13+AF13+AI13+AL13+AO13+AR13+AU13+AX13+BA13+BD13+BG13+BJ13+BM13+BP13+BS13+BV13+BY13+CB13+CE13+CH13+CK13+CN13+CQ13+CT13+CW13) -> 2053.27 | I13: =COUNTA(L13,O13,R13,U13,X13,AA13,AD13,AG13,AJ13,AM13,AP13,AS13,AV13,AY13,BB13,BE13,BH13,BK13,BN13,BQ13,BT13,BW13,BZ13,CC13,CF13,CI13,CL13,CO13,CR13,CU13,CX13) -> 9 | J13: Junho | K13: 250.19 | L13: 42.049 | M13: POSTO VIP | W13: 225.44 | X13: 37.89 | Y13: POSTO VIP | AO13: 262.93 | AP13: 44.19 | AQ13: POSTO VIP | AX13: 216.58 | AY13: 36.4 | AZ13: POSTO VIP | BJ13: 176.77 | BK13: 29.7 | BL13: PSOTO VIP | BM13: 231.63 | BN13: 38.93 | BO13: POSTO VIP | BV13: 226.1 | BW13: 38 | BX13: POSTO VIP | CE13: 185.4 | CF13: 31.16 | CG13: POSTO VIP | CQ13: 278.23 | CR13: 45.99 | CS13: POSTO VIP
A14: JERFFERSON MOREIRA | B14: RVU5A22 | C14: RENEGADE | D14: - | E14: 49015 | F14: 54130 | G14: =F14-E14 -> 5115 | H14: =SUM(K14+N14+Q14+T14+W14+Z14+AC14+AF14+AI14+AL14+AO14+AR14+AU14+AX14+BA14+BD14+BG14+BJ14+BM14+BP14+BS14+BV14+BY14+CB14+CE14+CH14+CK14+CN14+CQ14+CT14+CW14) -> 1578.2 | I14: =COUNTA(L14,O14,R14,U14,X14,AA14,AD14,AG14,AJ14,AM14,AP14,AS14,AV14,AY14,BB14,BE14,BH14,BK14,BN14,BQ14,BT14,BW14,BZ14,CC14,CF14,CI14,CL14,CO14,CR14,CU14,CX14) -> 7 | J14: Julho | Q14: 226.55 | R14: 37.44 | S14: POSTO VIP | T14: 128.01 | U14: 21.02 | V14: POSTO VIP | BD14: 307.38 | BE14: 49.25 | BF14: POSTO VIP | BP14: 197.74 | BQ14: 31.69 | BR14: POSTO VIP | BY14: 155.37 | BZ14: 24.9 | CA14: PSOTO VIP | CE14: 303.07 | CF14: 48.56 | CG14: PSOTO VIP | CK14: 260.08 | CL14: 41.68 | CM14: POSTO VIP
A15: FELIPE REIS | B15: ELH8E81 | C15: TCROSS | D15: - | E15: 41560 | F15: 43253 | G15: =F15-E15 -> 1693 | H15: =SUM(K15+N15+Q15+T15+W15+Z15+AC15+AF15+AI15+AL15+AO15+AR15+AU15+AX15+BA15+BD15+BG15+BJ15+BM15+BP15+BS15+BV15+BY15+CB15+CE15+CH15+CK15+CN15+CQ15+CT15+CW15) -> 712.57 | I15: =COUNTA(L15,O15,R15,U15,X15,AA15,AD15,AG15,AJ15,AM15,AP15,AS15,AV15,AY15,BB15,BE15,BH15,BK15,BN15,BQ15,BT15,BW15,BZ15,CC15,CF15,CI15,CL15,CO15,CR15,CU15,CX15) -> 3 | J15: Julho | AO15: 234.41 | AP15: 37.58 | AQ15: POSTO VIP | BG15: 233.56 | BH15: 37.43 | BI15: POSTO VIP | CB15: 244.6 | CC15: 39.2 | CD15: POSTO VIP
A16: JERFFERSON MOREIRA | B16: RVU5A22 | C16: RENEGADE | D16: - | E16: 54130 | F16: 55428 | G16: =F16-E16 -> 1298 | H16: =SUM(K16+N16+Q16+T16+W16+Z16+AC16+AF16+AI16+AL16+AO16+AR16+AU16+AX16+BA16+BD16+BG16+BJ16+BM16+BP16+BS16+BV16+BY16+CB16+CE16+CH16+CK16+CN16+CQ16+CT16+CW16) -> 1298.48 | I16: =COUNTA(L16,O16,R16,U16,X16,AA16,AD16,AG16,AJ16,AM16,AP16,AS16,AV16,AY16,BB16,BE16,BH16,BK16,BN16,BQ16,BT16,BW16,BZ16,CC16,CF16,CI16,CL16,CO16,CR16,CU16,CX16) -> 5 | J16: Agosto | K16: 304.13 | L16: 49.94 | M16: POSTO DOM PEDRO | AF16: 287.93 | AG16: 47.28 | AH16: POSTO DOM PEDRO | BP16: 261.74 | BQ16: 42.98 | BR16: REDE DOM PEDRO | BY16: 170.13 | BZ16: 28.4 | CA16: REDE DOM PEDRO | CT16: 274.55 | CU16: 45.83 | CV16: REDE DOM PEDRO
A17: JERFFERSON MOREIRA | B17: TCB9G87 | C17: TRACKER | D17: - | E17: 10473 | F17: 11957 | G17: =F17-E17 -> 1484 | H17: =SUM(K17+N17+Q17+T17+W17+Z17+AC17+AF17+AI17+AL17+AO17+AR17+AU17+AX17+BA17+BD17+BG17+BJ17+BM17+BP17+BS17+BV17+BY17+CB17+CE17+CH17+CK17+CN17+CQ17+CT17+CW17) -> 0 | I17: =COUNTA(L17,O17,R17,U17,X17,AA17,AD17,AG17,AJ17,AM17,AP17,AS17,AV17,AY17,BB17,BE17,BH17,BK17,BN17,BQ17,BT17,BW17,BZ17,CC17,CF17,CI17,CL17,CO17,CR17,CU17,CX17) -> 0 | J17: Dezembro

Sheet 22005_MAPEAMENTO
A4: CONDUTOR | B4: VEICULO | C4: PLACA | D4: STATUS | E4: KM INICIAL | F4: KM FINAL | G4: KM PERCORRIDA | H4: CONSUMO | I4: CONSUMO DE 01 A 15 | J4: CONSUMO DE 16 A 31 | K4: ABASTECIMENTO MÊS | L4: QTD LITROS | M4: MÊS | N4: OBS
A5: Suianne | B5: C4 | C5: SHB4H30 | D5: - | E5: 44038 | F5: 46142 | G5: =F5-E5 -> 2104 | H5: =SUM(I5+J5) -> 603.38 | I5: 332.59 | J5: 270.79 | K5: 4 | L5: 107.45 | M5: Janeiro | N5: DESMOBILIZADO
A6: Renata | B6: TCROSS | C6: ENI9F24 | D6: - | E6: 35529 | F6: 37274 | G6: =F6-E6 -> 1745 | H6: =SUM(I6+J6) -> 821.55 | I6: 423.07 | J6: 398.48 | K6: 4 | L6: 141.262 | M6: Janeiro
A7: Paulo Ricardo | B7: RENEGADE | C7: SIM9C98 | D7: - | E7: 11110 | F7: 14051 | G7: =F7-E7 -> 2941 | H7: =SUM(I7+J7) -> 1685.54 | I7: 677.87 | J7: 1007.67 | K7: 7 | L7: 283.78 | M7: Janeiro
A8: Jamille | B8: TCROSS | C8: ENI9F24 | D8: - | E8: 37274 | F8: 37730 | G8: =F8-E8 -> 456 | H8: =SUM(I8+J8) -> 202.99 | I8: 202.99 | J8: 0 | K8: 1 | L8: 35.12 | M8: Fevereiro
A9: Paulo Ricardo | B9: RENEGADE | C9: SIM9C98 | D9: - | E9: 14051 | F9: 17195 | G9: =F9-E9 -> 3144 | H9: =SUM(I9+J9) -> 1923.46 | I9: 837.17 | J9: 1086.29 | K9: 7 | L9: 137.37 | M9: Fevereiro
A10: Jamille | B10: TCROSS | C10: ENI9F24 | D10: - | E10: 37730 | F10: 39250 | G10: =F10-E10 -> 1520 | H10: =SUM(I10+J10) -> 1257.57 | I10: 850 | J10: 407.57 | K10: 6 | L10: 225.54 | M10: Março
A11: Paulo Ricardo | B11: RENEGADE | C11: SIM9C98 | D11: - | E11: 17195 | F11: 21097 | G11: =F11-E11 -> 3902 | H11: =SUM(I11+J11) -> 1016.64 | I11: 763.79 | J11: 252.85 | K11: 4 | L11: 166 | M11: Março
A12: Jamille | B12: TCROSS | C12: ENI9F24 | D12: - | E12: 39250 | F12: 39472 | G12: =F12-E12 -> 222 | H12: =SUM(I12+J12) -> 176.62 | J12: 176.62 | K12: 1 | L12: 37.66 | M12: Abril
A13: Paulo Ricardo | B13: RENEGADE | C13: SIM9C98 | D13: - | E13: 21097 | F13: 23899 | G13: =F13-E13 -> 2802 | H13: =SUM(I13+J13) -> 1417.64 | I13: 822.08 | J13: 595.56 | K13: 5 | L13: 231.97 | M13: Abril
A14: Paulo Ricardo | B14: RENEGADE | C14: SIM9C98 | D14: - | E14: 23899 | F14: 25978 | G14: =F14-E14 -> 2079 | H14: =SUM(I14+J14) -> 276.97 | I14: 276.97 | J14: 0 | K14: 1 | L14: 45.48 | M14: Maio

Sheet 21029_ENEL GOIANIA
A4: CONDUTOR | B4: VEICULO | C4: PLACA | D4: STATUS | E4: KM INICIAL | F4: KM FINAL | G4: KM PERCORRIDA | H4: CONSUMO | I4: CONSUMO DE 01 A 15 | J4: CONSUMO DE 16 A 31 | K4: ABASTECIMENTO MÊS | L4: QTD LITROS | M4: MÊS | N4: OBS
A5: GLEISON | B5: ARGO | C5: RTE1I62 | D5: - | E5: 37591 | F5: 38560 | G5: =F5-E5 -> 969 | H5: =SUM(I5+J5) -> 526.18 | I5: 328.73 | J5: 197.45 | K5: 5 | L5: 157.116 | M5: 45292
A6: PEDRO / RAINOR | B6: ARGO | C6: RUM5I29 | D6: - | E6: 9625 | F6: 10649 | G6: =F6-E6 -> 1024 | H6: =SUM(I6+J6) -> 440.53 | I6: 253.48 | J6: 187.05 | K6: 3 | L6: 74.16 | M6: 45292
A7: GLEISON | B7: ARGO | C7: RTE1I62 | D7: - | E7: 38560 | F7: 39149 | G7: =F7-E7 -> 589 | H7: =SUM(I7+J7) -> 300.05 | I7: 123.62 | J7: 176.43 | K7: 3 | L7: 86.088 | M7: 45323
A8: PEDRO / RAINOR | B8: ARGO | C8: RUM5I29 | D8: - | E8: 10649 | F8: 11134 | G8: =F8-E8 -> 485 | H8: =SUM(I8+J8) -> 205.05 | I8: 205.05 | J8: 0 | K8: 1 | L8: 34.52 | M8: 45323
A9: GLEISON | B9: ARGO | C9: RTE1I62 | D9: - | E9: 39149 | F9: 40265 | G9: =F9-E9 -> 1116 | H9: =SUM(I9+J9) -> 343.35 | I9: 343.35 | J9: 0 | K9: 3 | L9: 96.153 | M9: 45352
A10: PEDRO / RAINOR | B10: ARGO | C10: RUM5I29 | D10: - | E10: 11134 | F10: 12157 | G10: =F10-E10 -> 1023 | H10: =SUM(I10+J10) -> 611.94 | I10: 611.94 | J10: 0 | K10: 3 | L10: 103.02 | M10: 45352
A11: GLEISON | B11: ARGO | C11: RTE1I62 | D11: - | E11: 40265 | F11: 41245 | G11: =F11-E11 -> 980 | H11: =SUM(I11+J11) -> 740.63 | I11: 265.12 | J11: 475.51 | K11: 5 | L11: 195.23 | M11: 45383
A12: PEDRO / RAINOR | B12: ARGO | C12: RUM5I29 | D12: - | E12: 12157 | F12: 13076 | G12: =F12-E12 -> 919 | H12: =SUM(I12+J12) -> 570.32 | I12: 208.02 | J12: 362.3 | K12: 3 | L12: 97.2 | M12: 45383
A13: GLEISON | B13: ARGO | C13: RTE1I62 | D13: - | E13: 41245 | F13: 42242 | G13: =F13-E13 -> 997 | H13: 245.03 | I13: 96.31 | J13: 245.03 | K13: 3 | L13: 86.21 | M13: 45413
A14: PEDRO / RAINOR | B14: ARGO | C14: RUM5I29 | D14: - | E14: 13076 | F14: 13599 | G14: =F14-E14 -> 523 | H14: 185.09 | I14: 0 | J14: 185.09 | K14: 1 | L14: 34.34 | M14: 45413
A15: GLEISON | B15: ARGO | C15: RTE1I62 | D15: - | E15: 42242 | F15: 42748 | G15: =F15-E15 -> 506 | H15: 174.54 | I15: 174.54 | J15: 0 | K15: 1 | L15: 44.87 | M15: 45444
A16: PEDRO / RAINOR | B16: ARGO | C16: RUM5I29 | D16: - | E16: 13599 | F16: 14148 | G16: =F16-E16 -> 549 | H16: 366.35 | I16: 200.02 | J16: 166.33 | K16: 2 | L16: 62.2 | M16: 45444
A17: GLEISON | B17: ARGO | C17: RTE1I62 | D17: - | E17: 42748 | F17: 43921 | G17: =F17-E17 -> 1173 | H17: 788.13 | I17: 506.13 | J17: 282.03 | K17: 3 | L17: 196.64 | M17: 45474
A18: PEDRO / RAINOR | B18: ARGO | C18: RUM5I29 | D18: - | E18: 14148 | F18: 14608 | G18: =F18-E18 -> 460 | H18: 208.78 | I18: 208.78 | J18: 0 | K18: 1 | L18: 32.42 | M18: 45474
A19: GLEISON | B19: ARGO | C19: RTE1I62 | D19: - | E19: 43921 | F19: 44891 | G19: =F19-E19 -> 970 | H19: =SUM(I19+J19) -> 527.19 | I19: 193.58 | J19: 333.61 | K19: 3 | L19: 125.82 | M19: 45505
A20: PEDRO / RAINOR | B20: ARGO | C20: RUM5I29 | D20: - | E20: 14608 | F20: 15444 | G20: =F20-E20 -> 836 | H20: =SUM(I20+J20) -> 389.478 | I20: 181.798 | J20: 207.68 | K20: 2 | L20: 69.65 | M20: 45505
A21: GLEISON | B21: ARGO | C21: RTE1I62 | D21: - | E21: 44891 | F21: 45916 | G21: =F21-E21 -> 1025 | H21: =SUM(I21+J21) -> 541.6 | I21: 208.83 | J21: 332.77 | K21: 3 | L21: 129.06 | M21: 45536
A22: PEDRO / RAINOR | B22: ARGO | C22: RUM5I29 | D22: - | E22: 15444 | F22: 15549 | G22: =F22-E22 -> 105 | H22: =SUM(I22+J22) -> 0 | I22: 0 | J22: 0 | M22: 45536
A23: GLEISON | B23: ARGO | C23: RTE1I62 | D23: ATIVO | E23: 45916 | F23: 46145 | G23: =F23-E23 -> 229 | H23: =SUM(I23+J23) -> 244.1 | I23: 89.2 | J23: 154.9 | K23: 2 | L23: 54.23 | M23: 45566
A24: PEDRO / RAINOR | B24: ARGO | C24: RUM5I29 | D24: ATIVO | E24: 15549 | F24: 16385 | G24: =F24-E24 -> 836 | H24: =SUM(I24+J24) -> 408.04 | I24: 225.14 | J24: 182.9 | K24: 2 | L24: 63.3 | M24: 45566
A25: GLEISON | B25: ARGO | C25: RTE1I62 | D25: ATIVO | E25: 46145 | F25: 47241 | G25: =F25-E25 -> 1096 | H25: =SUM(I25+J25) -> 0 | M25: 45597
A26: RAINOR | B26: ARGO | C26: RUM5I29 | D26: ATIVO | E26: 16619 | F26: 16978 | G26: =F26-E26 -> 359 | H26: =SUM(I26+J26) -> 0 | M26: 45597
A27: GLEISON | B27: ARGO | C27: RTE1I62 | D27: ATIVO | E27: 47241 | F27: 47495 | G27: =F27-E27 -> 254 | H27: =SUM(I27+J27) -> 0 | M27: 45627
A28: RAINOR | B28: ARGO | C28: RUM5I29 | D28: ATIVO | E28: 16978 | F28: 17538 | G28: =F28-E28 -> 560 | H28: =SUM(I28+J28) -> 0 | M28: 45627
A29: GLEISON | B29: ARGO | C29: RTE1I62 | D29: ATIVO | E29: 47495 | F29: 49140 | G29: =F29-E29 -> 1645 | H29: =SUM(I29+J29) -> 0 | M29: 45658
A30: RAINOR | B30: ARGO | C30: RUM5I29 | D30: ATIVO | E30: 17538 | F30: 18450 | G30: =F30-E30 -> 912 | H30: =SUM(I30+J30) -> 0 | M30: 45658
A31: GLEISON | B31: ARGO | C31: RTE1I62 | D31: ATIVO | E31: 49140 | F31: 51085 | G31: =F31-E31 -> 1945 | H31: =SUM(I31+J31) -> 0 | M31: 45689
A32: RAINOR | B32: ARGO | C32: RUM5I29 | D32: ATIVO | E32: 18450 | F32: 19107 | G32: =F32-E32 -> 657 | H32: =SUM(I32+J32) -> 209.04 | J32: 209.04 | K32: 1 | M32: 45689
A33: GLEISON | B33: ARGO | C33: RTE1I62 | D33: ATIVO | E33: 51085 | F33: 52713 | G33: =F33-E33 -> 1628 | H33: =SUM(I33+J33) -> 0 | M33: 45717
A34: RAINOR | B34: ARGO | C34: RUM5I29 | D34: ATIVO | E34: 19107 | F34: 20284 | G34: =F34-E34 -> 1177 | H34: =SUM(I34+J34) -> 218.2 | I34: 218.2 | K34: 1 | M34: 45717
A35: GLEISON | B35: ARGO | C35: RTE1I62 | D35: ATIVO | E35: 52713 | F35: 54306 | G35: =F35-E35 -> 1593 | H35: =SUM(I35+J35) -> 0 | M35: 45748
A36: RAINOR | B36: ARGO | C36: RUM5I29 | D36: ATIVO | E36: 20284 | F36: 21616 | G36: =F36-E36 -> 1332 | H36: =SUM(I36+J36) -> 0 | M36: 45748
A37: GLEISON | B37: ARGO | C37: RTE1I62 | D37: ATIVO | E37: 54306 | F37: 55449 | G37: =F37-E37 -> 1143 | H37: =SUM(I37+J37) -> 598.48 | I37: =98.98 -> 98.98 | J37: =294.62+204.88 -> 499.5 | K37: 3 | M37: 45778
A38: RAINOR | B38: ARGO | C38: RUM5I29 | D38: ATIVO | E38: 21616 | F38: 22476 | G38: =F38-E38 -> 860 | H38: =SUM(I38+J38) -> 427.36 | I38: 230.81 | J38: 196.55 | K38: 2 | M38: 45778
A39: GLEISON | B39: ARGO | C39: RTE1I62 | D39: ATIVO | E39: 55449 | F39: 56104 | G39: =F39-E39 -> 655 | H39: =SUM(I39+J39) -> 361.16 | I39: 194.3 | J39: 166.86 | K39: 2 | M39: 45809
A40: RAINOR | B40: ARGO | C40: RUM5I29 | D40: ATIVO | E40: 22476 | F40: 23135 | G40: =F40-E40 -> 659 | H40: =SUM(I40+J40) -> 450.83 | I40: 240.03 | J40: 210.8 | K40: 2 | M40: 45809
A41: GLEISON | B41: ARGO | C41: RTE1I62 | D41: ATIVO | E41: 56104 | F41: 58673 | G41: =F41-E41 -> 2569 | H41: =SUM(I41+J41) -> 1531.19 | I41: =204.56+240+290.15+206.91 -> 941.62 | J41: =249.5+218.22+121.85 -> 589.57 | K41: 7 | L41: =33.812+40.067+47.18+34.2+41.24+36.07+20.14 -> 252.709 | M41: 45839
A42: RAINOR | B42: ARGO | C42: RUM5I29 | D42: ATIVO | E42: 23135 | F42: 23791 | G42: =F42-E42 -> 656 | H42: =SUM(I42+J42) -> 208.19 | J42: =177.67+30.52 -> 208.19 | K42: 2 | M42: 45839
A43: GLEISON | B43: ARGO | C43: RTE1I62 | D43: ATIVO | E43: 58673 | F43: 60157 | G43: =F43-E43 -> 1484 | H43: =SUM(I43+J43) -> 772.25 | I43: 266.58 | J43: =247.62+258.05 -> 505.67 | K43: 3 | L43: 131.868 | M43: 45870 | N43: Férias: 25 a 29/08/2025
A44: RAINOR | B44: POLO | C44: TJZ9J36 | D44: ATIVO | E44: 8 | F44: 940 | G44: =F44-E44 -> 932 | H44: =SUM(I44+J44) -> 472.74 | J44: =222.42+250.32 -> 472.74 | K44: 2 | L44: 80.49 | M44: 45870
A45: GLEISON | B45: ARGO | C45: RTE1I62 | D45: ATIVO | E45: 60157 | F45: 62066 | G45: =F45-E45 -> 1909 | H45: =SUM(I45+J45) -> 1168.67 | I45: =229.56+238.61 -> 468.17 | J45: =287.86+176.49+236.15 -> 700.5 | K45: 5 | L45: 191.087 | M45: 45901
A46: RAINOR | B46: POLO | C46: TJZ9J36 | D46: ATIVO | E46: 940 | F46: 2519 | G46: =F46-E46 -> 1579 | H46: =SUM(I46+J46) -> 924.19 | I46: 211.33 | J46: =188.61+261.01+263.24 -> 712.86 | K46: 4 | L46: =37.14 +28.84 +39.91+40.25 -> 146.14 | M46: 45901
A47: GLEISON | B47: ARGO | C47: RTE1I62 | D47: ATIVO | E47: 62066 | F47: 64436 | G47: =F47-E47 -> 2370 | H47: =SUM(I47+J47) -> 1018.78 | I47: =258.77 -> 258.77 | J47: =234.42+271.25+254.34 -> 760.01 | K47: 4 | L47: =40.496+40.488+43.211+40.89 -> 165.085 | M47: 45931
A48: RAINOR | B48: POLO | C48: TJZ9J36 | D48: ATIVO | E48: 2519 | F48: 4185 | G48: =F48-E48 -> 1666 | H48: =SUM(I48+J48) -> 530.32 | I48: =260.03 -> 260.03 | J48: 270.29 | K48: 2 | L48: =39.76+41.97 -> 81.73 | M48: 45931
A49: GLEISON | B49: ARGO | C49: RTE1I62 | D49: ATIVO | E49: 64436 | F49: 65137 | G49: =F49-E49 -> 701 | H49: =SUM(I49+J49) -> 0 | M49: 45962 | N49: Férias: 18 a 26/11/2025
A50: RAINOR | B50: POLO | C50: TJZ9J36 | D50: ATIVO | E50: 4185 | F50: 4991 | G50: =F50-E50 -> 806 | H50: =SUM(I50+J50) -> 249.81 | J50: 249.81 | K50: 1 | L50: 38.79 | M50: 45962
A51: GLEISON | B51: ARGO | C51: RTE1I62 | D51: ATIVO | E51: 65137 | F51: 66637 | G51: =F51-E51 -> 1500 | H51: =SUM(I51+J51) -> 983.08 | I51: =297.14+186.98+205.51 -> 689.63 | J51: =293.45 -> 293.45 | K51: 4 | L51: =45.181+29.68+32.62+46.58 -> 154.061 | M51: 45992
A52: RAINOR | B52: POLO | C52: TJZ9J36 | D52: ATIVO | E52: 4991 | F52: 6411 | G52: =F52-E52 -> 1420 | H52: =SUM(I52+J52) -> 931.76 | I52: =252.83+248.2 -> 501.03 | J52: =249.11+181.62 -> 430.73 | K52: 4 | L52: =39.26+38.54+38.09+27.77 -> 143.66 | M52: 45992
A53: GLEISON | B53: ARGO | C53: RTE1I62 | D53: ATIVO | E53: 66637 | F53: 69142 | G53: =F53-E53 -> 2505 | H53: =SUM(I53+J53) -> 0 | M53: 46023
A54: RAINOR | B54: POLO | C54: TJZ9J36 | D54: ATIVO | E54: 6411 | F54: 8660 | G54: =F54-E54 -> 2249 | H54: =SUM(I54+J54) -> 0 | M54: 46023
A55: GLEISON | B55: ARGO | C55: RTE1I63 | D55: ATIVO | E55: 69142 | F55: 70491 | G55: =F55-E55 -> 1349 | H55: =SUM(I55+J55) -> 0 | M55: 46054
A56: RAINOR | B56: POLO | C56: TJZ9J37 | D56: ATIVO | E56: 8660 | F56: 9937 | G56: =F56-E56 -> 1277 | H56: =SUM(I56+J56) -> 0 | M56: 46054
A57: GLEISON | B57: ARGO | C57: RTE1I64 | D57: ATIVO | E57: 70491 | F57: 71736 | G57: =F57-E57 -> 1245 | H57: =SUM(I57+J57) -> 0 | M57: 46082 | N57: Devolução 01/04/2026
A58: RAINOR | B58: POLO | C58: TJZ9J38 | D58: ATIVO | E58: 9937 | F58: 12510 | G58: =F58-E58 -> 2573 | H58: =SUM(I58+J58) -> 0 | M58: 46082 | N58: Devolução 30/03/2026
A59: GLEISON | B59: ARGO | C59: RTE1I65 | D59: ATIVO | G59: =F59-E59 -> 0 | H59: =SUM(I59+J59) -> 0 | M59: 46113
A60: RAINOR | B60: POLO | C60: TJZ9J39 | D60: ATIVO | G60: =F60-E60 -> 0 | H60: =SUM(I60+J60) -> 0 | M60: 46113

Sheet 19018_F.Angra
A4: CONDUTOR | B4: VEICULO | C4: PLACA | D4: STATUS | E4: KM INICIAL | F4: KM FINAL | G4: KM PERCORRIDA | H4: CONSUMO | I4: CONSUMO DE 01 A 15 | J4: CONSUMO DE 16 A 31 | K4: ABASTECIMENTO MÊS | L4: QTD LITROS | M4: MÊS | N4: OBS
A5: LUIZ FERNANDO | B5: HILUX | C5: SEO0D82 | D5: - | E5: 17852 | F5: 19998 | G5: =F5-E5 -> 2146 | H5: =SUM(I5+J5) -> 1200 | I5: 400 | J5: 800 | K5: 4 | L5: 180.69 | M5: Janeiro
A6: ANDERSON | B6: S10 | C6: SHF5J17 | D6: - | E6: 20562 | F6: 22638 | G6: =F6-E6 -> 2076 | H6: =SUM(I6+J6) -> 600 | I6: 600 | K6: 2 | L6: 72.6 | M6: Janeiro | N6: DESMOBILIZADO
A7: ANDERSON | B7: HILUX | C7: SEO0D82 | D7: - | E7: 19998 | F7: 22766 | G7: =F7-E7 -> 2768 | H7: =SUM(I7+J7) -> 1200.01 | I7: 450 | J7: 750.01 | K7: 5 | L7: 206.27 | M7: Fevereiro
A8: ANDERSON | B8: HILUX | C8: SEO0D82 | D8: - | E8: 22766 | F8: 25421 | G8: =F8-E8 -> 2655 | H8: =SUM(I8+J8) -> 1250 | I8: 650 | J8: 600 | K8: 6 | L8: 221.01 | M8: Março
A9: ANDERSON | B9: HILUX | C9: SEO0D82 | D9: - | E9: 25421 | F9: 27148 | G9: =F9-E9 -> 1727 | H9: =SUM(I9+J9) -> 950 | I9: 250 | J9: 700 | K9: 4 | L9: 159.6 | M9: Abril
A10: ANDERSON | B10: HILUX | C10: SEO0D82 | D10: - | E10: 27148 | F10: 29283 | G10: =F10-E10 -> 2135 | H10: =SUM(I10+J10) -> 1000 | I10: 550 | J10: 450 | K10: 3 | L10: 177.73 | M10: Maio
A11: ANDERSON | B11: HILUX | C11: SEO0D82 | D11: - | E11: 29283 | F11: 31115 | G11: =F11-E11 -> 1832 | H11: =SUM(I11+J11) -> 1000 | I11: 500 | J11: 500 | K11: 4 | L11: 184.84 | M11: Junho
A12: ANDERSON | B12: HILUX | C12: SEO0D82 | D12: - | E12: 31115 | F12: 33098 | G12: =F12-E12 -> 1983 | H12: =SUM(I12+J12) -> 1080.1 | I12: 530.01 | J12: 550.09 | K12: 5 | L12: 187.48 | M12: Julho
A13: ANDERSON | B13: HILUX | C13: SEO0D82 | D13: - | E13: 33110 | F13: 34627 | G13: =F13-E13 -> 1517 | H13: =SUM(I13+J13) -> 700 | I13: 450 | J13: 250 | K13: 2 | L13: 125.21 | M13: Agosto
A14: ANDERSON | B14: S10 | C14: SYD6H52 | D14: - | E14: 19159 | F14: 19807 | G14: =F14-E14 -> 648 | H14: 150 | I14: 450 | J14: 250 | K14: 3 | L14: 125.7 | M14: Setembro
A15: ANDERSON | B15: S10 | C15: SYD6H52 | D15: - | E15: 19807 | F15: 20958 | G15: =F15-E15 -> 1151 | H15: 150 | I15: 450 | J15: 250 | K15: 3 | L15: 125.7 | M15: Setembro
A16: ANDERSON | B16: S10 | C16: SYD6H52 | D16: - | E16: 21124 | F16: 22394 | G16: =F16-E16 -> 1270 | H16: 300 | I16: 0 | J16: 300 | K16: 1 | L16: 53.95 | M16: Novembro
A17: ANDERSON | B17: S10 | C17: SYD6H52 | D17: - | E17: 22394 | F17: 22576 | G17: =F17-E17 -> 182 | H17: 426.05 | I17: 426.05 | J17: 0 | K17: 2 | L17: 76.5 | M17: Dezembro

Sheet 20017_DNIT
A4: CONDUTOR | B4: VEICULO | C4: PLACA | D4: STATUS | E4: KM INICIAL | F4: KM FINAL | G4: KM PERCORRIDA | H4: CONSUMO | I4: CONSUMO DE 01 A 15 | J4: CONSUMO DE 16 A 31 | K4: ABASTECIMENTO MÊS | L4: QTD LITROS | M4: MÊS | N4: OBS
A5: NELLO | B5: ARGO | C5: SHG9C44 | D5: - | E5: 8168 | F5: 10563 | G5: =F5-E5 -> 2395 | H5: 949.74 | L5: 147.68 | M5: Janeiro
A6: GILSON | B6: HB20 | C6: SIE1C81 | D6: - | E6: 10274 | F6: 10461 | G6: =F6-E6 -> 187 | H6: 85.84 | L6: 22.709 | M6: Janeiro
A7: NELLO | B7: HB20 | C7: RVY3C19 | E7: 27052 | F7: 29537 | G7: =F7-E7 -> 2485 | H7: 1037.74 | K7: 4 | L7: 196.201 | M7: Fevereiro
A8: GILSON | B8: GOL | C8: SEA1I86 | D8: - | E8: 50454 | F8: 50632 | G8: =F8-E8 -> 178 | M8: Fevereiro
A9: NELLO | G9: =F9-E9 -> 0 | M9: Março
A10: GILSON | G10: =F10-E10 -> 0 | M10: Março
A11: NELLO | G11: =F11-E11 -> 0 | M11: Abril
A12: GILSON | G12: =F12-E12 -> 0 | L12: ='20017_DNIT'!H8('20017_DNIT'!H7:H8) -> #REF! | M12: Abril
A13: NELLO | G13: =F13-E13 -> 0 | M13: Maio
A14: GILSON | G14: =F14-E14 -> 0 | M14: Maio
A15: NELLO | G15: =F15-E15 -> 0 | M15: Junho
A16: GILSON | G16: =F16-E16 -> 0 | M16: Junho
A17: NELLO | G17: =F17-E17 -> 0 | M17: Julho
A18: GILSON | G18: =F18-E18 -> 0 | M18: Julho
A19: NELLO | G19: =F19-E19 -> 0 | M19: Agosto
A20: GILSON | G20: =F20-E20 -> 0 | M20: Agosto
A21: NELLO | G21: =F21-E21 -> 0 | M21: Setembro
A22: GILSON | G22: =F22-E22 -> 0 | M22: Setembro
A23: NELLO | G23: =F23-E23 -> 0 | M23: Outubro
A24: GILSON | G24: =F24-E24 -> 0 | M24: Outubro
... A28: GILSON | G28: =F28-E28 -> 0 | M28: Dezembro

Sheet 0000_ARO
A1: QTD DE VEICULOS ATIVO | B1: =COUNTIF(D3:D33,"ATIVO") -> 0 | C1: CONTROLE DE KM - 2024 - 22000_ARO | M1: ABASTECIMENTO | P1: ABASTECIMENTO | S1: ABASTECIMENTO | V1: ABASTECIMENTO | Y1: ABASTECIMENTO | AB1: ABASTECIMENTO | AE1: ABASTECIMENTO | AH1: ABASTECIMENTO | AK1: ABASTECIMENTO | AN1: ABASTECIMENTO | AQ1: ABASTECIMENTO | AT1: ABASTECIMENTO | AW1: ABASTECIMENTO | AZ1: ABASTECIMENTO | BC1: ABASTECIMENTO | BF1: ABASTECIMENTO | BI1: ABASTECIMENTO | BL1: ABASTECIMENTO | BO1: ABASTECIMENTO | BR1: ABASTECIMENTO | BU1: ABASTECIMENTO | BX1: ABASTECIMENTO | CA1: ABASTECIMENTO | CD1: ABASTECIMENTO | CG1: ABASTECIMENTO | CJ1: ABASTECIMENTO | CM1: ABASTECIMENTO | CP1: ABASTECIMENTO | CS1: ABASTECIMENTO | CV1: ABASTECIMENTO | CY1: ABASTECIMENTO | DB1: OBS | DC1: Folga
A2: CONDUTOR | B2: VEICULO | C2: PLACA | D2: STATUS | E2: KM INICIAL | F2: KM FINAL | G2: KM PERCORRIDA | H2: CONSUMO TOTAL | I2: ABASTECIMENTO MÊS | J2: POSTO S. RITA | K2: POSTO VIP | L2: MÊS | M2: 1º DIA VALOR | N2: QTD LITROS | O2: POSTO | P2: 2º DIA VALOR | Q2: QTD LITROS | R2: POSTO | S2: 3º DIA VALOR | T2: QTD LITROS | U2: POSTO | V2: 4º DIA VALOR | W2: QTD LITROS | X2: POSTO | Y2: 5º DIA VALOR | Z2: QTD LITROS | AA2: POSTO | AB2: 6º DIA VALOR | AC2: QTD LITROS | AD2: POSTO | AE2: 7º DIA VALOR | AF2: QTD LITROS | AG2: POSTO | AH2: 8º DIA VALOR | AI2: QTD LITROS | AJ2: POSTO | AK2: 9º DIA VALOR | AL2: QTD LITROS | AM2: POSTO | AN2: 10º DIA VALOR | AO2: QTD LITROS | AP2: POSTO | AQ2: 11º DIA VALOR | AR2: QTD LITROS | AS2: POSTO | AT2: 12º DIA VALOR | AU2: QTD LITROS | AV2: POSTO | AW2: 13º DIA VALOR | AX2: QTD LITROS | AY2: POSTO | AZ2: 14º DIA VALOR | BA2: QTD LITROS | BB2: POSTO | BC2: 15º DIA VALOR | BD2: QTD LITROS | BE2: POSTO | BF2: 16º DIA VALOR | BG2: QTD LITROS | BH2: POSTO | BI2: 17º DIA VALOR | BJ2: QTD LITROS | BK2: POSTO | BL2: 18º DIA VALOR | BM2: QTD LITROS | BN2: POSTO | BO2: 19º DIA VALOR | BP2: QTD LITROS | BQ2: POSTO | BR2: 20º DIA VALOR | BS2: QTD LITROS | BT2: POSTO | BU2: 21º DIA VALOR | BV2: QTD LITROS | BW2: POSTO | BX2: 22º DIA VALOR | BY2: QTD LITROS | BZ2: POSTO | CA2: 23º DIA VALOR | CB2: QTD LITROS | CC2: POSTO | CD2: 24º DIA VALOR | CE2: QTD LITROS | CF2: POSTO | CG2: 25º DIA VALOR | CH2: QTD LITROS | CI2: POSTO | CJ2: 26º DIA VALOR | CK2: QTD LITROS | CL2: POSTO | CM2: 27º DIA VALOR | CN2: QTD LITROS | CO2: POSTO | CP2: 28º DIA VALOR | CQ2: QTD LITROS | CR2: POSTO | CS2: 29º DIA VALOR | CT2: QTD LITROS | CU2: POSTO | CV2: 30º DIA VALOR | CW2: QTD LITROS | CX2: POSTO | CY2: 31º DIA VALOR | CZ2: QTD LITROS | DA2: POSTO
A3: ESEQUIAS | B3: TCROSS | C3: SYD7G06 | D3: - | E3: 4907 | F3: 7062 | G3: =F3-E3 -> 2155 | H3: =SUM(M3+P3+S3+V3+Y3+AB3+AE3+AH3+AK3+AN3+AQ3+AT3+AW3+AZ3+BC3+BF3+BI3+BL3+BO3+BR3+BU3+BX3+CA3+CD3+CG3+CJ3+CM3+CP3+CS3+CV3+CY3) -> 1141.65 | I3: =COUNTA(N3,Q3,T3,W3,Z3,AC3,AF3,AI3,AL3,AO3,AR3,AU3,AX3,BA3,BD3,BG3,BJ3,BM3,BP3,BS3,BV3,BY3,CB3,CE3,CH3,CK3,CN3,CQ3,CT3,CW3,CZ3) -> 4 | J3: =COUNTIF(M3:DC3,"POSTO S. RITA") -> 0 | K3: =COUNTIF(M3:DD3,"POSTO VIP") -> 0 | L3: Fevereiro | AB3: 306.44 | AC3: 52.117 | AD3: POSTO CAMACAM | BC3: 266.55 | BD3: 43.848 | BE3: POSTO CAMACAM | BX3: 269.86 | BY3: 44.023 | BZ3: POSTO CAMACAM | CP3: 298.8 | CQ3: 48.745 | CR3: POSTO CAMACAM
A4: ESEQUIAS | B4: TCROSS | C4: SYD7G06 | D4: - | E4: 7062 | F4: 9100 | G4: =F4-E4 -> 2038 | H4: =SUM(M4+P4+S4+V4+Y4+AB4+AE4+AH4+AK4+AN4+AQ4+AT4+AW4+AZ4+BC4+BF4+BI4+BL4+BO4+BR4+BU4+BX4+CA4+CD4+CG4+CJ4+CM4+CP4+CS4+CV4+CY4) -> 987.56 | I4: =COUNTA(N4,Q4,T4,W4,Z4,AC4,AF4,AI4,AL4,AO4,AR4,AU4,AX4,BA4,BD4,BG4,BJ4,BM4,BP4,BS4,BV4,BY4,CB4,CE4,CH4,CK4,CN4,CQ4,CT4,CW4,CZ4) -> 4 | J4: =COUNTIF(M4:DC4,"POSTO S. RITA") -> 0 | K4: =COUNTIF(N4:DD4,"POSTO VIP") -> 0 | L4: Março | AE4: 290.62 | AF4: 47.41 | AG4: POSTO CAMACAM | AZ4: 298.6 | BA4: 48.386 | BB4: POSTO CAMACAM | BU4: 224.21 | BV4: 36.577 | BW4: POSTO CAMACAM | CJ4: 174.13 | CK4: 28.407 | CL4: POSTO CAMACAM
D5: - | G5: =F5-E5 -> 0 | H5: =SUM(M5+P5+S5+V5+Y5+AB5+AE5+AH5+AK5+AN5+AQ5+AT5+AW5+AZ5+BC5+BF5+BI5+BL5+BO5+BR5+BU5+BX5+CA5+CD5+CG5+CJ5+CM5+CP5+CS5+CV5+CY5) -> 0 | I5: =COUNTA(N5,Q5,T5,W5,Z5,AC5,AF5,AI5,AL5,AO5,AR5,AU5,AX5,BA5,BD5,BG5,BJ5,BM5,BP5,BS5,BV5,BY5,CB5,CE5,CH5,CK5,CN5,CQ5,CT5,CW5,CZ5) -> 0 | J5: =COUNTIF(M5:DC5,"POSTO S. RITA") -> 0 | K5: =COUNTIF(N5:DD5,"POSTO VIP") -> 0 | L5: Março
D6: - | G6: =F6-E6 -> 0 | H6: =SUM(M6+P6+S6+V6+Y6+AB6+AE6+AH6+AK6+AN6+AQ6+AT6+AW6+AZ6+BC6+BF6+BI6+BL6+BO6+BR6+BU6+BX6+CA6+CD6+CG6+CJ6+CM6+CP6+CS6+CV6+CY6) -> 0 | I6: =COUNTA(N6,Q6,T6,W6,Z6,AC6,AF6,AI6,AL6,AO6,AR6,AU6,AX6,BA6,BD6,BG6,BJ6,BM6,BP6,BS6,BV6,BY6,CB6,CE6,CH6,CK6,CN6,CQ6,CT6,CW6,CZ6) -> 0 | J6: =COUNTIF(M6:DC6,"POSTO S. RITA") -> 0 | K6: =COUNTIF(N6:DD6,"POSTO VIP") -> 0 | L6: Março
D7: - | G7: =F7-E7 -> 0 | H7: =SUM(M7+P7+S7+V7+Y7+AB7+AE7+AH7+AK7+AN7+AQ7+AT7+AW7+AZ7+BC7+BF7+BI7+BL7+BO7+BR7+BU7+BX7+CA7+CD7+CG7+CJ7+CM7+CP7+CS7+CV7+CY7) -> 0 | I7: =COUNTA(N7,Q7,T7,W7,Z7,AC7,AF7,AI7,AL7,AO7,AR7,AU7,AX7,BA7,BD7,BG7,BJ7,BM7,BP7,BS7,BV7,BY7,CB7,CE7,CH7,CK7,CN7,CQ7,CT7,CW7,CZ7) -> 0 | J7: =COUNTIF(M7:DC7,"POSTO S. RITA") -> 0 | K7: =COUNTIF(N7:DD7,"POSTO VIP") -> 0 | L7: Abril
D8: - | G8: =F8-E8 -> 0 | H8: =SUM(M8+P8+S8+V8+Y8+AB8+AE8+AH8+AK8+AN8+AQ8+AT8+AW8+AZ8+BC8+BF8+BI8+BL8+BO8+BR8+BU8+BX8+CA8+CD8+CG8+CJ8+CM8+CP8+CS8+CV8+CY8) -> 0 | I8: =COUNTA(N8,Q8,T8,W8,Z8,AC8,AF8,AI8,AL8,AO8,AR8,AU8,AX8,BA8,BD8,BG8,BJ8,BM8,BP8,BS8,BV8,BY8,CB8,CE8,CH8,CK8,CN8,CQ8,CT8,CW8,CZ8) -> 0 | J8: =COUNTIF(M8:DC8,"POSTO S. RITA") -> 0 | K8: =COUNTIF(N8:DD8,"POSTO VIP") -> 0 | L8: Abril
D9: - | G9: =F9-E9 -> 0 | H9: =SUM(M9+P9+S9+V9+Y9+AB9+AE9+AH9+AK9+AN9+AQ9+AT9+AW9+AZ9+BC9+BF9+BI9+BL9+BO9+BR9+BU9+BX9+CA9+CD9+CG9+CJ9+CM9+CP9+CS9+CV9+CY9) -> 0 | I9: =COUNTA(N9,Q9,T9,W9,Z9,AC9,AF9,AI9,AL9,AO9,AR9,AU9,AX9,BA9,BD9,BG9,BJ9,BM9,BP9,BS9,BV9,BY9,CB9,CE9,CH9,CK9,CN9,CQ9,CT9,CW9,CZ9) -> 0 | J9: =COUNTIF(M9:DC9,"POSTO S. RITA") -> 0 | K9: =COUNTIF(N9:DD9,"POSTO VIP") -> 0 | L9: Abril
D10: - | G10: =F10-E10 -> 0 | H10: =SUM(M10+P10+S10+V10+Y10+AB10+AE10+AH10+AK10+AN10+AQ10+AT10+AW10+AZ10+BC10+BF10+BI10+BL10+BO10+BR10+BU10+BX10+CA10+CD10+CG10+CJ10+CM10+CP10+CS10+CV10+CY10) -> 0 | I10: =COUNTA(N10,Q10,T10,W10,Z10,AC10,AF10,AI10,AL10,AO10,AR10,AU10,AX10,BA10,BD10,BG10,BJ10,BM10,BP10,BS10,BV10,BY10,CB10,CE10,CH10,CK10,CN10,CQ10,CT10,CW10,CZ10) -> 0 | J10: =COUNTIF(M10:DC10,"POSTO S. RITA") -> 0 | K10: =COUNTIF(N10:DD10,"POSTO VIP") -> 0 | L10: Maio
D11: - | G11: =F11-E11 -> 0 | H11: =SUM(M11+P11+S11+V11+Y11+AB11+AE11+AH11+AK11+AN11+AQ11+AT11+AW11+AZ11+BC11+BF11+BI11+BL11+BO11+BR11+BU11+BX11+CA11+CD11+CG11+CJ11+CM11+CP11+CS11+CV11+CY11) -> 0 | I11: =COUNTA(N11,Q11,T11,W11,Z11,AC11,AF11,AI11,AL11,AO11,AR11,AU11,AX11,BA11,BD11,BG11,BJ11,BM11,BP11,BS11,BV11,BY11,CB11,CE11,CH11,CK11,CN11,CQ11,CT11,CW11,CZ11) -> 0 | J11: =COUNTIF(M11:DC11,"POSTO S. RITA") -> 0 | K11: =COUNTIF(N11:DD11,"POSTO VIP") -> 0 | L11: Maio
